Workbook

Sheet Curso Classif Desp.
A3: Orçamento Doméstico
D5: 43101 | F5: 43132 | H5: 43160 | J5: 43191 | L5: 43221 | N5: 43252 | P5: 43282 | R5: 43313 | T5: 43344 | V5: 43374 | X5: 43405 | Z5: 43435
A6: Receitas | C6: Descrição | D6: Orçado | E6: Realizado | F6: Orçado | G6: Realizado | H6: Orçado | I6: Realizado | J6: Orçado | K6: Realizado | L6: Orçado | M6: Realizado | N6: Orçado | O6: Realizado | P6: Orçado | Q6: Realizado | R6: Orçado | S6: Realizado | T6: Orçado | U6: Realizado | V6: Orçado | W6: Realizado | X6: Orçado | Y6: Realizado | Z6: Orçado | AA6: Realizado
C7: Salário | D7: 4000 | E7: 4000 | F7: 4000 | H7: 4000 | J7: 4000 | N7: 4000 | P7: 4000 | R7: 4000 | T7: 4000 | V7: 4000 | X7: 4000 | Z7: 4000
C8: Outros | D8: 0 | E8: 0 | F8: 0 | H8: 0 | J8: 0 | N8: 0 | P8: 0 | R8: 0 | T8: 0 | V8: 0 | X8: 0 | Z8: 0
C9: Horas extras | D9: 0 | E9: 100 | F9: 0 | H9: 0 | J9: 0 | N9: 0 | P9: 0 | R9: 0 | T9: 0 | V9: 0 | X9: 0 | Z9: 0
C10: 13º salário | D10: 0 | E10: 0 | F10: 0 | H10: 0 | J10: 0 | N10: 0 | P10: 0 | R10: 0 | T10: 0 | V10: 0 | X10: 0 | Z10: 0
C11: Férias | D11: 0 | E11: 0 | F11: 0 | H11: 0 | J11: 0 | N11: 0 | P11: 0 | R11: 0 | T11: 0 | V11: 0 | X11: 0 | Z11: 0
C12: Renda Extra | D12: 0 | E12: 0 | F12: 0 | H12: 0 | J12: 0 | L12: 0 | N12: 0 | P12: 0 | R12: 0 | T12: 0 | V12: 0 | X12: 0 | Z12: 0
C13: Total | D13: =SUM(D7:D12) -> 4000 | E13: =SUM(E7:E12) -> 4100 | F13: =SUM(F7:F12) -> 4000 | G13: =SUM(G7:G12) -> 0 | H13: =SUM(H7:H12) -> 4000 | I13: =SUM(I7:I12) -> 0 | J13: =SUM(J7:J12) -> 4000 | K13: =SUM(K7:K12) -> 0 | ... AA13: =SUM(AA7:AA12) -> 0
A15: Investimentos Insira aqui o montante mensal que você destinará aos seus investimentos | C15: Descrição | D15: Orçado | E15: Realizado | F15: Orçado | G15: Realizado | H15: Orçado | I15: Realizado | J15: Orçado | K15: Realizado | L15: Orçado | M15: Realizado | N15: Orçado | O15: Realizado | P15: Orçado | Q15: Realizado | R15: Orçado | S15: Realizado | T15: Orçado | U15: Realizado | V15: Orçado | W15: Realizado | X15: Orçado | Y15: Realizado | Z15: Orçado | AA15: Realizado
C16: Reserva de Emergência | D16: =D7*10% -> 400 | E16: =E13*10% -> 410 | F16: =F7*10% -> 400 | H16: =H7*10% -> 400 | J16: =J7*10% -> 400 | L16: =L7*10% -> 0 | N16: =N7*10% -> 400 | P16: =P7*10% -> 400 | R16: =R7*10% -> 400 | T16: =T7*10% -> 400 | V16: =V7*10% -> 400 | X16: =X7*10% -> 400 | Z16: =Z7*10% -> 400
C17: Plano de Aposentadoria | D17: 0 | E17: 0 | F17: 0 | H17: 0 | J17: 0 | L17: 0 | N17: 0 | P17: 0 | R17: 0 | T17: 0 | V17: 0 | X17: 0 | Z17: 0
C18: Independencia | D18: 0 | E18: 0 | F18: 0 | H18: 0 | J18: 0 | L18: 0 | N18: 0 | P18: 0 | R18: 0 | T18: 0 | V18: 0 | X18: 0 | Z18: 0
C19: Ações | D19: 0 | E19: 0 | F19: 0 | H19: 0 | J19: 0 | L19: 0 | N19: 0 | P19: 0 | R19: 0 | T19: 0 | V19: 0 | X19: 0 | Z19: 0
C20: Outros | D20: 0 | E20: 0 | F20: 0 | H20: 0 | J20: 0 | L20: 0 | N20: 0 | P20: 0 | R20: 0 | T20: 0 | V20: 0 | X20: 0 | Z20: 0
C22: Total | D22: =SUM(D16:D21) -> 400 | E22: =SUM(E16:E21) -> 410 | F22: =SUM(F16:F21) -> 400 | G22: =SUM(G16:G21) -> 0 | H22: =SUM(H16:H21) -> 400 | I22: =SUM(I16:I21) -> 0 | J22: =SUM(J16:J21) -> 400 | K22: =SUM(K16:K21) -> 0 | ... AA22: =SUM(AA16:AA21) -> 0
C23: % sobre Receita | D23: =D22/$D$13 -> 0.1 | E23: =E22/$D$13 -> 0.1025 | F23: =F22/$D$13 -> 0.1 | G23: =G22/$D$13 -> 0 | H23: =H22/$D$13 -> 0.1 | I23: =I22/$D$13 -> 0 | J23: =J22/$D$13 -> 0.1 | K23: =K22/$D$13 -> 0 | ... AA23: =AA22/$D$13 -> 0
A25: Categoria | C25: Despesa | D25: Orçado | E25: Realizado | F25: Orçado | G25: Realizado | H25: Orçado | I25: Realizado | J25: Orçado | K25: Realizado | L25: Orçado | M25: Realizado | N25: Orçado | O25: Realizado | P25: Orçado | Q25: Realizado | R25: Orçado | S25: Realizado | T25: Orçado | U25: Realizado | V25: Orçado | W25: Realizado | X25: Orçado | Y25: Realizado | Z25: Orçado | AA25: Realizado
A26: Fixas o mesmo montante mensalmente | B26: Habitação | C26: Prestação da casa | D26: 650 | E26: 650 | F26: 650 | H26: 650 | J26: 650 | N26: 650 | P26: 650 | R26: 650 | T26: 650 | V26: 650 | X26: 650 | Z26: 650
C27: Telefone | D27: 60 | E27: 50 | F27: 60 | H27: 60 | J27: 60 | N27: 60 | P27: 60 | R27: 60 | T27: 60 | V27: 60 | X27: 60 | Z27: 60
C28: Internet | D28: 80 | E28: 80 | F28: 80 | H28: 80 | J28: 80 | N28: 80 | P28: 80 | R28: 80 | T28: 80 | V28: 80 | X28: 80 | Z28: 80
D32: 80 | E32: 80 | F32: 80 | H32: 80 | J32: 80 | N32: 80 | P32: 80 | R32: 80 | T32: 80 | V32: 80 | X32: 80 | Z32: 80
B34: Transporte | C34: Prestação do carro | D34: 0 | E34: 0 | F34: 0 | H34: 0 | J34: 0 | N34: 0 | P34: 0 | R34: 0 | T34: 0 | V34: 0 | X34: 0 | Z34: 0
C35: Seguro do carro | D35: 60 | E35: 60 | F35: 60 | H35: 60 | J35: 60 | N35: 60 | P35: 60 | R35: 60 | T35: 60 | V35: 60 | X35: 60 | Z35: 60
B37: Saúde | C37: Academia | D37: 100 | E37: 100 | F37: 100 | H37: 100 | J37: 100 | N37: 100 | P37: 100 | R37: 100 | T37: 100 | V37: 100 | X37: 100 | Z37: 100
C38: Seguro de vida
C39: Plano de saúde
D41: 100 | E41: 100 | F41: 100 | H41: 100 | J41: 100 | N41: 100 | P41: 100 | R41: 100 | T41: 100 | V41: 100 | X41: 100 | Z41: 100
B43: Educação | C43: Livros | D43: 0 | E43: 0 | F43: 0 | H43: 0 | J43: 0 | N43: 0 | P43: 0 | R43: 0 | T43: 0 | V43: 0 | X43: 0 | Z43: 0
C44: Faculdade | D44: 0 | E44: 0 | F44: 0 | H44: 0 | J44: 0 | N44: 0 | P44: 0 | R44: 0 | T44: 0 | V44: 0 | X44: 0 | Z44: 0
D46: 0 | E46: 0 | F46: 0 | H46: 0 | J46: 0 | N46: 0 | P46: 0 | R46: 0 | T46: 0 | V46: 0 | X46: 0 | Z46: 0
B48: Impostos | C48: IPTU | D48: 50 | E48: 50 | F48: 50 | H48: 50 | J48: 50 | N48: 50 | P48: 50 | R48: 50 | T48: 50 | V48: 50 | X48: 50 | Z48: 50
C49: IPVA | D49: 0 | E49: 0 | F49: 0 | H49: 0 | J49: 0 | N49: 0 | P49: 0 | R49: 0 | T49: 0 | V49: 0 | X49: 0 | Z49: 0
D51: 0 | E51: 0 | F51: 0 | H51: 0 | J51: 0 | N51: 0 | P51: 0 | R51: 0 | T51: 0 | V51: 0 | X51: 0 | Z51: 0
B53: Espiritual | C53: Dízimo | D53: =$D$13*10% -> 400 | E53: 400 | F53: =$D$13*10% -> 400 | H53: =$D$13*10% -> 400 | J53: =$D$13*10% -> 400 | N53: =$D$13*10% -> 400 | P53: =$D$13*10% -> 400 | R53: =$D$13*10% -> 400 | T53: =$D$13*10% -> 400 | V53: =$D$13*10% -> 400 | X53: =$D$13*10% -> 400 | Z53: =$D$13*10% -> 400
C54: Ofertas | E54: 80
E55: 80
B57: Total despesas fixas | D57: =SUM(D26:D55) -> 1580 | E57: =SUM(E26:E55) -> 1730 | F57: =SUM(F26:F55) -> 1580 | G57: =SUM(G26:G55) -> 0 | H57: =SUM(H26:H55) -> 1580 | I57: =SUM(I26:I55) -> 0 | J57: =SUM(J26:J55) -> 1580 | K57: =SUM(K26:K55) -> 0 | ... AA57: =SUM(AA26:AA55) -> 0
B59: % sobre Receita | D59: =D57/$D$13 -> 0.395 | E59: =E57/$D$13 -> 0.4325 | F59: =F57/$D$13 -> 0.395 | G59: =G57/$D$13 -> 0 | H59: =H57/$D$13 -> 0.395 | I59: =I57/$D$13 -> 0 | J59: =J57/$D$13 -> 0.395 | K59: =K57/$D$13 -> 0 | N59: =N57/$D$13 -> 0.395 | O59: =O57/$D$13 -> 0 | P59: =P57/$D$13 -> 0.395 | Q59: =Q57/$D$13 -> 0 | R59: =R57/$D$13 -> 0.395 | S59: =S57/$D$13 -> 0 | T59: =T57/$D$13 -> 0.395 | U59: =U57/$D$13 -> 0 | ... AA59: =AA57/$D$13 -> 0
A61: Variáveis aquelas que acontecem mensalmente, mas podemos tentar reduzir | B61: Moradia | C61: Luz | D61: 180 | E61: 150 | F61: 180 | H61: 180 | J61: 180 | N61: 180 | P61: 180 | R61: 180 | T61: 180 | V61: 180 | X61: 180 | Z61: 180
C62: Água | D62: 60 | E62: 50 | F62: 60 | H62: 60 | J62: 60 | N62: 60 | P62: 60 | R62: 60 | T62: 60 | V62: 60 | X62: 60 | Z62: 60
C63: Telefone Celular | D63: 50 | E63: 35 | F63: 50 | H63: 50 | J63: 50 | N63: 50 | P63: 50 | R63: 50 | T63: 50 | V63: 50 | X63: 50 | Z63: 50
C64: Gás | D64: 0 | E64: 0 | F64: 0 | H64: 0 | J64: 0 | N64: 0 | P64: 0 | R64: 0 | T64: 0 | V64: 0 | X64: 0 | Z64: 0
C65: Seguro | D65: 0 | E65: 0 | F65: 0 | H65: 0 | J65: 0 | N65: 0 | P65: 0 | R65: 0 | T65: 0 | V65: 0 | X65: 0 | Z65: 0
D67: 0 | E67: 0 | F67: 0 | H67: 0 | J67: 0 | N67: 0 | P67: 0 | R67: 0 | T67: 0 | V67: 0 | X67: 0 | Z67: 0
B69: Transporte | C69: Ônibus | D69: 0 | E69: 60 | F69: 0 | H69: 0 | J69: 0 | N69: 0 | P69: 0 | R69: 0 | T69: 0 | V69: 0 | X69: 0 | Z69: 0
C70: Combustível | D70: 250 | E70: 100 | F70: 250 | H70: 250 | J70: 250 | N70: 250 | P70: 250 | R70: 250 | T70: 250 | V70: 250 | X70: 250 | Z70: 250
D71: 250 | E71: 100 | F71: 250 | H71: 250 | J71: 250 | N71: 250 | P71: 250 | R71: 250 | T71: 250 | V71: 250 | X71: 250 | Z71: 250
B73: Alimentação | C73: Supermercado | D73: 650 | E73: 680 | F73: 650 | H73: 650 | J73: 650 | N73: 650 | P73: 650 | R73: 650 | T73: 650 | V73: 650 | X73: 650 | Z73: 650
C74: Casa de carne | D74: 100 | E74: 120 | F74: 100 | H74: 100 | J74: 100 | N74: 100 | P74: 100 | R74: 100 | T74: 100 | V74: 100 | X74: 100 | Z74: 100
C75: Padaria | D75: 0 | F75: 0 | H75: 0 | J75: 0 | N75: 0 | P75: 0 | R75: 0 | T75: 0 | V75: 0 | X75: 0 | Z75: 0
C76: Feira
D77: 0 | F77: 0 | H77: 0 | J77: 0 | N77: 0 | P77: 0 | R77: 0 | T77: 0 | V77: 0 | X77: 0 | Z77: 0
D78: 0 | F78: 0 | H78: 0 | J78: 0 | N78: 0 | P78: 0 | R78: 0 | T78: 0 | V78: 0 | X78: 0 | Z78: 0
B80: Saúde | C80: Medicamentos | D80: 150 | E80: 180 | F80: 150 | H80: 150 | J80: 150 | N80: 150 | P80: 150 | R80: 150 | T80: 150 | V80: 150 | X80: 150 | Z80: 150
D81: 150 | E81: 180 | F81: 150 | H81: 150 | J81: 150 | N81: 150 | P81: 150 | R81: 150 | T81: 150 | V81: 150 | X81: 150 | Z81: 150
B83: Cuidados pessoais | C83: Cabeleireiro | D83: 40 | E83: 0 | F83: 40 | H83: 40 | J83: 40 | N83: 40 | P83: 40 | R83: 40 | T83: 40 | V83: 40 | X83: 40 | Z83: 40
C84: Manicure | D84: 50 | E84: 25 | F84: 50 | H84: 50 | J84: 50 | N84: 50 | P84: 50 | R84: 50 | T84: 50 | V84: 50 | X84: 50 | Z84: 50
C85: Perfumaria | D85: 50 | E85: 30 | F85: 50 | H85: 50 | J85: 50 | N85: 50 | P85: 50 | R85: 50 | T85: 50 | V85: 50 | X85: 50 | Z85: 50
B89: Despesas Financeiras | C89: Tarifas bancarias | D89: 20 | E89: 20 | F89: 20 | H89: 20 | J89: 20 | N89: 20 | P89: 20 | R89: 20 | T89: 20 | V89: 20 | X89: 20 | Z89: 20
B91: Total despesas variáveis | D91: =SUM(D61:D89) -> 2000 | E91: =SUM(E61:E89) -> 1730 | F91: =SUM(F61:F89) -> 2000 | G91: =SUM(G61:G89) -> 0 | H91: =SUM(H61:H89) -> 2000 | I91: =SUM(I61:I89) -> 0 | J91: =SUM(J61:J89) -> 2000 | K91: =SUM(K61:K89) -> 0 | ... AA91: =SUM(AA61:AA89) -> 0
B93: % sobre Receita | D93: =D91/$D$13 -> 0.5 | E93: =E91/$D$13 -> 0.4325 | F93: =F91/$D$13 -> 0.5 | G93: =G91/$D$13 -> 0 | H93: =H91/$D$13 -> 0.5 | I93: =I91/$D$13 -> 0 | J93: =J91/$D$13 -> 0.5 | K93: =K91/$D$13 -> 0 | N93: =N91/$D$13 -> 0.5 | O93: =O91/$D$13 -> 0 | P93: =P91/$D$13 -> 0.5 | Q93: =Q91/$D$13 -> 0 | R93: =R91/$D$13 -> 0.5 | S93: =S91/$D$13 -> 0 | T93: =T91/$D$13 -> 0.5 | U93: =U91/$D$13 -> 0 | ... AA93: =AA91/$D$13 -> 0
A95: Extras são as despesas as quais precisamos estar preparados para quando acontecerem | B95: Saúde | C95: Médico | D95: 0 | E95: 150 | F95: 0 | H95: 0 | J95: 0 | N95: 0 | P95: 0 | R95: 0 | T95: 0 | V95: 0 | X95: 0 | Z95: 0
C96: Dentista | D96: 0 | E96: 0 | F96: 0 | H96: 0 | J96: 0 | N96: 0 | P96: 0 | R96: 0 | T96: 0 | V96: 0 | X96: 0 | Z96: 0
D97: 0 | E97: 0 | F97: 0 | H97: 0 | J97: 0 | N97: 0 | P97: 0 | R97: 0 | T97: 0 | V97: 0 | X97: 0 | Z97: 0
B99: Manutenção/ prevenção | C99: Veículo | D99: 60 | E99: 80 | F99: 60 | H99: 60 | J99: 60 | N99: 60 | P99: 60 | R99: 60 | T99: 60 | V99: 60 | X99: 60 | Z99: 60
C100: Residência | D100: 20 | E100: 0 | F100: 20 | H100: 20 | J100: 20 | N100: 20 | P100: 20 | R100: 20 | T100: 20 | V100: 20 | X100: 20 | Z100: 20
B102: Educação | C102: Material escolar | D102: 0 | E102: 0 | F102: 0 | H102: 0 | J102: 0 | N102: 0 | P102: 0 | R102: 0 | T102: 0 | V102: 0 | X102: 0 | Z102: 0
C103: Uniforme
D104: 0 | E104: 0 | F104: 0 | H104: 0 | J104: 0 | N104: 0 | P104: 0 | R104: 0 | T104: 0 | V104: 0 | X104: 0 | Z104: 0
B106: Total despesas extras | D106: =SUM(D95:D104) -> 80 | E106: =SUM(E95:E104) -> 230 | F106: =SUM(F95:F104) -> 80 | G106: =SUM(G95:G104) -> 0 | H106: =SUM(H95:H104) -> 80 | I106: =SUM(I95:I104) -> 0 | J106: =SUM(J95:J104) -> 80 | K106: =SUM(K95:K104) -> 0 | ... AA106: =SUM(AA95:AA104) -> 0
B108: % sobre Receita | D108: =D106/$D$13 -> 0.02 | E108: =E106/$D$13 -> 0.0575 | F108: =F106/$D$13 -> 0.02 | G108: =G106/$D$13 -> 0 | H108: =H106/$D$13 -> 0.02 | I108: =I106/$D$13 -> 0 | J108: =J106/$D$13 -> 0.02 | K108: =K106/$D$13 -> 0 | N108: =N106/$D$13 -> 0.02 | O108: =O106/$D$13 -> 0 | P108: =P106/$D$13 -> 0.02 | Q108: =Q106/$D$13 -> 0 | R108: =R106/$D$13 -> 0.02 | S108: =S106/$D$13 -> 0 | T108: =T106/$D$13 -> 0.02 | U108: =U106/$D$13 -> 0 | ... AA108: =AA106/$D$13 -> 0
A110: Adicionais aquelas que não precisam, necessariamente, acontecer | B110: Lazer | C110: Cinema/teatro/parque | D110: 0 | E110: 0 | F110: 0 | G110: 0 | H110: 0 | I110: 0 | J110: 0 | K110: 0 | N110: 0 | O110: 0 | P110: 0 | Q110: 0 | R110: 0 | S110: 0 | T110: 0 | U110: 0 | V110: 0 | W110: 0 | X110: 0 | Y110: 0 | Z110: 0 | AA110: 0
C111: Restaurantes/bares | D111: 150 | E111: 100 | F111: 150 | H111: 150 | J111: 150 | N111: 150 | P111: 150 | R111: 150 | T111: 150 | V111: 150 | X111: 150 | Z111: 150
B115: Vestuário | C115: Roupas | D115: 130 | E115: 130 | F115: 130 | H115: 130 | J115: 130 | N115: 130 | P115: 130 | R115: 130 | T115: 130 | V115: 130 | X115: 130 | Z115: 130
C116: Calçados | D116: 60 | E116: 80 | F116: 60 | H116: 60 | J116: 60 | N116: 60 | P116: 60 | R116: 60 | T116: 60 | V116: 60 | X116: 60 | Z116: 60
C117: Acessórios | D117: 0 | E117: 0 | F117: 0 | H117: 0 | J117: 0 | N117: 0 | P117: 0 | R117: 0 | T117: 0 | V117: 0 | X117: 0 | Z117: 0
D119: 0 | E119: 0 | F119: 0 | H119: 0 | J119: 0 | N119: 0 | P119: 0 | R119: 0 | T119: 0 | V119: 0 | X119: 0 | Z119: 0
B121: Outros | C121: Presentes | D121: 100 | E121: 110 | F121: 100 | H121: 100 | J121: 100 | N121: 100 | P121: 100 | R121: 100 | T121: 100 | V121: 100 | X121: 100 | Z121: 100
D123: 0 | E123: 0 | F123: 0 | H123: 0 | J123: 0 | N123: 0 | P123: 0 | R123: 0 | T123: 0 | V123: 0 | X123: 0 | Z123: 0
B125: Total despesas adicionais | D125: =SUM(D110:D123) -> 440 | E125: =SUM(E110:E123) -> 420 | F125: =SUM(F110:F123) -> 440 | G125: =SUM(G110:G123) -> 0 | H125: =SUM(H110:H123) -> 440 | I125: =SUM(I110:I123) -> 0 | J125: =SUM(J110:J123) -> 440 | K125: =SUM(K110:K123) -> 0 | ... AA125: =SUM(AA110:AA123) -> 0
B127: % sobre Receita | D127: =D125/$D$13 -> 0.11 | E127: =E125/$D$13 -> 0.105 | F127: =F125/$D$13 -> 0.11 | G127: =G125/$D$13 -> 0 | H127: =H125/$D$13 -> 0.11 | I127: =I125/$D$13 -> 0 | J127: =J125/$D$13 -> 0.11 | K127: =K125/$D$13 -> 0 | N127: =N125/$D$13 -> 0.11 | O127: =O125/$D$13 -> 0 | P127: =P125/$D$13 -> 0.11 | Q127: =Q125/$D$13 -> 0 | R127: =R125/$D$13 -> 0.11 | S127: =S125/$D$13 -> 0 | T127: =T125/$D$13 -> 0.11 | U127: =U125/$D$13 -> 0 | ... AA127: =AA125/$D$13 -> 0
A129: Total despesas
A131: Resumo Geral | C131: Descrição | D131: Orçado | E131: Realizado | F131: Orçado | G131: Realizado | H131: Orçado | I131: Realizado | J131: Orçado | K131: Realizado | L131: Orçado | M131: Realizado | N131: Orçado | O131: Realizado | P131: Orçado | Q131: Realizado | R131: Orçado | S131: Realizado | T131: Orçado | U131: Realizado | V131: Orçado | W131: Realizado | X131: Orçado | Y131: Realizado | Z131: Orçado | AA131: Realizado
C132: Saldo Anterior | D132: 0 | E132: 0 | F132: =E139 -> -420 | G132: =E139 -> -420 | H132: =G139 -> -420 | J132: =I139 -> 0 | N132: =M139 -> 0 | P132: =O139 -> 0 | R132: =Q139 -> 0 | T132: =S139 -> 0 | V132: =U139 -> 0 | X132: =W139 -> 0 | Z132: =Y139 -> 0
C133: Receita | D133: =D13 -> 4000 | E133: =E13 -> 4100 | F133: =F13 -> 4000 | G133: =G13 -> 0 | H133: =H13 -> 4000 | I133: =I13 -> 0 | J133: =J13 -> 4000 | K133: =K13 -> 0 | M133: =M13 -> 0 | N133: =N13 -> 4000 | O133: =O13 -> 0 | P133: =P13 -> 4000 | Q133: =Q13 -> 0 | R133: =R13 -> 4000 | S133: =S13 -> 0 | T133: =T13 -> 4000 | ... AA133: =AA13 -> 0
C134: Investimentos | D134: =D22 -> 400 | E134: =E22 -> 410 | F134: =F22 -> 400 | G134: =G22 -> 0 | H134: =H22 -> 400 | I134: =I22 -> 0 | J134: =J22 -> 400 | K134: =K22 -> 0 | M134: =M22 -> 0 | N134: =N22 -> 400 | O134: =O22 -> 0 | P134: =P22 -> 400 | Q134: =Q22 -> 0 | R134: =R22 -> 400 | S134: =S22 -> 0 | T134: =T22 -> 400 | ... AA134: =AA22 -> 0
C135: Despesas fixas | D135: =D57 -> 1580 | E135: =E57 -> 1730 | F135: =F57 -> 1580 | G135: =G57 -> 0 | H135: =H57 -> 1580 | I135: =I57 -> 0 | J135: =J57 -> 1580 | K135: =K57 -> 0 | M135: =M57 -> 0 | N135: =N57 -> 1580 | O135: =O57 -> 0 | P135: =P57 -> 1580 | Q135: =Q57 -> 0 | R135: =R57 -> 1580 | S135: =S57 -> 0 | T135: =T57 -> 1580 | ... AA135: =AA57 -> 0
C136: Despesas variáveis | D136: =D91 -> 2000 | E136: =E91 -> 1730 | F136: =F91 -> 2000 | G136: =G91 -> 0 | H136: =H91 -> 2000 | I136: =I91 -> 0 | J136: =J91 -> 2000 | K136: =K91 -> 0 | M136: =M91 -> 0 | N136: =N91 -> 2000 | O136: =O91 -> 0 | P136: =P91 -> 2000 | Q136: =Q91 -> 0 | R136: =R91 -> 2000 | S136: =S91 -> 0 | T136: =T91 -> 2000 | ... AA136: =AA91 -> 0
C137: Despesas extras | D137: =D106 -> 80 | E137: =E106 -> 230 | F137: =F106 -> 80 | G137: =G106 -> 0 | H137: =H106 -> 80 | I137: =I106 -> 0 | J137: =J106 -> 80 | K137: =K106 -> 0 | M137: =M106 -> 0 | N137: =N106 -> 80 | O137: =O106 -> 0 | P137: =P106 -> 80 | Q137: =Q106 -> 0 | R137: =R106 -> 80 | S137: =S106 -> 0 | T137: =T106 -> 80 | ... AA137: =AA106 -> 0
C138: Despesas adicionais | D138: =D125 -> 440 | E138: =E125 -> 420 | F138: =F125 -> 440 | G138: =G125 -> 0 | H138: =H125 -> 440 | I138: =I125 -> 0 | J138: =J125 -> 440 | K138: =K125 -> 0 | M138: =M125 -> 0 | N138: =N125 -> 440 | O138: =O125 -> 0 | P138: =P125 -> 440 | Q138: =Q125 -> 0 | R138: =R125 -> 440 | S138: =S125 -> 0 | T138: =T125 -> 440 | ... AA138: =AA125 -> 0
C139: Saldo Atual | D139: =D132+D133-SUM(D134:D138) -> -500 | E139: =E132+E133-SUM(E134:E138) -> -420 | F139: =F132+F133-SUM(F134:F138) -> -920 | G139: =G132+G133-SUM(G134:G138) -> -420 | H139: =H132+H133-SUM(H134:H138) -> -920 | I139: =I132+I133-SUM(I134:I138) -> 0 | J139: =J132+J133-SUM(J134:J138) -> -500 | K139: =K132+K133-SUM(K134:K138) -> 0 | ... AA139: =AA132+AA133-SUM(AA134:AA138) -> 0

Sheet Mod. Controle de Gastos
A3: Controle de Gastos
D5: 43101 | F5: 43132 | H5: 43160 | J5: 43191 | L5: 43221 | N5: 43252 | P5: 43282 | R5: 43313 | T5: 43344 | V5: 43374 | X5: 43405 | Z5: 43435
A6: Receitas | C6: Descrição | D6: Orçado | E6: Realizado | F6: Orçado | G6: Realizado | H6: Orçado | I6: Realizado | J6: Orçado | K6: Realizado | L6: Orçado | M6: Realizado | N6: Orçado | O6: Realizado | P6: Orçado | Q6: Realizado | R6: Orçado | S6: Realizado | T6: Orçado | U6: Realizado | V6: Orçado | W6: Realizado | X6: Orçado | Y6: Realizado | Z6: Orçado | AA6: Realizado
C7: Salário | D7: 4000 | E7: 4000 | F7: 4000 | H7: 4000 | J7: 4000 | N7: 4000 | P7: 4000 | R7: 4000 | T7: 4000 | V7: 4000 | X7: 4000 | Z7: 4000
C8: Outros | D8: 0 | E8: 0 | F8: 0 | H8: 0 | J8: 0 | N8: 0 | P8: 0 | R8: 0 | T8: 0 | V8: 0 | X8: 0 | Z8: 0
C9: Horas extras | D9: 0 | E9: 100 | F9: 0 | H9: 0 | J9: 0 | N9: 0 | P9: 0 | R9: 0 | T9: 0 | V9: 0 | X9: 0 | Z9: 0
C10: 13º salário | D10: 0 | E10: 0 | F10: 0 | H10: 0 | J10: 0 | N10: 0 | P10: 0 | R10: 0 | T10: 0 | V10: 0 | X10: 0 | Z10: 0
C11: Férias | D11: 0 | E11: 0 | F11: 0 | H11: 0 | J11: 0 | N11: 0 | P11: 0 | R11: 0 | T11: 0 | V11: 0 | X11: 0 | Z11: 0
C12: Renda Extra | D12: 0 | E12: 0 | F12: 0 | H12: 0 | J12: 0 | L12: 0 | N12: 0 | P12: 0 | R12: 0 | T12: 0 | V12: 0 | X12: 0 | Z12: 0
C13: Total | D13: =SUM(D7:D12) -> 4000 | E13: =SUM(E7:E12) -> 4100 | F13: =SUM(F7:F12) -> 4000 | G13: =SUM(G7:G12) -> 0 | H13: =SUM(H7:H12) -> 4000 | I13: =SUM(I7:I12) -> 0 | J13: =SUM(J7:J12) -> 4000 | K13: =SUM(K7:K12) -> 0 | ... AA13: =SUM(AA7:AA12) -> 0
A15: Investimentos Insira aqui o montante mensal que você destinará aos seus investimentos | C15: Descrição | D15: Orçado | E15: Realizado | F15: Orçado | G15: Realizado | H15: Orçado | I15: Realizado | J15: Orçado | K15: Realizado | L15: Orçado | M15: Realizado | N15: Orçado | O15: Realizado | P15: Orçado | Q15: Realizado | R15: Orçado | S15: Realizado | T15: Orçado | U15: Realizado | V15: Orçado | W15: Realizado | X15: Orçado | Y15: Realizado | Z15: Orçado | AA15: Realizado
C16: Reserva de Emergência | D16: =D7*10% -> 400 | E16: =E13*10% -> 410 | F16: =F7*10% -> 400 | H16: =H7*10% -> 400 | J16: =J7*10% -> 400 | L16: =L7*10% -> 0 | N16: =N7*10% -> 400 | P16: =P7*10% -> 400 | R16: =R7*10% -> 400 | T16: =T7*10% -> 400 | V16: =V7*10% -> 400 | X16: =X7*10% -> 400 | Z16: =Z7*10% -> 400
C17: Plano de Aposentadoria | D17: 0 | E17: 0 | F17: 0 | H17: 0 | J17: 0 | L17: 0 | N17: 0 | P17: 0 | R17: 0 | T17: 0 | V17: 0 | X17: 0 | Z17: 0
C18: Independencia | D18: 0 | E18: 0 | F18: 0 | H18: 0 | J18: 0 | L18: 0 | N18: 0 | P18: 0 | R18: 0 | T18: 0 | V18: 0 | X18: 0 | Z18: 0
C19: Ações | D19: 0 | E19: 0 | F19: 0 | H19: 0 | J19: 0 | L19: 0 | N19: 0 | P19: 0 | R19: 0 | T19: 0 | V19: 0 | X19: 0 | Z19: 0
C20: Outros | D20: 0 | E20: 0 | F20: 0 | H20: 0 | J20: 0 | L20: 0 | N20: 0 | P20: 0 | R20: 0 | T20: 0 | V20: 0 | X20: 0 | Z20: 0
C22: Total | D22: =SUM(D16:D21) -> 400 | E22: =SUM(E16:E21) -> 410 | F22: =SUM(F16:F21) -> 400 | G22: =SUM(G16:G21) -> 0 | H22: =SUM(H16:H21) -> 400 | I22: =SUM(I16:I21) -> 0 | J22: =SUM(J16:J21) -> 400 | K22: =SUM(K16:K21) -> 0 | ... AA22: =SUM(AA16:AA21) -> 0
C23: % sobre Receita | D23: =D22/$D$13 -> 0.1 | E23: =E22/$D$13 -> 0.1025 | F23: =F22/$D$13 -> 0.1 | G23: =G22/$D$13 -> 0 | H23: =H22/$D$13 -> 0.1 | I23: =I22/$D$13 -> 0 | J23: =J22/$D$13 -> 0.1 | K23: =K22/$D$13 -> 0 | ... AA23: =AA22/$D$13 -> 0
A25: Categoria | C25: Despesa | D25: Orçado | E25: Realizado | F25: Orçado | G25: Realizado | H25: Orçado | I25: Realizado | J25: Orçado | K25: Realizado | L25: Orçado | M25: Realizado | N25: Orçado | O25: Realizado | P25: Orçado | Q25: Realizado | R25: Orçado | S25: Realizado | T25: Orçado | U25: Realizado | V25: Orçado | W25: Realizado | X25: Orçado | Y25: Realizado | Z25: Orçado | AA25: Realizado
A26: Fixas o mesmo montante mensalmente | B26: Habitação | C26: Prestação / Aluguel | D26: 650 | E26: 650 | F26: 650 | H26: 650 | J26: 650 | N26: 650 | P26: 650 | R26: 650 | T26: 650 | V26: 650 | X26: 650 | Z26: 650
C27: Telefone | D27: 60 | E27: 50 | F27: 60 | H27: 60 | J27: 60 | N27: 60 | P27: 60 | R27: 60 | T27: 60 | V27: 60 | X27: 60 | Z27: 60
C28: Internet | D28: 80 | E28: 80 | F28: 80 | H28: 80 | J28: 80 | N28: 80 | P28: 80 | R28: 80 | T28: 80 | V28: 80 | X28: 80 | Z28: 80
D32: 80 | E32: 80 | F32: 80 | H32: 80 | J32: 80 | N32: 80 | P32: 80 | R32: 80 | T32: 80 | V32: 80 | X32: 80 | Z32: 80
B34: Transporte | C34: Prestação do carro | D34: 0 | E34: 0 | F34: 0 | H34: 0 | J34: 0 | N34: 0 | P34: 0 | R34: 0 | T34: 0 | V34: 0 | X34: 0 | Z34: 0
C35: Seguro do carro | D35: 60 | E35: 60 | F35: 60 | H35: 60 | J35: 60 | N35: 60 | P35: 60 | R35: 60 | T35: 60 | V35: 60 | X35: 60 | Z35: 60
B37: Saúde | C37: Academia | D37: 100 | E37: 100 | F37: 100 | H37: 100 | J37: 100 | N37: 100 | P37: 100 | R37: 100 | T37: 100 | V37: 100 | X37: 100 | Z37: 100
C38: Seguro de vida
C39: Plano de saúde
D41: 100 | E41: 100 | F41: 100 | H41: 100 | J41: 100 | N41: 100 | P41: 100 | R41: 100 | T41: 100 | V41: 100 | X41: 100 | Z41: 100
B43: Educação | C43: Livros | D43: 0 | E43: 0 | F43: 0 | H43: 0 | J43: 0 | N43: 0 | P43: 0 | R43: 0 | T43: 0 | V43: 0 | X43: 0 | Z43: 0
C44: Faculdade | D44: 0 | E44: 0 | F44: 0 | H44: 0 | J44: 0 | N44: 0 | P44: 0 | R44: 0 | T44: 0 | V44: 0 | X44: 0 | Z44: 0
D46: 0 | E46: 0 | F46: 0 | H46: 0 | J46: 0 | N46: 0 | P46: 0 | R46: 0 | T46: 0 | V46: 0 | X46: 0 | Z46: 0
B48: Impostos | C48: IPTU | D48: 50 | E48: 50 | F48: 50 | H48: 50 | J48: 50 | N48: 50 | P48: 50 | R48: 50 | T48: 50 | V48: 50 | X48: 50 | Z48: 50
C49: IPVA | D49: 0 | E49: 0 | F49: 0 | H49: 0 | J49: 0 | N49: 0 | P49: 0 | R49: 0 | T49: 0 | V49: 0 | X49: 0 | Z49: 0
C50: INSS
C51: IRRF | D51: 0 | E51: 0 | F51: 0 | H51: 0 | J51: 0 | N51: 0 | P51: 0 | R51: 0 | T51: 0 | V51: 0 | X51: 0 | Z51: 0
B53: Espiritual | C53: Dízimo | D53: =$D$13*10% -> 400 | E53: 400 | F53: =$D$13*10% -> 400 | H53: =$D$13*10% -> 400 | J53: =$D$13*10% -> 400 | N53: =$D$13*10% -> 400 | P53: =$D$13*10% -> 400 | R53: =$D$13*10% -> 400 | T53: =$D$13*10% -> 400 | V53: =$D$13*10% -> 400 | X53: =$D$13*10% -> 400 | Z53: =$D$13*10% -> 400
C54: Ofertas | E54: 80
E55: 80
B57: Total despesas fixas | D57: =SUM(D26:D55) -> 1580 | E57: =SUM(E26:E55) -> 1730 | F57: =SUM(F26:F55) -> 1580 | G57: =SUM(G26:G55) -> 0 | H57: =SUM(H26:H55) -> 1580 | I57: =SUM(I26:I55) -> 0 | J57: =SUM(J26:J55) -> 1580 | K57: =SUM(K26:K55) -> 0 | ... AA57: =SUM(AA26:AA55) -> 0
B59: % sobre Receita | D59: =D57/$D$13 -> 0.395 | E59: =E57/$D$13 -> 0.4325 | F59: =F57/$D$13 -> 0.395 | G59: =G57/$D$13 -> 0 | H59: =H57/$D$13 -> 0.395 | I59: =I57/$D$13 -> 0 | J59: =J57/$D$13 -> 0.395 | K59: =K57/$D$13 -> 0 | N59: =N57/$D$13 -> 0.395 | O59: =O57/$D$13 -> 0 | P59: =P57/$D$13 -> 0.395 | Q59: =Q57/$D$13 -> 0 | R59: =R57/$D$13 -> 0.395 | S59: =S57/$D$13 -> 0 | T59: =T57/$D$13 -> 0.395 | U59: =U57/$D$13 -> 0 | ... AA59: =AA57/$D$13 -> 0
A61: Variáveis aquelas que acontecem mensalmente, mas podemos tentar reduzir | B61: Moradia | C61: Luz | D61: 180 | E61: 150 | F61: 180 | H61: 180 | J61: 180 | N61: 180 | P61: 180 | R61: 180 | T61: 180 | V61: 180 | X61: 180 | Z61: 180
C62: Água | D62: 60 | E62: 50 | F62: 60 | H62: 60 | J62: 60 | N62: 60 | P62: 60 | R62: 60 | T62: 60 | V62: 60 | X62: 60 | Z62: 60
C63: Telefone Celular | D63: 50 | E63: 35 | F63: 50 | H63: 50 | J63: 50 | N63: 50 | P63: 50 | R63: 50 | T63: 50 | V63: 50 | X63: 50 | Z63: 50
C64: Gás | D64: 0 | E64: 0 | F64: 0 | H64: 0 | J64: 0 | N64: 0 | P64: 0 | R64: 0 | T64: 0 | V64: 0 | X64: 0 | Z64: 0
C65: Seguro | D65: 0 | E65: 0 | F65: 0 | H65: 0 | J65: 0 | N65: 0 | P65: 0 | R65: 0 | T65: 0 | V65: 0 | X65: 0 | Z65: 0
D67: 0 | E67: 0 | F67: 0 | H67: 0 | J67: 0 | N67: 0 | P67: 0 | R67: 0 | T67: 0 | V67: 0 | X67: 0 | Z67: 0
B69: Transporte | C69: Ônibus | D69: 0 | E69: 60 | F69: 0 | H69: 0 | J69: 0 | N69: 0 | P69: 0 | R69: 0 | T69: 0 | V69: 0 | X69: 0 | Z69: 0
C70: Combustível | D70: 250 | E70: 100 | F70: 250 | H70: 250 | J70: 250 | N70: 250 | P70: 250 | R70: 250 | T70: 250 | V70: 250 | X70: 250 | Z70: 250
D71: 250 | E71: 100 | F71: 250 | H71: 250 | J71: 250 | N71: 250 | P71: 250 | R71: 250 | T71: 250 | V71: 250 | X71: 250 | Z71: 250
B73: Alimentação | C73: Supermercado | D73: 650 | E73: 680 | F73: 650 | H73: 650 | J73: 650 | N73: 650 | P73: 650 | R73: 650 | T73: 650 | V73: 650 | X73: 650 | Z73: 650
C74: Casa de carne | D74: 100 | E74: 120 | F74: 100 | H74: 100 | J74: 100 | N74: 100 | P74: 100 | R74: 100 | T74: 100 | V74: 100 | X74: 100 | Z74: 100
C75: Padaria | D75: 0 | F75: 0 | H75: 0 | J75: 0 | N75: 0 | P75: 0 | R75: 0 | T75: 0 | V75: 0 | X75: 0 | Z75: 0
C76: Feira
D77: 0 | F77: 0 | H77: 0 | J77: 0 | N77: 0 | P77: 0 | R77: 0 | T77: 0 | V77: 0 | X77: 0 | Z77: 0
D78: 0 | F78: 0 | H78: 0 | J78: 0 | N78: 0 | P78: 0 | R78: 0 | T78: 0 | V78: 0 | X78: 0 | Z78: 0
B80: Saúde | C80: Medicamentos | D80: 150 | E80: 180 | F80: 150 | H80: 150 | J80: 150 | N80: 150 | P80: 150 | R80: 150 | T80: 150 | V80: 150 | X80: 150 | Z80: 150
D81: 150 | E81: 180 | F81: 150 | H81: 150 | J81: 150 | N81: 150 | P81: 150 | R81: 150 | T81: 150 | V81: 150 | X81: 150 | Z81: 150
B83: Cuidados pessoais | C83: Cabeleireiro | D83: 40 | E83: 0 | F83: 40 | H83: 40 | J83: 40 | N83: 40 | P83: 40 | R83: 40 | T83: 40 | V83: 40 | X83: 40 | Z83: 40
C84: Manicure | D84: 50 | E84: 25 | F84: 50 | H84: 50 | J84: 50 | N84: 50 | P84: 50 | R84: 50 | T84: 50 | V84: 50 | X84: 50 | Z84: 50
C85: Perfumaria | D85: 50 | E85: 30 | F85: 50 | H85: 50 | J85: 50 | N85: 50 | P85: 50 | R85: 50 | T85: 50 | V85: 50 | X85: 50 | Z85: 50
B89: Despesas Financeiras | C89: Tarifas bancarias | D89: 20 | E89: 20 | F89: 20 | H89: 20 | J89: 20 | N89: 20 | P89: 20 | R89: 20 | T89: 20 | V89: 20 | X89: 20 | Z89: 20
B91: Total despesas variáveis | D91: =SUM(D61:D89) -> 2000 | E91: =SUM(E61:E89) -> 1730 | F91: =SUM(F61:F89) -> 2000 | G91: =SUM(G61:G89) -> 0 | H91: =SUM(H61:H89) -> 2000 | I91: =SUM(I61:I89) -> 0 | J91: =SUM(J61:J89) -> 2000 | K91: =SUM(K61:K89) -> 0 | ... AA91: =SUM(AA61:AA89) -> 0
B93: % sobre Receita | D93: =D91/$D$13 -> 0.5 | E93: =E91/$D$13 -> 0.4325 | F93: =F91/$D$13 -> 0.5 | G93: =G91/$D$13 -> 0 | H93: =H91/$D$13 -> 0.5 | I93: =I91/$D$13 -> 0 | J93: =J91/$D$13 -> 0.5 | K93: =K91/$D$13 -> 0 | N93: =N91/$D$13 -> 0.5 | O93: =O91/$D$13 -> 0 | P93: =P91/$D$13 -> 0.5 | Q93: =Q91/$D$13 -> 0 | R93: =R91/$D$13 -> 0.5 | S93: =S91/$D$13 -> 0 | T93: =T91/$D$13 -> 0.5 | U93: =U91/$D$13 -> 0 | ... AA93: =AA91/$D$13 -> 0
A95: Extras são as despesas as quais precisamos estar preparados para quando acontecerem | B95: Saúde | C95: Médico | D95: 0 | E95: 150 | F95: 0 | H95: 0 | J95: 0 | N95: 0 | P95: 0 | R95: 0 | T95: 0 | V95: 0 | X95: 0 | Z95: 0
C96: Dentista | D96: 0 | E96: 0 | F96: 0 | H96: 0 | J96: 0 | N96: 0 | P96: 0 | R96: 0 | T96: 0 | V96: 0 | X96: 0 | Z96: 0
D97: 0 | E97: 0 | F97: 0 | H97: 0 | J97: 0 | N97: 0 | P97: 0 | R97: 0 | T97: 0 | V97: 0 | X97: 0 | Z97: 0
B99: Manutenção/ prevenção | C99: Veículo | D99: 60 | E99: 80 | F99: 60 | H99: 60 | J99: 60 | N99: 60 | P99: 60 | R99: 60 | T99: 60 | V99: 60 | X99: 60 | Z99: 60
C100: Residência | D100: 20 | E100: 0 | F100: 20 | H100: 20 | J100: 20 | N100: 20 | P100: 20 | R100: 20 | T100: 20 | V100: 20 | X100: 20 | Z100: 20
B102: Educação | C102: Material escolar | D102: 0 | E102: 0 | F102: 0 | H102: 0 | J102: 0 | N102: 0 | P102: 0 | R102: 0 | T102: 0 | V102: 0 | X102: 0 | Z102: 0
C103: Uniforme
D104: 0 | E104: 0 | F104: 0 | H104: 0 | J104: 0 | N104: 0 | P104: 0 | R104: 0 | T104: 0 | V104: 0 | X104: 0 | Z104: 0
B106: Total despesas extras | D106: =SUM(D95:D104) -> 80 | E106: =SUM(E95:E104) -> 230 | F106: =SUM(F95:F104) -> 80 | G106: =SUM(G95:G104) -> 0 | H106: =SUM(H95:H104) -> 80 | I106: =SUM(I95:I104) -> 0 | J106: =SUM(J95:J104) -> 80 | K106: =SUM(K95:K104) -> 0 | ... AA106: =SUM(AA95:AA104) -> 0
B108: % sobre Receita | D108: =D106/$D$13 -> 0.02 | E108: =E106/$D$13 -> 0.0575 | F108: =F106/$D$13 -> 0.02 | G108: =G106/$D$13 -> 0 | H108: =H106/$D$13 -> 0.02 | I108: =I106/$D$13 -> 0 | J108: =J106/$D$13 -> 0.02 | K108: =K106/$D$13 -> 0 | N108: =N106/$D$13 -> 0.02 | O108: =O106/$D$13 -> 0 | P108: =P106/$D$13 -> 0.02 | Q108: =Q106/$D$13 -> 0 | R108: =R106/$D$13 -> 0.02 | S108: =S106/$D$13 -> 0 | T108: =T106/$D$13 -> 0.02 | U108: =U106/$D$13 -> 0 | ... AA108: =AA106/$D$13 -> 0
A110: Adicionais aquelas que não precisam, necessariamente, acontecer | B110: Lazer | C110: Cinema/teatro/parque | D110: 0 | E110: 0 | F110: 0 | G110: 0 | H110: 0 | I110: 0 | J110: 0 | K110: 0 | N110: 0 | O110: 0 | P110: 0 | Q110: 0 | R110: 0 | S110: 0 | T110: 0 | U110: 0 | V110: 0 | W110: 0 | X110: 0 | Y110: 0 | Z110: 0 | AA110: 0
C111: Restaurantes / lanchonetes | D111: 150 | E111: 100 | F111: 150 | H111: 150 | J111: 150 | N111: 150 | P111: 150 | R111: 150 | T111: 150 | V111: 150 | X111: 150 | Z111: 150
B115: Vestuário | C115: Roupas | D115: 130 | E115: 130 | F115: 130 | H115: 130 | J115: 130 | N115: 130 | P115: 130 | R115: 130 | T115: 130 | V115: 130 | X115: 130 | Z115: 130
C116: Calçados | D116: 60 | E116: 80 | F116: 60 | H116: 60 | J116: 60 | N116: 60 | P116: 60 | R116: 60 | T116: 60 | V116: 60 | X116: 60 | Z116: 60
C117: Acessórios | D117: 0 | E117: 0 | F117: 0 | H117: 0 | J117: 0 | N117: 0 | P117: 0 | R117: 0 | T117: 0 | V117: 0 | X117: 0 | Z117: 0
D119: 0 | E119: 0 | F119: 0 | H119: 0 | J119: 0 | N119: 0 | P119: 0 | R119: 0 | T119: 0 | V119: 0 | X119: 0 | Z119: 0
B121: Outros | C121: Presentes | D121: 100 | E121: 110 | F121: 100 | H121: 100 | J121: 100 | N121: 100 | P121: 100 | R121: 100 | T121: 100 | V121: 100 | X121: 100 | Z121: 100
D123: 0 | E123: 0 | F123: 0 | H123: 0 | J123: 0 | N123: 0 | P123: 0 | R123: 0 | T123: 0 | V123: 0 | X123: 0 | Z123: 0
B125: Total despesas adicionais | D125: =SUM(D110:D123) -> 440 | E125: =SUM(E110:E123) -> 420 | F125: =SUM(F110:F123) -> 440 | G125: =SUM(G110:G123) -> 0 | H125: =SUM(H110:H123) -> 440 | I125: =SUM(I110:I123) -> 0 | J125: =SUM(J110:J123) -> 440 | K125: =SUM(K110:K123) -> 0 | ... AA125: =SUM(AA110:AA123) -> 0
B127: % sobre Receita | D127: =D125/$D$13 -> 0.11 | E127: =E125/$D$13 -> 0.105 | F127: =F125/$D$13 -> 0.11 | G127: =G125/$D$13 -> 0 | H127: =H125/$D$13 -> 0.11 | I127: =I125/$D$13 -> 0 | J127: =J125/$D$13 -> 0.11 | K127: =K125/$D$13 -> 0 | N127: =N125/$D$13 -> 0.11 | O127: =O125/$D$13 -> 0 | P127: =P125/$D$13 -> 0.11 | Q127: =Q125/$D$13 -> 0 | R127: =R125/$D$13 -> 0.11 | S127: =S125/$D$13 -> 0 | T127: =T125/$D$13 -> 0.11 | U127: =U125/$D$13 -> 0 | ... AA127: =AA125/$D$13 -> 0
A129: Total despesas
A131: Resumo Geral | C131: Descrição | D131: Orçado | E131: Realizado | F131: Orçado | G131: Realizado | H131: Orçado | I131: Realizado | J131: Orçado | K131: Realizado | L131: Orçado | M131: Realizado | N131: Orçado | O131: Realizado | P131: Orçado | Q131: Realizado | R131: Orçado | S131: Realizado | T131: Orçado | U131: Realizado | V131: Orçado | W131: Realizado | X131: Orçado | Y131: Realizado | Z131: Orçado | AA131: Realizado
C132: Saldo Anterior | D132: 0 | E132: 0 | F132: =E139 -> -420 | G132: =E139 -> -420 | H132: =G139 -> -420 | J132: =I139 -> 0 | N132: =M139 -> 0 | P132: =O139 -> 0 | R132: =Q139 -> 0 | T132: =S139 -> 0 | V132: =U139 -> 0 | X132: =W139 -> 0 | Z132: =Y139 -> 0
C133: Receita | D133: =D13 -> 4000 | E133: =E13 -> 4100 | F133: =F13 -> 4000 | G133: =G13 -> 0 | H133: =H13 -> 4000 | I133: =I13 -> 0 | J133: =J13 -> 4000 | K133: =K13 -> 0 | M133: =M13 -> 0 | N133: =N13 -> 4000 | O133: =O13 -> 0 | P133: =P13 -> 4000 | Q133: =Q13 -> 0 | R133: =R13 -> 4000 | S133: =S13 -> 0 | T133: =T13 -> 4000 | ... AA133: =AA13 -> 0
C134: Investimentos | D134: =D22 -> 400 | E134: =E22 -> 410 | F134: =F22 -> 400 | G134: =G22 -> 0 | H134: =H22 -> 400 | I134: =I22 -> 0 | J134: =J22 -> 400 | K134: =K22 -> 0 | M134: =M22 -> 0 | N134: =N22 -> 400 | O134: =O22 -> 0 | P134: =P22 -> 400 | Q134: =Q22 -> 0 | R134: =R22 -> 400 | S134: =S22 -> 0 | T134: =T22 -> 400 | ... AA134: =AA22 -> 0
C135: Despesas fixas | D135: =D57 -> 1580 | E135: =E57 -> 1730 | F135: =F57 -> 1580 | G135: =G57 -> 0 | H135: =H57 -> 1580 | I135: =I57 -> 0 | J135: =J57 -> 1580 | K135: =K57 -> 0 | M135: =M57 -> 0 | N135: =N57 -> 1580 | O135: =O57 -> 0 | P135: =P57 -> 1580 | Q135: =Q57 -> 0 | R135: =R57 -> 1580 | S135: =S57 -> 0 | T135: =T57 -> 1580 | ... AA135: =AA57 -> 0
C136: Despesas variáveis | D136: =D91 -> 2000 | E136: =E91 -> 1730 | F136: =F91 -> 2000 | G136: =G91 -> 0 | H136: =H91 -> 2000 | I136: =I91 -> 0 | J136: =J91 -> 2000 | K136: =K91 -> 0 | M136: =M91 -> 0 | N136: =N91 -> 2000 | O136: =O91 -> 0 | P136: =P91 -> 2000 | Q136: =Q91 -> 0 | R136: =R91 -> 2000 | S136: =S91 -> 0 | T136: =T91 -> 2000 | ... AA136: =AA91 -> 0
C137: Despesas extras | D137: =D106 -> 80 | E137: =E106 -> 230 | F137: =F106 -> 80 | G137: =G106 -> 0 | H137: =H106 -> 80 | I137: =I106 -> 0 | J137: =J106 -> 80 | K137: =K106 -> 0 | M137: =M106 -> 0 | N137: =N106 -> 80 | O137: =O106 -> 0 | P137: =P106 -> 80 | Q137: =Q106 -> 0 | R137: =R106 -> 80 | S137: =S106 -> 0 | T137: =T106 -> 80 | ... AA137: =AA106 -> 0
C138: Despesas adicionais | D138: =D125 -> 440 | E138: =E125 -> 420 | F138: =F125 -> 440 | G138: =G125 -> 0 | H138: =H125 -> 440 | I138: =I125 -> 0 | J138: =J125 -> 440 | K138: =K125 -> 0 | M138: =M125 -> 0 | N138: =N125 -> 440 | O138: =O125 -> 0 | P138: =P125 -> 440 | Q138: =Q125 -> 0 | R138: =R125 -> 440 | S138: =S125 -> 0 | T138: =T125 -> 440 | ... AA138: =AA125 -> 0
C139: Saldo Atual | D139: =D132+D133-SUM(D134:D138) -> -500 | E139: =E132+E133-SUM(E134:E138) -> -420 | F139: =F132+F133-SUM(F134:F138) -> -920 | G139: =G132+G133-SUM(G134:G138) -> -420 | H139: =H132+H133-SUM(H134:H138) -> -920 | I139: =I132+I133-SUM(I134:I138) -> 0 | J139: =J132+J133-SUM(J134:J138) -> -500 | K139: =K132+K133-SUM(K134:K138) -> 0 | ... AA139: =AA132+AA133-SUM(AA134:AA138) -> 0

Sheet Mod. Orçamento Doméstico
A3: Orçamento Doméstico | P3: Orçamento Doméstico
A5: Categoria | C5: Descrição | D5: 43101 | F5: 43132 | H5: 43160 | J5: 43191 | L5: 43221 | N5: 43252 | S5: 43282 | U5: 43313 | W5: 43344 | Y5: 43374 | AA5: 43405 | AC5: 43435
D6: Orçado | E6: Realizado | F6: Orçado | G6: Realizado | H6: Orçado | I6: Realizado | J6: Orçado | K6: Realizado | L6: Orçado | M6: Realizado | N6: Orçado | O6: Realizado | R6: Descrição | S6: Orçado | T6: Realizado | U6: Orçado | V6: Realizado | W6: Orçado | X6: Realizado | Y6: Orçado | Z6: Realizado | AA6: Orçado | AB6: Realizado | AC6: Orçado | AD6: Realizado
A7: Receitas | C7: Salário | P7: Receitas | R7: Salário
C8: Outros | R8: Outros
C9: Horas extras | R9: Horas extras
C10: 13º salário | R10: 13º salário
C11: Férias | R11: Férias
C12: Renda Extra | R12: Renda Extra
C13: Total | R13: Total
A15: Investimentos Insira aqui o montante mensal que você destinará aos seus investimentos | C15: Descrição | D15: Orçado | E15: Realizado | F15: Orçado | G15: Realizado | H15: Orçado | I15: Realizado | J15: Orçado | K15: Realizado | L15: Orçado | M15: Realizado | N15: Orçado | O15: Realizado | P15: Investimentos Insira aqui o montante mensal que você destinará aos seus investimentos | R15: Descrição | S15: Orçado | T15: Realizado | U15: Orçado | V15: Realizado | W15: Orçado | X15: Realizado | Y15: Orçado | Z15: Realizado | AA15: Orçado | AB15: Realizado | AC15: Orçado | AD15: Realizado
C16: Reserva de Emergência | D16: =D7*10% -> 0 | E16: =E13*10% -> 0 | F16: =F7*10% -> 0 | H16: =H7*10% -> 0 | J16: =J7*10% -> 0 | L16: =L7*10% -> 0 | N16: =N7*10% -> 0 | R16: Reserva de Emergência | S16: =S7*10% -> 0 | U16: =U7*10% -> 0 | W16: =W7*10% -> 0 | Y16: =Y7*10% -> 0 | AA16: =AA7*10% -> 0 | AC16: =AC7*10% -> 0
C17: Plano de Aposentadoria | D17: 0 | E17: 0 | F17: 0 | H17: 0 | J17: 0 | L17: 0 | N17: 0 | R17: Plano de Aposentadoria | S17: 0 | U17: 0 | W17: 0 | Y17: 0 | AA17: 0 | AC17: 0
C18: Independencia | D18: 0 | E18: 0 | F18: 0 | H18: 0 | J18: 0 | L18: 0 | N18: 0 | R18: Independencia | S18: 0 | U18: 0 | W18: 0 | Y18: 0 | AA18: 0 | AC18: 0
C19: Ações | D19: 0 | E19: 0 | F19: 0 | H19: 0 | J19: 0 | L19: 0 | N19: 0 | R19: Ações | S19: 0 | U19: 0 | W19: 0 | Y19: 0 | AA19: 0 | AC19: 0
C20: Outros | D20: 0 | E20: 0 | F20: 0 | H20: 0 | J20: 0 | L20: 0 | N20: 0 | R20: Outros | S20: 0 | U20: 0 | W20: 0 | Y20: 0 | AA20: 0 | AC20: 0
C22: Total | D22: =SUM(D16:D21) -> 0 | E22: =SUM(E16:E21) -> 0 | F22: =SUM(F16:F21) -> 0 | G22: =SUM(G16:G21) -> 0 | H22: =SUM(H16:H21) -> 0 | I22: =SUM(I16:I21) -> 0 | J22: =SUM(J16:J21) -> 0 | K22: =SUM(K16:K21) -> 0 | ... O22: =SUM(O16:O21) -> 0 | R22: Total | S22: =SUM(S16:S21) -> 0 | T22: =SUM(T16:T21) -> 0 | U22: =SUM(U16:U21) -> 0 | V22: =SUM(V16:V21) -> 0 | W22: =SUM(W16:W21) -> 0 | X22: =SUM(X16:X21) -> 0 | Y22: =SUM(Y16:Y21) -> 0 | Z22: =SUM(Z16:Z21) -> 0 | ... AD22: =SUM(AD16:AD21) -> 0
C23: % sobre Receita | D23: =D22/$D$13 -> #DIV/0! | E23: =E22/$D$13 -> #DIV/0! | F23: =F22/$D$13 -> #DIV/0! | G23: =G22/$D$13 -> #DIV/0! | H23: =H22/$D$13 -> #DIV/0! | I23: =I22/$D$13 -> #DIV/0! | J23: =J22/$D$13 -> #DIV/0! | K23: =K22/$D$13 -> #DIV/0! | ... O23: =O22/$D$13 -> #DIV/0! | R23: % sobre Receita | S23: =S22/$D$13 -> #DIV/0! | T23: =T22/$D$13 -> #DIV/0! | U23: =U22/$D$13 -> #DIV/0! | V23: =V22/$D$13 -> #DIV/0! | W23: =W22/$D$13 -> #DIV/0! | X23: =X22/$D$13 -> #DIV/0! | Y23: =Y22/$D$13 -> #DIV/0! | Z23: =Z22/$D$13 -> #DIV/0! | ... AD23: =AD22/$D$13 -> #DIV/0!
A25: Categoria | C25: Descrição | D25: Orçado | E25: Realizado | F25: Orçado | G25: Realizado | H25: Orçado | I25: Realizado | J25: Orçado | K25: Realizado | L25: Orçado | M25: Realizado | N25: Orçado | O25: Realizado | P25: Descrição | R25: Descrição | S25: Orçado | T25: Realizado | U25: Orçado | V25: Realizado | W25: Orçado | X25: Realizado | Y25: Orçado | Z25: Realizado | AA25: Orçado | AB25: Realizado | AC25: Orçado | AD25: Realizado
A26: Fixas o mesmo montante mensalmente | B26: Habitação | C26: Prestação / Aluguel | P26: Fixas o mesmo montante mensalmente | Q26: Habitação | R26: Prestação / Aluguel
C27: Telefone | R27: Telefone
C28: Internet | R28: Internet
B34: Transporte | C34: Prestação do carro | Q34: Transporte | R34: Prestação do carro
C35: Seguro do carro | R35: Seguro do carro
B37: Saúde | C37: Academia | Q37: Saúde | R37: Academia
C38: Seguro de vida | R38: Seguro de vida
C39: Plano de saúde | R39: Plano de saúde
B43: Educação | C43: Livros | Q43: Educação | R43: Livros
C44: Faculdade | R44: Faculdade
B48: Impostos | C48: IPTU | Q48: Impostos | R48: IPTU
C49: IPVA | R49: IPVA
C50: INSS
C51: IRRF
B53: Espiritual | C53: Dízimo | Q53: Espiritual | R53: Dízimo
C54: Ofertas | R54: Ofertas
B57: Total despesas fixas | Q57: Total despesas fixas
B59: % sobre Receita | Q59: % sobre Receita
A61: Variáveis aquelas que acontecem mensalmente, mas podemos tentar reduzir | B61: Moradia | C61: Luz | P61: Variáveis aquelas que acontecem mensalmente, mas podemos tentar reduzir | Q61: Moradia | R61: Luz
C62: Água | R62: Água
C63: Telefone Celular | R63: Telefone Celular
C64: Gás | R64: Gás
C65: Seguro | R65: Seguro
B69: Transporte | C69: Ônibus | Q69: Transporte | R69: Ônibus
C70: Combustível | R70: Combustível
B73: Alimentação | C73: Supermercado | Q73: Alimentação | R73: Supermercado
C74: Casa de carne | R74: Casa de carne
C75: Padaria | R75: Padaria
C76: Feira | R76: Feira
B80: Saúde | C80: Medicamentos | Q80: Saúde | R80: Medicamentos
B83: Cuidados pessoais | C83: Cabeleireiro | Q83: Cuidados pessoais | R83: Cabeleireiro
C84: Manicure | R84: Manicure
C85: Perfumaria | R85: Perfumaria
B89: Despesas Financeiras | C89: Tarifas bancarias | Q89: Despesas Financeiras | R89: Tarifas bancarias
B91: Total despesas variáveis | Q91: Total despesas variáveis
B93: % sobre Receita | Q93: % sobre Receita
A95: Extras são as despesas as quais precisamos estar preparados para quando acontecerem | B95: Saúde | C95: Médico | P95: Extras são as despesas as quais precisamos estar preparados para quando acontecerem | Q95: Saúde | R95: Médico
C96: Dentista | R96: Dentista
B99: Manutenção/ prevenção | C99: Veículo | Q99: Manutenção/ prevenção | R99: Veículo
C100: Residência | R100: Residência
B102: Educação | C102: Material escolar | Q102: Educação | R102: Material escolar
C103: Uniforme | R103: Uniforme
B106: Total despesas extras | Q106: Total despesas extras
B108: % sobre Receita | Q108: % sobre Receita
A110: Adicionais aquelas que não precisam, necessariamente, acontecer | B110: Lazer | C110: Cinema/teatro/parque | P110: Adicionais aquelas que não precisam, necessariamente, acontecer | Q110: Lazer | R110: Cinema/teatro/parque
C111: Restaurantes/lanchonetes | R111: Restaurantes/lanchonetes
B115: Vestuário | C115: Roupas | Q115: Vestuário | R115: Roupas
C116: Calçados | R116: Calçados
C117: Acessórios | R117: Acessórios
B121: Outros | C121: Presentes | Q121: Outros | R121: Presentes
B125: Total despesas adicionais | Q125: Total despesas adicionais
B127: % sobre Receita | D127: =D125/$D$13 -> #DIV/0! | E127: =E125/$D$13 -> #DIV/0! | F127: =F125/$D$13 -> #DIV/0! | G127: =G125/$D$13 -> #DIV/0! | H127: =H125/$D$13 -> #DIV/0! | I127: =I125/$D$13 -> #DIV/0! | J127: =J125/$D$13 -> #DIV/0! | K127: =K125/$D$13 -> #DIV/0! | N127: =N125/$D$13 -> #DIV/0! | O127: =O125/$D$13 -> #DIV/0! | Q127: % sobre Receita | S127: =S125/$D$13 -> #DIV/0! | T127: =T125/$D$13 -> #DIV/0! | U127: =U125/$D$13 -> #DIV/0! | V127: =V125/$D$13 -> #DIV/0! | W127: =W125/$D$13 -> #DIV/0! | X127: =X125/$D$13 -> #DIV/0! | Y127: =Y125/$D$13 -> #DIV/0! | Z127: =Z125/$D$13 -> #DIV/0! | ... AD127: =AD125/$D$13 -> #DIV/0!
A129: Total despesas | P129: Total despesas
A131: Resumo Geral | C131: Descrição | D131: Orçado | E131: Realizado | F131: Orçado | G131: Realizado | H131: Orçado | I131: Realizado | J131: Orçado | K131: Realizado | L131: Orçado | M131: Realizado | N131: Orçado | O131: Realizado | P131: Resumo Geral | R131: Descrição | S131: Orçado | T131: Realizado | U131: Orçado | V131: Realizado | W131: Orçado | X131: Realizado | Y131: Orçado | Z131: Realizado | AA131: Orçado | AB131: Realizado | AC131: Orçado | AD131: Realizado
C132: Saldo Anterior | R132: Saldo Anterior
C133: Receita | R133: Receita
C134: Investimentos | R134: Investimentos
C135: Despesas fixas | R135: Despesas fixas
C136: Despesas variáveis | R136: Despesas variáveis
C137: Despesas extras | R137: Despesas extras
C138: Despesas adicionais | R138: Despesas adicionais
C139: Saldo Atual | R139: Saldo Atual

Sheet Controle de Gastos
B2: CONTROLE DE GASTOS
B4: SALDO ANTERIOR
B6: GANHOS | F6: GASTOS | L6: Cartão de Crédito
B7: Data | C7: Fonte | D7: Valor | F7: Data | G7: Descrição | H7: Valor | I7: Parcela | J7: Class. | L7: Descrição | M7: Valor | N7: Parcela | O7: Class.
B31: TOTAL | D31: =SUM(D8:D30) -> 0
B33: SALDO INICIAL | D33: =D4+D31 -> 0
B35: INVESTIMENTOS
B36: Data | C36: Tipo | D36: Valor
G41: Cartão de Crédito | H41: =M43 -> 0
B43: TOTAL | D43: =SUM(D37:D42) -> 0 | F43: TOTAL | H43: =SUM(H8:H42) -> 0 | L43: TOTAL | M43: =SUM(M8:M42) -> 0
B45: LEGENDA: Classificação das Despesas | F45: SALDO FINAL | H45: =D33-D43-H43 -> 0 | L45: Endividamento
B46: Fixos Prioritários (FP): o mesmo montante mensalmente, extremamente necessários | L46: Valor das Parcelas
B47: Variáveis Prioritários (VP): não acontecem mensalmente, são extremamente necessários, alguns podem ser reduzidos | L47: Receita Fixa
B48: Fixos Secundários (FS): o mesmo montante mensalmente, mas podem ser reduzidos | L48: Índice de Endividamento | M48: =M46/M47 -> #DIV/0!
B49: Variáveis Secundários (VS): não precisam, necessariamente acontecer.

Sheet Instruções para preenchimento
A1: Instruções para Preenchimento
A2: Orçamento Familiar | B2: - As descrições devem ser alteradas somente na aba "Orçamento Familiar", ela irá reproduzir, automaticamente, nas outras abas. - Para definir o valor que será poupado, mensalmente, para a reserva de emergência, pode-se somente alterar o percentual na célula "D19". Se preferir, também pode desconsiderar o percentual e colocar o valor fixo para cada mês - Inserir os valores esperados mensais para cada subcategoria - Verificar o saldo final (buscar sempre deixar o saldo positivo)
A3: Meses | B3: - Toda alteração de descrição deve ser feita na aba "Orçamento Familiar" - Sugestão atualizar os lançamentos das despesas, semanalmente, para melhor controle - Verificar o saldo final (buscar sempre deixar o saldo positivo)
A4: Fluxo de Caixa | B4: - Traz o resumo das receitas e despesas "Orçado x Realizado" mensais e anual, portanto deve ser utilizada para avaliação, não precisa preencher nada

Sheet Orçamento Familiar
A3: Orçamento Familiar
A5: Categoria | C5: Descrição | D5: Percentual | E5: 46023 | F5: 46054 | G5: 46082 | H5: 46113 | I5: 46143 | J5: 46174 | K5: 46204 | L5: 46235 | M5: 46266 | N5: 46296 | O5: 46327 | P5: 46357 | Q5: Total
A7: Receitas | C7: Prebenda | E7: 7216 | F7: 7216 | G7: 7216 | H7: 7216 | I7: 7216 | J7: 7216 | K7: 7216 | L7: 7216 | M7: 7216 | N7: 7216 | O7: 7216 | P7: 7216 | Q7: =SUM(E7:P7) -> 86592
C8: Inglês | E8: 340 | F8: 340 | G8: 335 | H8: 335 | I8: 335 | J8: 335 | K8: 335 | L8: 335 | M8: 335 | N8: 335 | O8: 335 | P8: 335 | Q8: =SUM(E8:P8) -> 4030
C9: 13º Salário | O9: =O7/2 -> 3608 | P9: =P7/2 -> 3608 | Q9: =SUM(E9:P9) -> 7216
C10: Renda Extra | Q10: =SUM(E10:P10) -> 0
Q11: =SUM(E11:P11) -> 0
Q12: =SUM(E12:P12) -> 0
Q13: =SUM(E13:P13) -> 0
Q14: =SUM(E14:P14) -> 0
Q15: =SUM(E15:P15) -> 0
C16: Total | E16: =SUM(E7:E15) -> 7556 | F16: =SUM(F7:F15) -> 7556 | G16: =SUM(G7:G15) -> 7551 | H16: =SUM(H7:H15) -> 7551 | I16: =SUM(I7:I15) -> 7551 | J16: =SUM(J7:J15) -> 7551 | K16: =SUM(K7:K15) -> 7551 | L16: =SUM(L7:L15) -> 7551 | ... Q16: =SUM(Q7:Q15) -> 97838
A18: Investimentos Insira aqui o montante mensal que você destinará aos seus investimentos | C18: Descrição | D18: Percentual | E18: =E5 -> 46023 | F18: =F5 -> 46054 | G18: =G5 -> 46082 | H18: =H5 -> 46113 | I18: =I5 -> 46143 | J18: =J5 -> 46174 | K18: =K5 -> 46204 | L18: =L5 -> 46235 | ... Q18: =Q5 -> Total
C19: Reserva de Emergência (CP) R$ 9.151 | E19: =E16*$D$19 -> 0 | F19: =F16*$D$19 -> 0 | G19: =G16*$D$19 -> 0 | H19: =H16*$D$19 -> 0 | I19: =I16*$D$19 -> 0 | J19: =J16*$D$19 -> 0 | K19: =K16*$D$19 -> 0 | L19: =L16*$D$19 -> 0 | ... P19: =P16*$D$19 -> 0 | Q19: =SUM(E19:P19) -> 0
C20: Projeto 1 | Q20: =SUM(E20:P20) -> 0
C21: Projeto 2 | Q21: =SUM(E21:P21) -> 0
C22: Projeto 3 | Q22: =SUM(E22:P22) -> 0
C23: Projeto 4 | Q23: =SUM(E23:P23) -> 0
C24: Projeto 5 | Q24: =SUM(E24:P24) -> 0
C25: Projeto 6 | Q25: =SUM(E25:P25) -> 0
C26: Independência Financeira | Q26: =SUM(E26:P26) -> 0
C27: Total Investimentos | E27: =SUM(E19:E26) -> 0 | F27: =SUM(F19:F26) -> 0 | G27: =SUM(G19:G26) -> 0 | H27: =SUM(H19:H26) -> 0 | I27: =SUM(I19:I26) -> 0 | J27: =SUM(J19:J26) -> 0 | K27: =SUM(K19:K26) -> 0 | L27: =SUM(L19:L26) -> 0 | ... Q27: =SUM(Q19:Q26) -> 0
C28: % sobre Receita | E28: =E27/E16 -> 0 | F28: =F27/F16 -> 0 | G28: =G27/G16 -> 0 | H28: =H27/H16 -> 0 | I28: =I27/I16 -> 0 | J28: =J27/J16 -> 0 | K28: =K27/K16 -> 0 | L28: =L27/L16 -> 0 | ... Q28: =Q27/Q16 -> 0
A30: Categoria | C30: Descrição | E30: =E5 -> 46023 | F30: =F5 -> 46054 | G30: =G5 -> 46082 | H30: =H5 -> 46113 | I30: =I5 -> 46143 | J30: =J5 -> 46174 | K30: =K5 -> 46204 | L30: =L5 -> 46235 | ... Q30: =Q5 -> Total
A31: Despesas Essenciais | B31: Moradia | C31: Aluguel | Q31: =SUM(E31:P31) -> 0
C32: Energia Elétrica | Q32: =SUM(E32:P32) -> 0
C33: Água e Esgoto | Q33: =SUM(E33:P33) -> 0
C34: Gás | Q34: =SUM(E34:P34) -> 0
C35: Internet e Celular | E35: 125 | F35: 125 | G35: 184.7 | H35: 184.7 | I35: 184.7 | J35: 184.7 | K35: 184.7 | L35: 184.7 | M35: 184.7 | N35: 184.7 | O35: 184.7 | P35: 184.7 | Q35: =SUM(E35:P35) -> 2097
C36: Manutenção | G36: 50 | H36: 50 | I36: 50 | J36: 50 | K36: 50 | L36: 50 | M36: 50 | N36: 50 | O36: 50 | P36: 50 | Q36: =SUM(E36:P36) -> 500
Q37: =SUM(E37:P37) -> 0
Q38: =SUM(E38:P38) -> 0
Q39: =SUM(E39:P39) -> 0
B40: Alimentação | C40: Supermercado | E40: 3100 | F40: 3100 | G40: 3100 | H40: 3100 | I40: 3100 | J40: 3100 | K40: 3100 | L40: 3100 | M40: 3100 | N40: 3100 | O40: 3100 | P40: 3100 | Q40: =SUM(E40:P40) -> 37200
Q41: =SUM(E41:P41) -> 0
Q42: =SUM(E42:P42) -> 0
Q43: =SUM(E43:P43) -> 0
Q44: =SUM(E44:P44) -> 0
Q45: =SUM(E45:P45) -> 0
B46: Transporte | C46: Combustível | E46: 400 | F46: 400 | G46: 400 | H46: 400 | I46: 400 | J46: 400 | K46: 400 | L46: 400 | M46: 400 | N46: 400 | O46: 400 | P46: 400 | Q46: =SUM(E46:P46) -> 4800
C47: Manutenção | E47: 1430 | F47: 1430 | G47: 500 | H47: 555 | I47: 555 | J47: 555 | Q47: =SUM(E47:P47) -> 5025
C48: Multas | Q48: =SUM(E48:P48) -> 0
C49: Seguro | Q49: =SUM(E49:P49) -> 0
C50: Lavagem | Q50: =SUM(E50:P50) -> 0
C51: Estacionamento | Q51: =SUM(E51:P51) -> 0
C52: Taxi / Uber | Q52: =SUM(E52:P52) -> 0
Q53: =SUM(E53:P53) -> 0
Q54: =SUM(E54:P54) -> 0
B55: Saúde | C55: Medicamentos | E55: 80 | F55: 80 | G55: 80 | H55: 80 | I55: 80 | J55: 80 | K55: 80 | L55: 80 | M55: 80 | N55: 80 | O55: 80 | P55: 80 | Q55: =SUM(E55:P55) -> 960
C56: Médicos / Exames | Q56: =SUM(E56:P56) -> 0
C57: Dentista | Q57: =SUM(E57:P57) -> 0
Q58: =SUM(E58:P58) -> 0
Q59: =SUM(E59:P59) -> 0
B60: Impostos | C60: IPVA | E60: 210 | N60: 850 | Q60: =SUM(E60:P60) -> 1060
C61: Licenciamento | N61: 160 | Q61: =SUM(E61:P61) -> 160
C62: Imposto de Renda | Q62: =SUM(E62:P62) -> 0
C63: INSS | Q63: =SUM(E63:P63) -> 0
Q64: =SUM(E64:P64) -> 0
Q65: =SUM(E65:P65) -> 0
B66: Educação | C66: Especialização | Q66: =SUM(E66:P66) -> 0
C67: Cursos | G67: 150 | H67: 150 | I67: 150 | J67: 150 | K67: 150 | L67: 150 | Q67: =SUM(E67:P67) -> 900
C68: Mentoria Financeira | E68: 200 | F68: 200 | G68: 225 | H68: 225 | I68: 225 | J68: 225 | K68: 225 | L68: 225 | M68: 225 | N68: 225 | O68: 225 | P68: 225 | Q68: =SUM(E68:P68) -> 2650
Q69: =SUM(E69:P69) -> 0
Q70: =SUM(E70:P70) -> 0
B71: Filhos | C71: Piano Laura | Q71: =SUM(E71:P71) -> 0
C72: Material Escolar | Q72: =SUM(E72:P72) -> 0
C73: Mesadas | E73: 410 | F73: 300 | G73: 330 | H73: =120+70 -> 190 | I73: =120+70 -> 190 | J73: =120+70 -> 190 | K73: =120+70 -> 190 | L73: 120 | M73: 120 | Q73: =SUM(E73:P73) -> 2040
C74: Violão | Q74: =SUM(E74:P74) -> 0
C75: Médicos / Exames | Q75: =SUM(E75:P75) -> 0
C76: Cursos | Q76: =SUM(E76:P76) -> 0
C77: Retiro Carnaval 2026/2027 | H77: 240 | I77: 240 | J77: 240 | K77: 240 | L77: 240 | M77: 240 | N77: 240 | O77: 240 | P77: 240 | Q77: =SUM(E77:P77) -> 2160 | R77: até fevereiro
C78: Acampadentro | Q78: =SUM(E78:P78) -> 0
Q79: =SUM(E79:P79) -> 0
B80: Pet | C80: Ração | E80: 50 | F80: 50 | G80: 50 | H80: 50 | I80: 50 | J80: 50 | K80: 50 | L80: 50 | M80: 50 | N80: 50 | O80: 50 | P80: 50 | Q80: =SUM(E80:P80) -> 600
C81: Vacinas | Q81: =SUM(E81:P81) -> 0
C82: Veterinário | Q82: =SUM(E82:P82) -> 0
Q83: =SUM(E83:P83) -> 0
Q84: =SUM(E84:P84) -> 0
B85: Total Despesas Essenciais | E85: =SUM(E31:E84) -> 6005 | F85: =SUM(F31:F84) -> 5685 | G85: =SUM(G31:G84) -> 5069.7 | H85: =SUM(H31:H84) -> 5224.7 | I85: =SUM(I31:I84) -> 5224.7 | J85: =SUM(J31:J84) -> 5224.7 | K85: =SUM(K31:K84) -> 4669.7 | L85: =SUM(L31:L84) -> 4599.7 | ... Q85: =SUM(Q31:Q84) -> 60152
B86: % sobre Receita | E86: =E85/E16 -> 0.79473266 | F86: =F85/F16 -> 0.75238221 | G86: =G85/G16 -> 0.67139452 | H86: =H85/H16 -> 0.6919216 | I86: =I85/I16 -> 0.6919216 | J86: =J85/J16 -> 0.6919216 | K86: =K85/K16 -> 0.6184214 | L86: =L85/L16 -> 0.60915111 | ... Q86: =Q85/Q16 -> 0.61481224
A87: Profissional e Trabalho | B87: Ministério | C87: Materiais (livros) | G87: 125 | H87: 30 | I87: 30 | J87: 30 | K87: 30 | L87: 30 | M87: 30 | N87: 30 | O87: 30 | P87: 30 | Q87: =SUM(E87:P87) -> 395
Q88: =SUM(E88:P88) -> 0
Q89: =SUM(E89:P89) -> 0
Q90: =SUM(E90:P90) -> 0
Q91: =SUM(E91:P91) -> 0
Q92: =SUM(E92:P92) -> 0
B93: Autônomo | C93: Ferramentas de trabalho | E93: 50 | F93: 50 | G93: 200 | H93: 200 | I93: 150 | J93: 150 | K93: 150 | L93: 150 | M93: 150 | N93: 150 | O93: 150 | P93: 150 | Q93: =SUM(E93:P93) -> 1700
C94: Colaboradores | E94: 140 | F94: 140 | G94: 50 | Q94: =SUM(E94:P94) -> 330
Q95: =SUM(E95:P95) -> 0
Q96: =SUM(E96:P96) -> 0
Q97: =SUM(E97:P97) -> 0
Q98: =SUM(E98:P98) -> 0
B99: Total Profissional e Trabalho | E99: =SUM(E87:E98) -> 190 | F99: =SUM(F87:F98) -> 190 | G99: =SUM(G87:G98) -> 375 | H99: =SUM(H87:H98) -> 230 | I99: =SUM(I87:I98) -> 180 | J99: =SUM(J87:J98) -> 180 | K99: =SUM(K87:K98) -> 180 | L99: =SUM(L87:L98) -> 180 | ... Q99: =SUM(Q87:Q98) -> 2425
B100: % sobre Receita | E100: =E99/E16 -> 0.02514558 | F100: =F99/F16 -> 0.02514558 | G100: =G99/G16 -> 0.049662296 | H100: =H99/H16 -> 0.030459542 | I100: =I99/I16 -> 0.023837902 | J100: =J99/J16 -> 0.023837902 | K100: =K99/K16 -> 0.023837902 | L100: =L99/L16 -> 0.023837902 | ... Q100: =Q99/Q16 -> 0.024785871
A101: Contribuição | B101: Ofertas | C101: Dízimo | E101: 700 | F101: 850 | G101: 850 | H101: 850 | I101: 850 | J101: 850 | K101: 850 | L101: 850 | M101: 850 | N101: 850 | O101: 850 | P101: 850 | Q101: =SUM(E101:P101) -> 10050
C102: Sacrificial | Q102: =SUM(E102:P102) -> 0
C103: Doações | Q103: =SUM(E103:P103) -> 0
Q104: =SUM(E104:P104) -> 0
B105: Total Contribuição | E105: =SUM(E101:E104) -> 700 | F105: =SUM(F101:F104) -> 850 | G105: =SUM(G101:G104) -> 850 | H105: =SUM(H101:H104) -> 850 | I105: =SUM(I101:I104) -> 850 | J105: =SUM(J101:J104) -> 850 | K105: =SUM(K101:K104) -> 850 | L105: =SUM(L101:L104) -> 850 | ... P105: =SUM(P101:P104) -> 850 | Q105: =SUM(Q93:Q104) -> 14505.025
B106: % sobre Receita | E106: =E105/E16 -> 0.092641609 | F106: =F105/F16 -> 0.11249338 | G106: =G105/G16 -> 0.11256787 | H106: =H105/H16 -> 0.11256787 | I106: =I105/I16 -> 0.11256787 | J106: =J105/J16 -> 0.11256787 | K106: =K105/K16 -> 0.11256787 | L106: =L105/L16 -> 0.11256787 | ... Q106: =Q105/Q16 -> 0.14825553
...

Sheet Jan
A2: Fluxo de Caixa Familiar
A5: Categoria | C5: Descrição | D5: Percentual | E5: =I5 -> Janeiro | I5: Janeiro
E6: Orçado | F6: Realizado | G6: Variação | I6: Semana 1 | J6: Semana 2 | K6: Semana 3 | L6: Semana 4 | M6: Semana 5 | N6: Cartão Nubank | O6: Cartão C & A | P6: Total
A7: Receitas | C7: ='Orçamento Familiar'!C7 -> Prebenda | E7: ='Orçamento Familiar'!E7 -> 7216 | F7: =P7 -> 6296 | G7: =F7-E7 -> -920 | I7: 6296 | P7: =SUM(I7:O7) -> 6296
C8: ='Orçamento Familiar'!C8 -> Inglês | E8: ='Orçamento Familiar'!E8 -> 340 | F8: =P8 -> 335 | G8: =F8-E8 -> -5 | I8: 200 | K8: 135 | P8: =SUM(I8:O8) -> 335
C9: ='Orçamento Familiar'!C9 -> 13º Salário | E9: ='Orçamento Familiar'!E9 -> 0 | F9: =P9 -> 0 | G9: =F9-E9 -> 0 | P9: =SUM(I9:O9) -> 0
C10: ='Orçamento Familiar'!C10 -> Renda Extra | E10: ='Orçamento Familiar'!E10 -> 0 | F10: =P10 -> 1880 | G10: =F10-E10 -> 1880 | I10: 240 | K10: 1500 | L10: 140 | P10: =SUM(I10:O10) -> 1880 | Q10: 1500,00- vale + 240,00 Eric + 140,00 Levi
C11: ='Orçamento Familiar'!C11 -> 0 | E11: ='Orçamento Familiar'!E11 -> 0 | F11: =P11 -> 290 | G11: =F11-E11 -> 290 | K11: 290 | P11: =SUM(I11:O11) -> 290
C12: ='Orçamento Familiar'!C12 -> 0 | E12: ='Orçamento Familiar'!E12 -> 0 | F12: =P12 -> 0 | G12: =F12-E12 -> 0 | P12: =SUM(I12:O12) -> 0
C13: ='Orçamento Familiar'!C13 -> 0 | E13: ='Orçamento Familiar'!E13 -> 0 | F13: =P13 -> 0 | G13: =F13-E13 -> 0 | P13: =SUM(I13:O13) -> 0
C14: ='Orçamento Familiar'!C14 -> 0 | E14: ='Orçamento Familiar'!E14 -> 0 | F14: =P14 -> 0 | G14: =F14-E14 -> 0 | P14: =SUM(I14:O14) -> 0
C15: ='Orçamento Familiar'!C15 -> 0 | E15: ='Orçamento Familiar'!E15 -> 0 | F15: =P15 -> 0 | G15: =F15-E15 -> 0 | P15: =SUM(I15:O15) -> 0
C16: Total | E16: =SUM(E7:E15) -> 7556 | F16: =SUM(F7:F15) -> 8801 | G16: =SUM(G7:G15) -> 1245 | I16: =SUM(I7:I15) -> 6736 | J16: =SUM(J7:J15) -> 0 | K16: =SUM(K7:K15) -> 1925 | L16: =SUM(L7:L15) -> 140 | M16: =SUM(M7:M15) -> 0 | N16: =SUM(N7:N15) -> 0 | O16: =SUM(O7:O15) -> 0 | P16: =SUM(P7:P15) -> 8801
A18: Investimentos Insira aqui o montante mensal que você destinará aos seus investimentos | C18: Descrição | D18: Percentual | E18: Orçado | F18: Realizado | G18: Variação | I18: =I6 -> Semana 1 | J18: =J6 -> Semana 2 | K18: =K6 -> Semana 3 | L18: =L6 -> Semana 4 | M18: =M6 -> Semana 5 | P18: =P6 -> Total
C19: ='Orçamento Familiar'!C19 -> Reserva de Emergência (CP) R$ 9.151 | E19: ='Orçamento Familiar'!E19 -> 0 | F19: =P19 -> 0 | G19: =F19-E19 -> 0 | P19: =SUM(I19:O19) -> 0
C20: ='Orçamento Familiar'!C20 -> Projeto 1 | E20: ='Orçamento Familiar'!E20 -> 0 | F20: =P20 -> 0 | G20: =F20-E20 -> 0 | P20: =SUM(I20:O20) -> 0
C21: ='Orçamento Familiar'!C21 -> Projeto 2 | E21: ='Orçamento Familiar'!E21 -> 0 | F21: =P21 -> 0 | G21: =F21-E21 -> 0 | P21: =SUM(I21:O21) -> 0
C22: ='Orçamento Familiar'!C22 -> Projeto 3 | E22: ='Orçamento Familiar'!E22 -> 0 | F22: =P22 -> 0 | G22: =F22-E22 -> 0 | P22: =SUM(I22:O22) -> 0
C23: ='Orçamento Familiar'!C23 -> Projeto 4 | E23: ='Orçamento Familiar'!E23 -> 0 | F23: =P23 -> 0 | G23: =F23-E23 -> 0 | P23: =SUM(I23:O23) -> 0
C24: ='Orçamento Familiar'!C24 -> Projeto 5 | E24: ='Orçamento Familiar'!E24 -> 0 | F24: =P24 -> 0 | G24: =F24-E24 -> 0 | P24: =SUM(I24:O24) -> 0
C25: ='Orçamento Familiar'!C25 -> Projeto 6 | E25: ='Orçamento Familiar'!E25 -> 0 | F25: =P25 -> 0 | G25: =F25-E25 -> 0 | P25: =SUM(I25:O25) -> 0
C26: ='Orçamento Familiar'!C26 -> Independência Financeira | E26: ='Orçamento Familiar'!E26 -> 0 | F26: =P26 -> 0 | G26: =F26-E26 -> 0 | P26: =SUM(I26:O26) -> 0
C27: Total Investimentos | D27: =SUM(D19:D26) -> 0 | E27: =SUM(E19:E26) -> 0 | F27: =SUM(F19:F26) -> 0 | G27: =SUM(G19:G26) -> 0 | I27: =SUM(I19:I26) -> 0 | J27: =SUM(J19:J26) -> 0 | K27: =SUM(K19:K26) -> 0 | L27: =SUM(L19:L26) -> 0 | M27: =SUM(M19:M26) -> 0 | N27: =SUM(N19:N26) -> 0 | O27: =SUM(O19:O26) -> 0 | P27: =SUM(P19:P26) -> 0
C28: % sobre Receita | E28: =E27/E16 -> 0 | F28: =F27/F16 -> 0 | I28: =I27/I16 -> 0 | J28: =J27/J16 -> #DIV/0! | K28: =K27/K16 -> 0 | L28: =L27/L16 -> 0 | M28: =M27/M16 -> #DIV/0! | N28: =N27/N16 -> #DIV/0! | O28: =O27/O16 -> #DIV/0! | P28: =P27/P16 -> 0
A30: Categoria | C30: Descrição | D30: Percentual | E30: Orçado | F30: Realizado | G30: Variação | I30: =I18 -> Semana 1 | J30: =J18 -> Semana 2 | K30: =K18 -> Semana 3 | L30: =L18 -> Semana 4 | M30: =M18 -> Semana 5 | N30: =N6 -> Cartão Nubank | O30: =O6 -> Cartão C & A | P30: =P18 -> Total
A31: Despesas Essenciais | B31: Moradia | C31: ='Orçamento Familiar'!C31 -> Aluguel | E31: ='Orçamento Familiar'!E31 -> 0 | F31: =P31 -> 0 | G31: =E31-F31 -> 0 | P31: =SUM(I31:O31) -> 0
C32: ='Orçamento Familiar'!C32 -> Energia Elétrica | E32: ='Orçamento Familiar'!E32 -> 0 | F32: =P32 -> 0 | G32: =E32-F32 -> 0 | P32: =SUM(I32:O32) -> 0
C33: ='Orçamento Familiar'!C33 -> Água e Esgoto | E33: ='Orçamento Familiar'!E33 -> 0 | F33: =P33 -> 0 | G33: =E33-F33 -> 0 | P33: =SUM(I33:O33) -> 0
C34: ='Orçamento Familiar'!C34 -> Gás | E34: ='Orçamento Familiar'!E34 -> 0 | F34: =P34 -> 0 | G34: =E34-F34 -> 0 | P34: =SUM(I34:O34) -> 0
C35: ='Orçamento Familiar'!C35 -> Internet e Celular | E35: ='Orçamento Familiar'!E35 -> 125 | F35: =P35 -> 0 | G35: =E35-F35 -> 125 | P35: =SUM(I35:O35) -> 0
C36: ='Orçamento Familiar'!C36 -> Manutenção | E36: ='Orçamento Familiar'!E36 -> 0 | F36: =P36 -> 0 | G36: =E36-F36 -> 0 | P36: =SUM(I36:O36) -> 0
C37: ='Orçamento Familiar'!C37 -> 0 | E37: ='Orçamento Familiar'!E37 -> 0 | F37: =P37 -> 0 | G37: =E37-F37 -> 0 | P37: =SUM(I37:O37) -> 0
C38: ='Orçamento Familiar'!C38 -> 0 | E38: ='Orçamento Familiar'!E38 -> 0 | F38: =P38 -> 0 | G38: =E38-F38 -> 0 | P38: =SUM(I38:O38) -> 0
C39: ='Orçamento Familiar'!C39 -> 0 | E39: ='Orçamento Familiar'!E39 -> 0 | F39: =P39 -> 0 | G39: =E39-F39 -> 0 | P39: =SUM(I39:O39) -> 0
B40: Alimentação | C40: ='Orçamento Familiar'!C40 -> Supermercado | E40: ='Orçamento Familiar'!E40 -> 3100 | F40: =P40 -> 1942.99 | G40: =E40-F40 -> 1157.01 | I40: 313 | J40: 329.03 | K40: =339.97+129 -> 468.97 | L40: 467.43 | M40: 364.56 | P40: =SUM(I40:O40) -> 1942.99
C41: ='Orçamento Familiar'!C41 -> 0 | E41: ='Orçamento Familiar'!E41 -> 0 | F41: =P41 -> 0 | G41: =E41-F41 -> 0 | P41: =SUM(I41:O41) -> 0
C42: ='Orçamento Familiar'!C42 -> 0 | E42: ='Orçamento Familiar'!E42 -> 0 | F42: =P42 -> 0 | G42: =E42-F42 -> 0 | P42: =SUM(I42:O42) -> 0
C43: ='Orçamento Familiar'!C43 -> 0 | E43: ='Orçamento Familiar'!E43 -> 0 | F43: =P43 -> 0 | G43: =E43-F43 -> 0 | P43: =SUM(I43:O43) -> 0
C44: ='Orçamento Familiar'!C44 -> 0 | E44: ='Orçamento Familiar'!E44 -> 0 | F44: =P44 -> 0 | G44: =E44-F44 -> 0 | P44: =SUM(I44:O44) -> 0
C45: ='Orçamento Familiar'!C45 -> 0 | E45: ='Orçamento Familiar'!E45 -> 0 | F45: =P45 -> 0 | G45: =E45-F45 -> 0 | P45: =SUM(I45:O45) -> 0
B46: Transporte | C46: ='Orçamento Familiar'!C46 -> Combustível | E46: ='Orçamento Familiar'!E46 -> 400 | F46: =P46 -> 75 | G46: =E46-F46 -> 325 | I46: 35 | N46: 40 | P46: =SUM(I46:O46) -> 75
C47: ='Orçamento Familiar'!C47 -> Manutenção | E47: =Jan!I47 -> 61.38 | F47: =P47 -> 1612.44 | G47: =E47-F47 -> -1551.06 | I47: 61.38 | K47: 18.5 | N47: 1532.56 | P47: =SUM(I47:O47) -> 1612.44 | Q47: 430,90 =1/6 + 891,68 =2/3 + 100,00=2/3
C48: ='Orçamento Familiar'!C48 -> Multas | E48: ='Orçamento Familiar'!E48 -> 0 | F48: =P48 -> 0 | G48: =E48-F48 -> 0 | P48: =SUM(I48:O48) -> 0
C49: ='Orçamento Familiar'!C49 -> Seguro | E49: ='Orçamento Familiar'!E49 -> 0 | F49: =P49 -> 0 | G49: =E49-F49 -> 0 | P49: =SUM(I49:O49) -> 0
C50: ='Orçamento Familiar'!C50 -> Lavagem | E50: ='Orçamento Familiar'!E50 -> 0 | F50: =P50 -> 0 | G50: =E50-F50 -> 0 | P50: =SUM(I50:O50) -> 0
C51: ='Orçamento Familiar'!C51 -> Estacionamento | E51: ='Orçamento Familiar'!E51 -> 0 | F51: =P51 -> 0 | G51: =E51-F51 -> 0 | P51: =SUM(I51:O51) -> 0
C52: ='Orçamento Familiar'!C52 -> Taxi / Uber | E52: ='Orçamento Familiar'!E52 -> 0 | F52: =P52 -> 0 | G52: =E52-F52 -> 0 | P52: =SUM(I52:O52) -> 0
C53: ='Orçamento Familiar'!C53 -> 0 | E53: ='Orçamento Familiar'!E53 -> 0 | F53: =P53 -> 0 | G53: =E53-F53 -> 0 | P53: =SUM(I53:O53) -> 0
C54: ='Orçamento Familiar'!C54 -> 0 | E54: ='Orçamento Familiar'!E54 -> 0 | F54: =P54 -> 0 | G54: =E54-F54 -> 0 | P54: =SUM(I54:O54) -> 0
B55: Saúde | C55: ='Orçamento Familiar'!C55 -> Medicamentos | E55: ='Orçamento Familiar'!E55 -> 80 | F55: =P55 -> 31.62 | G55: =E55-F55 -> 48.38 | I55: 15.63 | K55: 15.99 | P55: =SUM(I55:O55) -> 31.62
C56: ='Orçamento Familiar'!C56 -> Médicos / Exames | E56: ='Orçamento Familiar'!E56 -> 0 | F56: =P56 -> 0 | G56: =E56-F56 -> 0 | P56: =SUM(I56:O56) -> 0
C57: ='Orçamento Familiar'!C57 -> Dentista | E57: ='Orçamento Familiar'!E57 -> 0 | F57: =P57 -> 0 | G57: =E57-F57 -> 0 | P57: =SUM(I57:O57) -> 0
C58: ='Orçamento Familiar'!C58 -> 0 | E58: ='Orçamento Familiar'!E58 -> 0 | F58: =P58 -> 0 | G58: =E58-F58 -> 0 | P58: =SUM(I58:O58) -> 0
C59: ='Orçamento Familiar'!C59 -> 0 | E59: ='Orçamento Familiar'!E59 -> 0 | F59: =P59 -> 0 | G59: =E59-F59 -> 0 | P59: =SUM(I59:O59) -> 0
B60: Impostos | C60: ='Orçamento Familiar'!C60 -> IPVA | E60: ='Orçamento Familiar'!E60 -> 210 | F60: =P60 -> 210.5 | G60: =E60-F60 -> -0.5 | K60: 210.5 | P60: =SUM(I60:O60) -> 210.5
C61: ='Orçamento Familiar'!C61 -> Licenciamento | E61: ='Orçamento Familiar'!E61 -> 0 | F61: =P61 -> 0 | G61: =E61-F61 -> 0 | P61: =SUM(I61:O61) -> 0
C62: ='Orçamento Familiar'!C62 -> Imposto de Renda | E62: ='Orçamento Familiar'!E62 -> 0 | F62: =P62 -> 0 | G62: =E62-F62 -> 0 | P62: =SUM(I62:O62) -> 0
C63: ='Orçamento Familiar'!C63 -> INSS | E63: ='Orçamento Familiar'!E63 -> 0 | F63: =P63 -> 0 | G63: =E63-F63 -> 0 | P63: =SUM(I63:O63) -> 0
C64: ='Orçamento Familiar'!C64 -> 0 | E64: ='Orçamento Familiar'!E64 -> 0 | F64: =P64 -> 0 | G64: =E64-F64 -> 0 | P64: =SUM(I64:O64) -> 0
C65: ='Orçamento Familiar'!C65 -> 0 | E65: ='Orçamento Familiar'!E65 -> 0 | F65: =P65 -> 0 | G65: =E65-F65 -> 0 | P65: =SUM(I65:O65) -> 0
B66: Educação | C66: ='Orçamento Familiar'!C66 -> Especialização | E66: ='Orçamento Familiar'!E66 -> 0 | F66: =P66 -> 0 | G66: =E66-F66 -> 0 | P66: =SUM(I66:O66) -> 0
C67: ='Orçamento Familiar'!C67 -> Cursos | E67: ='Orçamento Familiar'!E67 -> 0 | F67: =P67 -> 0 | G67: =E67-F67 -> 0 | P67: =SUM(I67:O67) -> 0
C68: ='Orçamento Familiar'!C68 -> Mentoria Financeira | E68: ='Orçamento Familiar'!E68 -> 200 | F68: =P68 -> 200 | G68: =E68-F68 -> 0 | I68: 200 | P68: =SUM(I68:O68) -> 200
C69: ='Orçamento Familiar'!C69 -> 0 | E69: ='Orçamento Familiar'!E69 -> 0 | F69: =P69 -> 0 | G69: =E69-F69 -> 0 | P69: =SUM(I69:O69) -> 0
C70: ='Orçamento Familiar'!C70 -> 0 | E70: ='Orçamento Familiar'!E70 -> 0 | F70: =P70 -> 0 | G70: =E70-F70 -> 0 | P70: =SUM(I70:O70) -> 0
B71: Filhos | C71: ='Orçamento Familiar'!C71 -> Piano Laura | E71: ='Orçamento Familiar'!E71 -> 0 | F71: =P71 -> 0 | G71: =E71-F71 -> 0 | P71: =SUM(I71:O71) -> 0
C72: ='Orçamento Familiar'!C72 -> Material Escolar | E72: ='Orçamento Familiar'!E72 -> 0 | F72: =P72 -> 0 | G72: =E72-F72 -> 0 | P72: =SUM(I72:O72) -> 0
C73: ='Orçamento Familiar'!C73 -> Mesadas | E73: ='Orçamento Familiar'!E73 -> 410 | F73: =P73 -> 221.73 | G73: =E73-F73 -> 188.27 | I73: 48.9 | J73: 120 | L73: 52.83 | P73: =SUM(I73:O73) -> 221.73 | Q73: 120,00 – Clube Laura = 52,83 - exame habilit.
C74: ='Orçamento Familiar'!C74 -> Violão | E74: ='Orçamento Familiar'!E74 -> 0 | F74: =P74 -> 0 | G74: =E74-F74 -> 0 | P74: =SUM(I74:O74) -> 0
C75: ='Orçamento Familiar'!C75 -> Médicos / Exames | E75: ='Orçamento Familiar'!E75 -> 0 | F75: =P75 -> 0 | G75: =E75-F75 -> 0 | P75: =SUM(I75:O75) -> 0
C76: ='Orçamento Familiar'!C76 -> Cursos | E76: ='Orçamento Familiar'!E76 -> 0 | F76: =P76 -> 0 | G76: =E76-F76 -> 0 | P76: =SUM(I76:O76) -> 0
C77: ='Orçamento Familiar'!C77 -> Retiro Carnaval 2026/2027 | E77: ='Orçamento Familiar'!E77 -> 0 | F77: =P77 -> 0 | G77: =E77-F77 -> 0 | P77: =SUM(I77:O77) -> 0
C78: ='Orçamento Familiar'!C78 -> Acampadentro | E78: ='Orçamento Familiar'!E78 -> 0 | F78: =P78 -> 0 | G78: =E78-F78 -> 0 | P78: =SUM(I78:O78) -> 0
C79: ='Orçamento Familiar'!C79 -> 0 | E79: ='Orçamento Familiar'!E79 -> 0 | F79: =P79 -> 0 | G79: =E79-F79 -> 0 | P79: =SUM(I79:O79) -> 0
B80: Pet | C80: ='Orçamento Familiar'!C80 -> Ração | E80: ='Orçamento Familiar'!E80 -> 50 | F80: =P80 -> 0 | G80: =E80-F80 -> 50 | P80: =SUM(I80:O80) -> 0
C81: ='Orçamento Familiar'!C81 -> Vacinas | E81: ='Orçamento Familiar'!E81 -> 0 | F81: =P81 -> 0 | G81: =E81-F81 -> 0 | P81: =SUM(I81:O81) -> 0
C82: ='Orçamento Familiar'!C82 -> Veterinário | E82: ='Orçamento Familiar'!E83 -> 0 | F82: =P82 -> 0 | G82: =E82-F82 -> 0 | P82: =SUM(I82:O82) -> 0
C83: ='Orçamento Familiar'!C83 -> 0 | E83: ='Orçamento Familiar'!E83 -> 0 | F83: =P83 -> 0 | G83: =E83-F83 -> 0 | P83: =SUM(I83:O83) -> 0
C84: ='Orçamento Familiar'!C84 -> 0 | E84: ='Orçamento Familiar'!E84 -> 0 | F84: =P84 -> 0 | G84: =E84-F84 -> 0 | P84: =SUM(I84:O84) -> 0
B85: Total Despesas Essenciais | E85: =SUM(E31:E84) -> 4636.38 | F85: =SUM(F31:F84) -> 4294.28 | G85: =SUM(G31:G84) -> 342.1 | I85: =SUM(I31:I84) -> 673.91 | J85: =SUM(J31:J84) -> 449.03 | K85: =SUM(K31:K84) -> 713.96 | L85: =SUM(L31:L84) -> 520.26 | M85: =SUM(M31:M84) -> 364.56 | N85: =SUM(N31:N84) -> 1572.56 | O85: =SUM(O31:O84) -> 0 | P85: =SUM(P31:P84) -> 4294.28
B86: % sobre Receita | C86: ='Orçamento Familiar'!C166 -> 0 | E86: =E85/E16 -> 0.61360244 | F86: =F85/F16 -> 0.48793092 | I86: =I85/I16 -> 0.10004602 | J86: =J85/J16 -> #DIV/0! | K86: =K85/K16 -> 0.37088831 | L86: =L85/L16 -> 3.7161429 | M86: =M85/M16 -> #DIV/0! | N86: =N85/N16 -> #DIV/0! | O86: =O85/O16 -> #DIV/0! | P86: =P85/P16 -> 0.48793092
A87: Profissional e Trabalho | B87: Ministério | C87: ='Orçamento Familiar'!C87 -> Materiais (livros) | E87: ='Orçamento Familiar'!E87 -> 0 | F87: =P87 -> 0 | G87: =E87-F87 -> 0 | P87: =SUM(I87:O87) -> 0
C88: ='Orçamento Familiar'!C88 -> 0 | E88: ='Orçamento Familiar'!E88 -> 0 | F88: =P88 -> 0 | G88: =E88-F88 -> 0 | P88: =SUM(I88:O88) -> 0
C89: ='Orçamento Familiar'!C89 -> 0 | E89: ='Orçamento Familiar'!E89 -> 0 | F89: =P89 -> 0 | G89: =E89-F89 -> 0 | P89: =SUM(I89:O89) -> 0
C90: ='Orçamento Familiar'!C90 -> 0 | E90: ='Orçamento Familiar'!E90 -> 0 | F90: =P90 -> 0 | G90: =E90-F90 -> 0 | P90: =SUM(I90:O90) -> 0
C91: ='Orçamento Familiar'!C91 -> 0 | E91: ='Orçamento Familiar'!E91 -> 0 | F91: =P91 -> 0 | G91: =E91-F91 -> 0 | P91: =SUM(I91:O91) -> 0
C92: ='Orçamento Familiar'!C92 -> 0 | E92: ='Orçamento Familiar'!E92 -> 0 | F92: =P92 -> 0 | G92: =E92-F92 -> 0 | P92: =SUM(I92:O92) -> 0
B93: Autônomo | C93: ='Orçamento Familiar'!C93 -> Ferramentas de trabalho | E93: ='Orçamento Familiar'!E93 -> 50 | F93: =P93 -> 207.35 | G93: =E93-F93 -> -157.35 | N93: 207.35 | P93: =SUM(I93:O93) -> 207.35 | Q93: 51,40=9/12
C94: ='Orçamento Familiar'!C94 -> Colaboradores | E94: ='Orçamento Familiar'!E94 -> 140 | F94: =P94 -> 200.82 | G94: =E94-F94 -> -60.82 | I94: 140 | N94: 60.82 | P94: =SUM(I94:O94) -> 200.82 | Q94: 60,82=5/11
C95: ='Orçamento Familiar'!C95 -> 0 | E95: ='Orçamento Familiar'!E95 -> 0 | F95: =P95 -> 0 | G95: =E95-F95 -> 0 | P95: =SUM(I95:O95) -> 0
C96: ='Orçamento Familiar'!C96 -> 0 | E96: ='Orçamento Familiar'!E96 -> 0 | F96: =P96 -> 0 | G96: =E96-F96 -> 0 | P96: =SUM(I96:O96) -> 0
C97: ='Orçamento Familiar'!C97 -> 0 | E97: ='Orçamento Familiar'!E97 -> 0 | F97: =P97 -> 0 | G97: =E97-F97 -> 0 | P97: =SUM(I97:O97) -> 0
C98: ='Orçamento Familiar'!C98 -> 0 | E98: ='Orçamento Familiar'!E98 -> 0 | F98: =P98 -> 0 | G98: =E98-F98 -> 0 | P98: =SUM(I98:O98) -> 0
B99: Total Profissional e Trabalho | E99: =SUM(E87:E98) -> 190 | F99: =SUM(F87:F98) -> 408.17 | G99: =SUM(G87:G98) -> -218.17 | I99: =SUM(I87:I98) -> 140 | J99: =SUM(J87:J98) -> 0 | K99: =SUM(K87:K98) -> 0 | L99: =SUM(L87:L98) -> 0 | M99: =SUM(M87:M98) -> 0 | N99: =SUM(N87:N98) -> 268.17 | O99: =SUM(O87:O98) -> 0 | P99: =SUM(P87:P98) -> 408.17
B100: % sobre Receita | E100: =E99/E16 -> 0.02514558 | F100: =F99/F16 -> 0.046377684 | I100: =I99/I16 -> 0.020783848 | J100: =J99/J16 -> #DIV/0! | K100: =K99/K16 -> 0 | L100: =L99/L16 -> 0 | M100: =M99/M16 -> #DIV/0! | N100: =N99/N16 -> #DIV/0! | O100: =O99/O16 -> #DIV/0! | P100: =P99/P16 -> 0.046377684
A101: Contribuição | B101: Ofertas | C101: ='Orçamento Familiar'!C101 -> Dízimo | E101: ='Orçamento Familiar'!E101 -> 700 | F101: =P101 -> 700 | G101: =E101-F101 -> 0 | I101: 700 | P101: =SUM(I101:O101) -> 700
C102: ='Orçamento Familiar'!C102 -> Sacrificial | E102: ='Orçamento Familiar'!E102 -> 0 | F102: =P102 -> 0 | G102: =E102-F102 -> 0 | P102: =SUM(I102:O102) -> 0
C103: ='Orçamento Familiar'!C103 -> Doações | E103: ='Orçamento Familiar'!E103 -> 0 | F103: =P103 -> 0 | G103: =E103-F103 -> 0 | P103: =SUM(I103:O103) -> 0
C104: ='Orçamento Familiar'!C104 -> 0 | E104: ='Orçamento Familiar'!E104 -> 0 | F104: =P104 -> 0 | G104: =E104-F104 -> 0 | P104: =SUM(I104:O104) -> 0
B105: Total Contribuição | E105: =SUM(E101:E104) -> 700 | F105: =SUM(F101:F104) -> 700 | G105: =SUM(G101:G104) -> 0 | I105: =SUM(I101:I104) -> 700 | J105: =SUM(J101:J104) -> 0 | K105: =SUM(K101:K104) -> 0 | L105: =SUM(L101:L104) -> 0 | M105: =SUM(M101:M104) -> 0 | N105: =SUM(N101:N104) -> 0 | O105: =SUM(O101:O104) -> 0 | P105: =SUM(P101:P104) -> 700
...

Sheet Fev
A2: Fluxo de Caixa Familiar
A5: Categoria | C5: Descrição | D5: Percentual | E5: =I5 -> Fevereiro | I5: Fevereiro
E6: Orçado | F6: Realizado | G6: Variação | I6: Semana 1 | J6: Semana 2 | K6: Semana 3 | L6: Semana 4 | M6: Semana 5 | N6: =Jan!N6 -> Cartão Nubank | O6: =Jan!O6 -> Cartão C & A | P6: Total
A7: Receitas | C7: ='Orçamento Familiar'!C7 -> Prebenda | E7: ='Orçamento Familiar'!F7 -> 7216 | F7: =P7 -> 5716 | G7: =F7-E7 -> -1500 | I7: 5716 | P7: =SUM(I7:O7) -> 5716
C8: ='Orçamento Familiar'!C8 -> Inglês | E8: ='Orçamento Familiar'!F8 -> 340 | F8: =P8 -> 335 | G8: =F8-E8 -> -5 | I8: 200 | L8: 135 | P8: =SUM(I8:O8) -> 335
C9: ='Orçamento Familiar'!C9 -> 13º Salário | E9: ='Orçamento Familiar'!F9 -> 0 | F9: =P9 -> 0 | G9: =F9-E9 -> 0 | P9: =SUM(I9:O9) -> 0
C10: ='Orçamento Familiar'!C10 -> Renda Extra | E10: ='Orçamento Familiar'!F10 -> 0 | F10: =P10 -> 1248 | G10: =F10-E10 -> 1248 | J10: 300 | K10: 460 | L10: 160 | M10: 328 | P10: =SUM(I10:O10) -> 1248 | Q10: Faxina japonês=300,00/ renda Eric 660,00 / 160,00=OFERTA / Eric=328,00
C11: ='Orçamento Familiar'!C11 -> 0 | E11: ='Orçamento Familiar'!F11 -> 0 | F11: =P11 -> 0 | G11: =F11-E11 -> 0 | P11: =SUM(I11:O11) -> 0
C12: ='Orçamento Familiar'!C12 -> 0 | E12: ='Orçamento Familiar'!F12 -> 0 | F12: =P12 -> 0 | G12: =F12-E12 -> 0 | P12: =SUM(I12:O12) -> 0
C13: ='Orçamento Familiar'!C13 -> 0 | E13: ='Orçamento Familiar'!F13 -> 0 | F13: =P13 -> 1500 | G13: =F13-E13 -> 1500 | J13: 1500 | P13: =SUM(I13:O13) -> 1500
C14: ='Orçamento Familiar'!C14 -> 0 | E14: ='Orçamento Familiar'!F14 -> 0 | F14: =P14 -> 0 | G14: =F14-E14 -> 0 | P14: =SUM(I14:O14) -> 0
C15: ='Orçamento Familiar'!C15 -> 0 | E15: ='Orçamento Familiar'!F15 -> 0 | F15: =P15 -> 0 | G15: =F15-E15 -> 0 | P15: =SUM(I15:O15) -> 0
C16: Total | E16: =SUM(E7:E15) -> 7556 | F16: =SUM(F7:F15) -> 8799 | G16: =SUM(G7:G15) -> 1243 | I16: =SUM(I7:I15) -> 5916 | J16: =SUM(J7:J15) -> 1800 | K16: =SUM(K7:K15) -> 460 | L16: =SUM(L7:L15) -> 295 | M16: =SUM(M7:M15) -> 328 | N16: =SUM(N7:N15) -> 0 | O16: =SUM(O7:O15) -> 0 | P16: =SUM(P7:P15) -> 8799
A18: Investimentos Insira aqui o montante mensal que você destinará aos seus investimentos | C18: Descrição | D18: Percentual | E18: Orçado | F18: Realizado | G18: Variação | I18: =I6 -> Semana 1 | J18: =J6 -> Semana 2 | K18: =K6 -> Semana 3 | L18: =L6 -> Semana 4 | M18: =M6 -> Semana 5 | P18: =P6 -> Total
C19: ='Orçamento Familiar'!C19 -> Reserva de Emergência (CP) R$ 9.151 | E19: ='Orçamento Familiar'!F19 -> 0 | F19: =P19 -> 0 | G19: =F19-E19 -> 0 | P19: =SUM(I19:O19) -> 0
C20: ='Orçamento Familiar'!C20 -> Projeto 1 | E20: ='Orçamento Familiar'!F20 -> 0 | F20: =P20 -> 0 | G20: =F20-E20 -> 0 | P20: =SUM(I20:O20) -> 0
C21: ='Orçamento Familiar'!C21 -> Projeto 2 | E21: ='Orçamento Familiar'!F21 -> 0 | F21: =P21 -> 0 | G21: =F21-E21 -> 0 | P21: =SUM(I21:O21) -> 0
C22: ='Orçamento Familiar'!C22 -> Projeto 3 | E22: ='Orçamento Familiar'!F22 -> 0 | F22: =P22 -> 0 | G22: =F22-E22 -> 0 | P22: =SUM(I22:O22) -> 0
C23: ='Orçamento Familiar'!C23 -> Projeto 4 | E23: ='Orçamento Familiar'!F23 -> 0 | F23: =P23 -> 0 | G23: =F23-E23 -> 0 | P23: =SUM(I23:O23) -> 0
C24: ='Orçamento Familiar'!C24 -> Projeto 5 | E24: ='Orçamento Familiar'!F24 -> 0 | F24: =P24 -> 0 | G24: =F24-E24 -> 0 | P24: =SUM(I24:O24) -> 0
C25: ='Orçamento Familiar'!C25 -> Projeto 6 | E25: ='Orçamento Familiar'!F25 -> 0 | F25: =P25 -> 0 | G25: =F25-E25 -> 0 | P25: =SUM(I25:O25) -> 0
C26: ='Orçamento Familiar'!C26 -> Independência Financeira | E26: ='Orçamento Familiar'!F26 -> 0 | F26: =P26 -> 0 | G26: =F26-E26 -> 0 | P26: =SUM(I26:O26) -> 0
C27: Total Investimentos | D27: =SUM(D19:D26) -> 0 | E27: =SUM(E19:E26) -> 0 | F27: =SUM(F19:F26) -> 0 | G27: =SUM(G19:G26) -> 0 | I27: =SUM(I19:I26) -> 0 | J27: =SUM(J19:J26) -> 0 | K27: =SUM(K19:K26) -> 0 | L27: =SUM(L19:L26) -> 0 | M27: =SUM(M19:M26) -> 0 | N27: =SUM(N19:N26) -> 0 | O27: =SUM(O19:O26) -> 0 | P27: =SUM(P19:P26) -> 0
C28: % sobre Receita | E28: =E27/E16 -> 0 | F28: =F27/F16 -> 0 | I28: =I27/I16 -> 0 | J28: =J27/J16 -> 0 | K28: =K27/K16 -> 0 | L28: =L27/L16 -> 0 | M28: =M27/M16 -> 0 | N28: =N27/N16 -> #DIV/0! | O28: =O27/O16 -> #DIV/0! | P28: =P27/P16 -> 0
A30: Categoria | C30: Descrição | D30: Percentual | E30: Orçado | F30: Realizado | G30: Variação | I30: =I18 -> Semana 1 | J30: =J18 -> Semana 2 | K30: =K18 -> Semana 3 | L30: =L18 -> Semana 4 | M30: =M18 -> Semana 5 | N30: =N6 -> Cartão Nubank | O30: =O6 -> Cartão C & A | P30: =P18 -> Total
A31: Despesas Essenciais | B31: Moradia | C31: ='Orçamento Familiar'!C31 -> Aluguel | E31: ='Orçamento Familiar'!F31 -> 0 | F31: =P31 -> 0 | G31: =E31-F31 -> 0 | P31: =SUM(I31:O31) -> 0
C32: ='Orçamento Familiar'!C32 -> Energia Elétrica | E32: ='Orçamento Familiar'!F32 -> 0 | F32: =P32 -> 0 | G32: =E32-F32 -> 0 | P32: =SUM(I32:O32) -> 0
C33: ='Orçamento Familiar'!C33 -> Água e Esgoto | E33: ='Orçamento Familiar'!F33 -> 0 | F33: =P33 -> 0 | G33: =E33-F33 -> 0 | P33: =SUM(I33:O33) -> 0
C34: ='Orçamento Familiar'!C34 -> Gás | E34: ='Orçamento Familiar'!F34 -> 0 | F34: =P34 -> 0 | G34: =E34-F34 -> 0 | P34: =SUM(I34:O34) -> 0
C35: ='Orçamento Familiar'!C35 -> Internet e Celular | E35: ='Orçamento Familiar'!F35 -> 125 | F35: =P35 -> 185.7 | G35: =E35-F35 -> -60.7 | N35: 185.7 | P35: =SUM(I35:O35) -> 185.7
C36: ='Orçamento Familiar'!C36 -> Manutenção | E36: ='Orçamento Familiar'!F36 -> 0 | F36: =P36 -> 60 | G36: =E36-F36 -> -60 | I36: 60 | P36: =SUM(I36:O36) -> 60
C37: ='Orçamento Familiar'!C37 -> 0 | E37: ='Orçamento Familiar'!F37 -> 0 | F37: =P37 -> 69 | G37: =E37-F37 -> -69 | I37: 69 | P37: =SUM(I37:O37) -> 69
C38: ='Orçamento Familiar'!C38 -> 0 | E38: ='Orçamento Familiar'!F38 -> 0 | F38: =P38 -> 0 | G38: =E38-F38 -> 0 | P38: =SUM(I38:O38) -> 0
C39: ='Orçamento Familiar'!C39 -> 0 | E39: ='Orçamento Familiar'!F39 -> 0 | F39: =P39 -> 0 | G39: =E39-F39 -> 0 | P39: =SUM(I39:O39) -> 0
B40: Alimentação | C40: ='Orçamento Familiar'!C40 -> Supermercado | E40: ='Orçamento Familiar'!F40 -> 3100 | F40: =P40 -> 3370.53 | G40: =E40-F40 -> -270.53 | I40: =644.79+42 -> 686.79 | J40: =1100+30.85 -> 1130.85 | K40: =615.88+103.98 -> 719.86 | L40: =287.35+80 -> 367.35 | M40: 379.21 | N40: 86.47 | P40: =SUM(I40:O40) -> 3370.53
C41: ='Orçamento Familiar'!C41 -> 0 | E41: ='Orçamento Familiar'!F41 -> 0 | F41: =P41 -> 0 | G41: =E41-F41 -> 0 | P41: =SUM(I41:O41) -> 0
C42: ='Orçamento Familiar'!C42 -> 0 | E42: ='Orçamento Familiar'!F42 -> 0 | F42: =P42 -> 0 | G42: =E42-F42 -> 0 | P42: =SUM(I42:O42) -> 0
C43: ='Orçamento Familiar'!C43 -> 0 | E43: ='Orçamento Familiar'!F43 -> 0 | F43: =P43 -> 0 | G43: =E43-F43 -> 0 | P43: =SUM(I43:O43) -> 0
C44: ='Orçamento Familiar'!C44 -> 0 | E44: ='Orçamento Familiar'!F44 -> 0 | F44: =P44 -> 0 | G44: =E44-F44 -> 0 | P44: =SUM(I44:O44) -> 0
C45: ='Orçamento Familiar'!C45 -> 0 | E45: ='Orçamento Familiar'!F45 -> 0 | F45: =P45 -> 0 | G45: =E45-F45 -> 0 | P45: =SUM(I45:O45) -> 0
B46: Transporte | C46: ='Orçamento Familiar'!C46 -> Combustível | E46: ='Orçamento Familiar'!F46 -> 400 | F46: =P46 -> 483 | G46: =E46-F46 -> -83 | I46: 100 | J46: 198 | L46: 90 | N46: 95 | P46: =SUM(I46:O46) -> 483
C47: ='Orçamento Familiar'!C47 -> Manutenção | E47: ='Orçamento Familiar'!F47 -> 1430 | F47: =P47 -> 1422.58 | G47: =E47-F47 -> 7.42 | N47: 1422.58 | P47: =SUM(I47:O47) -> 1422.58 | Q47: 430,90 =2/6 + 891,68 =3/3 + 100,00=3/3
C48: ='Orçamento Familiar'!C48 -> Multas | E48: ='Orçamento Familiar'!F48 -> 0 | F48: =P48 -> 0 | G48: =E48-F48 -> 0 | P48: =SUM(I48:O48) -> 0
C49: ='Orçamento Familiar'!C49 -> Seguro | E49: ='Orçamento Familiar'!F49 -> 0 | F49: =P49 -> 0 | G49: =E49-F49 -> 0 | P49: =SUM(I49:O49) -> 0
C50: ='Orçamento Familiar'!C50 -> Lavagem | E50: ='Orçamento Familiar'!F50 -> 0 | F50: =P50 -> 0 | G50: =E50-F50 -> 0 | P50: =SUM(I50:O50) -> 0
C51: ='Orçamento Familiar'!C51 -> Estacionamento | E51: ='Orçamento Familiar'!F51 -> 0 | F51: =P51 -> 0 | G51: =E51-F51 -> 0 | P51: =SUM(I51:O51) -> 0
C52: ='Orçamento Familiar'!C52 -> Taxi / Uber | E52: ='Orçamento Familiar'!F52 -> 0 | F52: =P52 -> 0 | G52: =E52-F52 -> 0 | P52: =SUM(I52:O52) -> 0
C53: ='Orçamento Familiar'!C53 -> 0 | E53: ='Orçamento Familiar'!F53 -> 0 | F53: =P53 -> 0 | G53: =E53-F53 -> 0 | P53: =SUM(I53:O53) -> 0
C54: ='Orçamento Familiar'!C54 -> 0 | E54: ='Orçamento Familiar'!F54 -> 0 | F54: =P54 -> 0 | G54: =E54-F54 -> 0 | P54: =SUM(I54:O54) -> 0
B55: Saúde | C55: ='Orçamento Familiar'!C55 -> Medicamentos | E55: ='Orçamento Familiar'!F55 -> 80 | F55: =P55 -> 50.63 | G55: =E55-F55 -> 29.37 | L55: 50.63 | P55: =SUM(I55:O55) -> 50.63
C56: ='Orçamento Familiar'!C56 -> Médicos / Exames | E56: ='Orçamento Familiar'!F56 -> 0 | F56: =P56 -> 0 | G56: =E56-F56 -> 0 | P56: =SUM(I56:O56) -> 0
C57: ='Orçamento Familiar'!C57 -> Dentista | E57: ='Orçamento Familiar'!F57 -> 0 | F57: =P57 -> 0 | G57: =E57-F57 -> 0 | P57: =SUM(I57:O57) -> 0
C58: ='Orçamento Familiar'!C58 -> 0 | E58: ='Orçamento Familiar'!F58 -> 0 | F58: =P58 -> 0 | G58: =E58-F58 -> 0 | P58: =SUM(I58:O58) -> 0
C59: ='Orçamento Familiar'!C59 -> 0 | E59: ='Orçamento Familiar'!F59 -> 0 | F59: =P59 -> 0 | G59: =E59-F59 -> 0 | P59: =SUM(I59:O59) -> 0
B60: Impostos | C60: ='Orçamento Familiar'!C60 -> IPVA | E60: ='Orçamento Familiar'!F60 -> 0 | F60: =P60 -> 0 | G60: =E60-F60 -> 0 | P60: =SUM(I60:O60) -> 0
C61: ='Orçamento Familiar'!C61 -> Licenciamento | E61: ='Orçamento Familiar'!F61 -> 0 | F61: =P61 -> 0 | G61: =E61-F61 -> 0 | P61: =SUM(I61:O61) -> 0
C62: ='Orçamento Familiar'!C62 -> Imposto de Renda | E62: ='Orçamento Familiar'!F62 -> 0 | F62: =P62 -> 0 | G62: =E62-F62 -> 0 | P62: =SUM(I62:O62) -> 0
C63: ='Orçamento Familiar'!C63 -> INSS | E63: ='Orçamento Familiar'!F63 -> 0 | F63: =P63 -> 0 | G63: =E63-F63 -> 0 | P63: =SUM(I63:O63) -> 0
C64: ='Orçamento Familiar'!C64 -> 0 | E64: ='Orçamento Familiar'!F64 -> 0 | F64: =P64 -> 0 | G64: =E64-F64 -> 0 | P64: =SUM(I64:O64) -> 0
C65: ='Orçamento Familiar'!C65 -> 0 | E65: ='Orçamento Familiar'!F65 -> 0 | F65: =P65 -> 0 | G65: =E65-F65 -> 0 | P65: =SUM(I65:O65) -> 0
B66: Educação | C66: ='Orçamento Familiar'!C66 -> Especialização | E66: ='Orçamento Familiar'!F66 -> 0 | F66: =P66 -> 0 | G66: =E66-F66 -> 0 | P66: =SUM(I66:O66) -> 0
C67: ='Orçamento Familiar'!C67 -> Cursos | E67: ='Orçamento Familiar'!F67 -> 0 | F67: =P67 -> 0 | G67: =E67-F67 -> 0 | P67: =SUM(I67:O67) -> 0
C68: ='Orçamento Familiar'!C68 -> Mentoria Financeira | E68: ='Orçamento Familiar'!F68 -> 200 | F68: =P68 -> 200 | G68: =E68-F68 -> 0 | I68: 200 | P68: =SUM(I68:O68) -> 200
C69: ='Orçamento Familiar'!C69 -> 0 | E69: ='Orçamento Familiar'!F69 -> 0 | F69: =P69 -> 0 | G69: =E69-F69 -> 0 | P69: =SUM(I69:O69) -> 0
C70: ='Orçamento Familiar'!C70 -> 0 | E70: ='Orçamento Familiar'!F70 -> 0 | F70: =P70 -> 0 | G70: =E70-F70 -> 0 | P70: =SUM(I70:O70) -> 0
B71: Filhos | C71: ='Orçamento Familiar'!C71 -> Piano Laura | E71: ='Orçamento Familiar'!F71 -> 0 | F71: =P71 -> 0 | G71: =E71-F71 -> 0 | P71: =SUM(I71:O71) -> 0
C72: ='Orçamento Familiar'!C72 -> Material Escolar | E72: ='Orçamento Familiar'!F72 -> 0 | F72: =P72 -> 0 | G72: =E72-F72 -> 0 | P72: =SUM(I72:O72) -> 0
C73: ='Orçamento Familiar'!C73 -> Mesadas | E73: ='Orçamento Familiar'!F73 -> 300 | F73: =P73 -> 0 | G73: =E73-F73 -> 300 | P73: =SUM(I73:O73) -> 0
C74: ='Orçamento Familiar'!C74 -> Violão | E74: ='Orçamento Familiar'!F74 -> 0 | F74: =P74 -> 0 | G74: =E74-F74 -> 0 | P74: =SUM(I74:O74) -> 0
C75: ='Orçamento Familiar'!C75 -> Médicos / Exames | E75: ='Orçamento Familiar'!F75 -> 0 | F75: =P75 -> 0 | G75: =E75-F75 -> 0 | P75: =SUM(I75:O75) -> 0
C76: ='Orçamento Familiar'!C76 -> Cursos | E76: ='Orçamento Familiar'!F76 -> 0 | F76: =P76 -> 0 | G76: =E76-F76 -> 0 | P76: =SUM(I76:O76) -> 0
C77: ='Orçamento Familiar'!C77 -> Retiro Carnaval 2026/2027 | E77: ='Orçamento Familiar'!F77 -> 0 | F77: =P77 -> 0 | G77: =E77-F77 -> 0 | P77: =SUM(I77:O77) -> 0
C78: ='Orçamento Familiar'!C78 -> Acampadentro | E78: ='Orçamento Familiar'!F78 -> 0 | F78: =P78 -> 0 | G78: =E78-F78 -> 0 | P78: =SUM(I78:O78) -> 0
C79: ='Orçamento Familiar'!C79 -> 0 | E79: ='Orçamento Familiar'!F79 -> 0 | F79: =P79 -> 0 | G79: =E79-F79 -> 0 | P79: =SUM(I79:O79) -> 0
B80: Pet | C80: ='Orçamento Familiar'!C80 -> Ração | E80: ='Orçamento Familiar'!F80 -> 50 | F80: =P80 -> 53.98 | G80: =E80-F80 -> -3.98 | I80: 53.98 | P80: =SUM(I80:O80) -> 53.98
C81: ='Orçamento Familiar'!C81 -> Vacinas | E81: ='Orçamento Familiar'!F81 -> 0 | F81: =P81 -> 0 | G81: =E81-F81 -> 0 | P81: =SUM(I81:O81) -> 0
C82: ='Orçamento Familiar'!C82 -> Veterinário | E82: ='Orçamento Familiar'!F82 -> 0 | F82: =P82 -> 59 | G82: =E82-F82 -> -59 | I82: 59 | P82: =SUM(I82:O82) -> 59
C83: ='Orçamento Familiar'!C83 -> 0 | E83: ='Orçamento Familiar'!F83 -> 0 | F83: =P83 -> 0 | G83: =E83-F83 -> 0 | P83: =SUM(I83:O83) -> 0
C84: ='Orçamento Familiar'!C84 -> 0 | E84: ='Orçamento Familiar'!F84 -> 0 | F84: =P84 -> 0 | G84: =E84-F84 -> 0 | P84: =SUM(I84:O84) -> 0
B85: Total Despesas Essenciais | E85: =SUM(E31:E84) -> 5685 | F85: =SUM(F31:F84) -> 5954.42 | G85: =SUM(G31:G84) -> -269.42 | I85: =SUM(I31:I84) -> 1228.77 | J85: =SUM(J31:J84) -> 1328.85 | K85: =SUM(K31:K84) -> 719.86 | L85: =SUM(L31:L84) -> 507.98 | M85: =SUM(M31:M84) -> 379.21 | N85: =SUM(N31:N84) -> 1789.75 | O85: =SUM(O31:O84) -> 0 | P85: =SUM(P31:P84) -> 5954.42
B86: % sobre Receita | C86: ='Orçamento Familiar'!C166 -> 0 | E86: =E85/E16 -> 0.75238221 | F86: =F85/F16 -> 0.67671554 | I86: =I85/I16 -> 0.20770284 | J86: =J85/J16 -> 0.73825 | K86: =K85/K16 -> 1.564913 | L86: =L85/L16 -> 1.7219661 | M86: =M85/M16 -> 1.156128 | N86: =N85/N16 -> #DIV/0! | O86: =O85/O16 -> #DIV/0! | P86: =P85/P16 -> 0.67671554
A87: Profissional e Trabalho | B87: Ministério | C87: ='Orçamento Familiar'!C87 -> Materiais (livros) | E87: ='Orçamento Familiar'!F87 -> 0 | F87: =P87 -> 0 | G87: =E87-F87 -> 0 | P87: =SUM(I87:O87) -> 0
C88: ='Orçamento Familiar'!C88 -> 0 | E88: ='Orçamento Familiar'!F88 -> 0 | F88: =P88 -> 0 | G88: =E88-F88 -> 0 | P88: =SUM(I88:O88) -> 0
C89: ='Orçamento Familiar'!C89 -> 0 | E89: ='Orçamento Familiar'!F89 -> 0 | F89: =P89 -> 0 | G89: =E89-F89 -> 0 | P89: =SUM(I89:O89) -> 0
C90: ='Orçamento Familiar'!C90 -> 0 | E90: ='Orçamento Familiar'!F90 -> 0 | F90: =P90 -> 0 | G90: =E90-F90 -> 0 | P90: =SUM(I90:O90) -> 0
C91: ='Orçamento Familiar'!C91 -> 0 | E91: ='Orçamento Familiar'!F91 -> 0 | F91: =P91 -> 0 | G91: =E91-F91 -> 0 | P91: =SUM(I91:O91) -> 0
C92: ='Orçamento Familiar'!C92 -> 0 | E92: ='Orçamento Familiar'!F92 -> 0 | F92: =P92 -> 0 | G92: =E92-F92 -> 0 | P92: =SUM(I92:O92) -> 0
B93: Autônomo | C93: ='Orçamento Familiar'!C93 -> Ferramentas de trabalho | E93: ='Orçamento Familiar'!F93 -> 50 | F93: =P93 -> 191.21 | G93: =E93-F93 -> -141.21 | I93: 24 | N93: 167.21 | P93: =SUM(I93:O93) -> 191.21 | Q93: 51,40=10/12
C94: ='Orçamento Familiar'!C94 -> Colaboradores | E94: ='Orçamento Familiar'!F94 -> 140 | F94: =P94 -> 110.82 | G94: =E94-F94 -> 29.18 | I94: 50 | N94: 60.82 | P94: =SUM(I94:O94) -> 110.82 | Q94: 60,82=6/11
C95: ='Orçamento Familiar'!C95 -> 0 | E95: ='Orçamento Familiar'!F95 -> 0 | F95: =P95 -> 0 | G95: =E95-F95 -> 0 | P95: =SUM(I95:O95) -> 0
C96: ='Orçamento Familiar'!C96 -> 0 | E96: ='Orçamento Familiar'!F96 -> 0 | F96: =P96 -> 0 | G96: =E96-F96 -> 0 | P96: =SUM(I96:O96) -> 0
C97: ='Orçamento Familiar'!C97 -> 0 | E97: ='Orçamento Familiar'!F97 -> 0 | F97: =P97 -> 0 | G97: =E97-F97 -> 0 | P97: =SUM(I97:O97) -> 0
C98: ='Orçamento Familiar'!C98 -> 0 | E98: ='Orçamento Familiar'!F98 -> 0 | F98: =P98 -> 0 | G98: =E98-F98 -> 0 | P98: =SUM(I98:O98) -> 0
B99: Total Profissional e Trabalho | E99: =SUM(E87:E98) -> 190 | F99: =SUM(F87:F98) -> 302.03 | G99: =SUM(G87:G98) -> -112.03 | I99: =SUM(I87:I98) -> 74 | J99: =SUM(J87:J98) -> 0 | K99: =SUM(K87:K98) -> 0 | L99: =SUM(L87:L98) -> 0 | M99: =SUM(M87:M98) -> 0 | N99: =SUM(N87:N98) -> 228.03 | O99: =SUM(O87:O98) -> 0 | P99: =SUM(P87:P98) -> 302.03
B100: % sobre Receita | E100: =E99/E16 -> 0.02514558 | F100: =F99/F16 -> 0.034325492 | I100: =I99/I16 -> 0.012508452 | J100: =J99/J16 -> 0 | K100: =K99/K16 -> 0 | L100: =L99/L16 -> 0 | M100: =M99/M16 -> 0 | N100: =N99/N16 -> #DIV/0! | O100: =O99/O16 -> #DIV/0! | P100: =P99/P16 -> 0.034325492
A101: Contribuição | B101: Ofertas | C101: ='Orçamento Familiar'!C101 -> Dízimo | E101: ='Orçamento Familiar'!F101 -> 850 | F101: =P101 -> 850 | G101: =E101-F101 -> 0 | I101: 850 | P101: =SUM(I101:O101) -> 850
C102: ='Orçamento Familiar'!C102 -> Sacrificial | E102: ='Orçamento Familiar'!F102 -> 0 | F102: =P102 -> 0 | G102: =E102-F102 -> 0 | P102: =SUM(I102:O102) -> 0
C103: ='Orçamento Familiar'!C103 -> Doações | E103: ='Orçamento Familiar'!F103 -> 0 | F103: =P103 -> 0 | G103: =E103-F103 -> 0 | P103: =SUM(I103:O103) -> 0
C104: ='Orçamento Familiar'!C104 -> 0 | E104: ='Orçamento Familiar'!F104 -> 0 | F104: =P104 -> 0 | G104: =E104-F104 -> 0 | P104: =SUM(I104:O104) -> 0
B105: Total Contribuição | E105: =SUM(E101:E104) -> 850 | F105: =SUM(F101:F104) -> 850 | G105: =SUM(G101:G104) -> 0 | I105: =SUM(I101:I104) -> 850 | J105: =SUM(J101:J104) -> 0 | K105: =SUM(K101:K104) -> 0 | L105: =SUM(L101:L104) -> 0 | M105: =SUM(M101:M104) -> 0 | N105: =SUM(N101:N104) -> 0 | O105: =SUM(O101:O104) -> 0 | P105: =SUM(P101:P104) -> 850
...

Sheet Mar
A2: Fluxo de Caixa Familiar
A5: Categoria | C5: Descrição | D5: Percentual | E5: =I5 -> Março | I5: Março
E6: Orçado | F6: Realizado | G6: Variação | I6: Semana 1 | J6: Semana 2 | K6: Semana 3 | L6: Semana 4 | M6: Semana 5 | N6: =Jan!N6 -> Cartão Nubank | O6: =Jan!O6 -> Cartão C & A | P6: Total
A7: Receitas | C7: ='Orçamento Familiar'!C7 -> Prebenda | E7: ='Orçamento Familiar'!G7 -> 7216 | F7: =P7 -> 5716 | G7: =F7-E7 -> -1500 | I7: 5716 | P7: =SUM(I7:O7) -> 5716
C8: ='Orçamento Familiar'!C8 -> Inglês | E8: ='Orçamento Familiar'!G8 -> 335 | F8: =P8 -> 200 | G8: =F8-E8 -> -135 | I8: 200 | P8: =SUM(I8:O8) -> 200
C9: ='Orçamento Familiar'!C9 -> 13º Salário | E9: ='Orçamento Familiar'!G9 -> 0 | F9: =P9 -> 0 | G9: =F9-E9 -> 0 | P9: =SUM(I9:O9) -> 0
C10: ='Orçamento Familiar'!C10 -> Renda Extra | E10: ='Orçamento Familiar'!G10 -> 0 | F10: =P10 -> 0 | G10: =F10-E10 -> 0 | P10: =SUM(I10:O10) -> 0
C11: ='Orçamento Familiar'!C11 -> 0 | E11: ='Orçamento Familiar'!G11 -> 0 | F11: =P11 -> 0 | G11: =F11-E11 -> 0 | P11: =SUM(I11:O11) -> 0
C12: ='Orçamento Familiar'!C12 -> 0 | E12: ='Orçamento Familiar'!G12 -> 0 | F12: =P12 -> 0 | G12: =F12-E12 -> 0 | P12: =SUM(I12:O12) -> 0
C13: ='Orçamento Familiar'!C13 -> 0 | E13: ='Orçamento Familiar'!G13 -> 0 | F13: =P13 -> 128 | G13: =F13-E13 -> 128 | I13: 128 | P13: =SUM(I13:O13) -> 128 | Q13: 128,00 Eric
C14: ='Orçamento Familiar'!C14 -> 0 | E14: ='Orçamento Familiar'!G14 -> 0 | F14: =P14 -> 0 | G14: =F14-E14 -> 0 | P14: =SUM(I14:O14) -> 0
C15: ='Orçamento Familiar'!C15 -> 0 | E15: ='Orçamento Familiar'!G15 -> 0 | F15: =P15 -> 0 | G15: =F15-E15 -> 0 | P15: =SUM(I15:O15) -> 0
C16: Total | E16: =SUM(E7:E15) -> 7551 | F16: =SUM(F7:F15) -> 6044 | G16: =SUM(G7:G15) -> -1507 | I16: =SUM(I7:I15) -> 6044 | J16: =SUM(J7:J15) -> 0 | K16: =SUM(K7:K15) -> 0 | L16: =SUM(L7:L15) -> 0 | M16: =SUM(M7:M15) -> 0 | N16: =SUM(N7:N15) -> 0 | O16: =SUM(O7:O15) -> 0 | P16: =SUM(P7:P15) -> 6044
A18: Investimentos Insira aqui o montante mensal que você destinará aos seus investimentos | C18: Descrição | D18: Percentual | E18: Orçado | F18: Realizado | G18: Variação | I18: =I6 -> Semana 1 | J18: =J6 -> Semana 2 | K18: =K6 -> Semana 3 | L18: =L6 -> Semana 4 | M18: =M6 -> Semana 5 | P18: =P6 -> Total
C19: ='Orçamento Familiar'!C19 -> Reserva de Emergência (CP) R$ 9.151 | E19: ='Orçamento Familiar'!G19 -> 0 | F19: =P19 -> 0 | G19: =F19-E19 -> 0 | P19: =SUM(I19:O19) -> 0
C20: ='Orçamento Familiar'!C20 -> Projeto 1 | E20: ='Orçamento Familiar'!G20 -> 0 | F20: =P20 -> 0 | G20: =F20-E20 -> 0 | P20: =SUM(I20:O20) -> 0
C21: ='Orçamento Familiar'!C21 -> Projeto 2 | E21: ='Orçamento Familiar'!G21 -> 0 | F21: =P21 -> 0 | G21: =F21-E21 -> 0 | P21: =SUM(I21:O21) -> 0
C22: ='Orçamento Familiar'!C22 -> Projeto 3 | E22: ='Orçamento Familiar'!G22 -> 0 | F22: =P22 -> 0 | G22: =F22-E22 -> 0 | P22: =SUM(I22:O22) -> 0
C23: ='Orçamento Familiar'!C23 -> Projeto 4 | E23: ='Orçamento Familiar'!G23 -> 0 | F23: =P23 -> 0 | G23: =F23-E23 -> 0 | P23: =SUM(I23:O23) -> 0
C24: ='Orçamento Familiar'!C24 -> Projeto 5 | E24: ='Orçamento Familiar'!G24 -> 0 | F24: =P24 -> 0 | G24: =F24-E24 -> 0 | P24: =SUM(I24:O24) -> 0
C25: ='Orçamento Familiar'!C25 -> Projeto 6 | E25: ='Orçamento Familiar'!G25 -> 0 | F25: =P25 -> 0 | G25: =F25-E25 -> 0 | P25: =SUM(I25:O25) -> 0
C26: ='Orçamento Familiar'!C26 -> Independência Financeira | E26: ='Orçamento Familiar'!G26 -> 0 | F26: =P26 -> 0 | G26: =F26-E26 -> 0 | P26: =SUM(I26:O26) -> 0
C27: Total Investimentos | D27: =SUM(D19:D26) -> 0 | E27: =SUM(E19:E26) -> 0 | F27: =SUM(F19:F26) -> 0 | G27: =SUM(G19:G26) -> 0 | I27: =SUM(I19:I26) -> 0 | J27: =SUM(J19:J26) -> 0 | K27: =SUM(K19:K26) -> 0 | L27: =SUM(L19:L26) -> 0 | M27: =SUM(M19:M26) -> 0 | N27: =SUM(N19:N26) -> 0 | O27: =SUM(O19:O26) -> 0 | P27: =SUM(P19:P26) -> 0
C28: % sobre Receita | E28: =E27/E16 -> 0 | F28: =F27/F16 -> 0 | I28: =I27/I16 -> 0 | J28: =J27/J16 -> #DIV/0! | K28: =K27/K16 -> #DIV/0! | L28: =L27/L16 -> #DIV/0! | M28: =M27/M16 -> #DIV/0! | N28: =N27/N16 -> #DIV/0! | O28: =O27/O16 -> #DIV/0! | P28: =P27/P16 -> 0
A30: Categoria | C30: Descrição | D30: Percentual | E30: Orçado | F30: Realizado | G30: Variação | I30: =I18 -> Semana 1 | J30: =J18 -> Semana 2 | K30: =K18 -> Semana 3 | L30: =L18 -> Semana 4 | M30: =M18 -> Semana 5 | N30: =N6 -> Cartão Nubank | O30: =O6 -> Cartão C & A | P30: =P18 -> Total
A31: Despesas Essenciais | B31: Moradia | C31: ='Orçamento Familiar'!C31 -> Aluguel | E31: ='Orçamento Familiar'!G31 -> 0 | F31: =P31 -> 0 | G31: =E31-F31 -> 0 | P31: =SUM(I31:O31) -> 0
C32: ='Orçamento Familiar'!C32 -> Energia Elétrica | E32: ='Orçamento Familiar'!G32 -> 0 | F32: =P32 -> 0 | G32: =E32-F32 -> 0 | P32: =SUM(I32:O32) -> 0
C33: ='Orçamento Familiar'!C33 -> Água e Esgoto | E33: ='Orçamento Familiar'!G33 -> 0 | F33: =P33 -> 0 | G33: =E33-F33 -> 0 | P33: =SUM(I33:O33) -> 0
C34: ='Orçamento Familiar'!C34 -> Gás | E34: ='Orçamento Familiar'!G34 -> 0 | F34: =P34 -> 0 | G34: =E34-F34 -> 0 | P34: =SUM(I34:O34) -> 0
C35: ='Orçamento Familiar'!C35 -> Internet e Celular | E35: ='Orçamento Familiar'!G35 -> 184.7 | F35: =P35 -> 184.7 | G35: =E35-F35 -> 0 | N35: 184.7 | P35: =SUM(I35:O35) -> 184.7
C36: ='Orçamento Familiar'!C36 -> Manutenção | E36: ='Orçamento Familiar'!G36 -> 50 | F36: =P36 -> 0 | G36: =E36-F36 -> 50 | P36: =SUM(I36:O36) -> 0
C37: ='Orçamento Familiar'!C37 -> 0 | E37: ='Orçamento Familiar'!G37 -> 0 | F37: =P37 -> 0 | G37: =E37-F37 -> 0 | P37: =SUM(I37:O37) -> 0
C38: ='Orçamento Familiar'!C38 -> 0 | E38: ='Orçamento Familiar'!G38 -> 0 | F38: =P38 -> 0 | G38: =E38-F38 -> 0 | P38: =SUM(I38:O38) -> 0
C39: ='Orçamento Familiar'!C39 -> 0 | E39: ='Orçamento Familiar'!G39 -> 0 | F39: =P39 -> 0 | G39: =E39-F39 -> 0 | P39: =SUM(I39:O39) -> 0
B40: Alimentação | C40: ='Orçamento Familiar'!C40 -> Supermercado | E40: ='Orçamento Familiar'!G40 -> 3100 | F40: =P40 -> 2410.57 | G40: =E40-F40 -> 689.43 | I40: 317.1 | J40: =740+133.5 -> 873.5 | K40: 450.3 | N40: 769.67 | P40: =SUM(I40:O40) -> 2410.57
C41: ='Orçamento Familiar'!C41 -> 0 | E41: ='Orçamento Familiar'!G41 -> 0 | F41: =P41 -> 0 | G41: =E41-F41 -> 0 | P41: =SUM(I41:O41) -> 0
C42: ='Orçamento Familiar'!C42 -> 0 | E42: ='Orçamento Familiar'!G42 -> 0 | F42: =P42 -> 0 | G42: =E42-F42 -> 0 | P42: =SUM(I42:O42) -> 0
C43: ='Orçamento Familiar'!C43 -> 0 | E43: ='Orçamento Familiar'!G43 -> 0 | F43: =P43 -> 0 | G43: =E43-F43 -> 0 | P43: =SUM(I43:O43) -> 0
C44: ='Orçamento Familiar'!C44 -> 0 | E44: ='Orçamento Familiar'!G44 -> 0 | F44: =P44 -> 0 | G44: =E44-F44 -> 0 | P44: =SUM(I44:O44) -> 0
C45: ='Orçamento Familiar'!C45 -> 0 | E45: ='Orçamento Familiar'!G45 -> 0 | F45: =P45 -> 0 | G45: =E45-F45 -> 0 | P45: =SUM(I45:O45) -> 0
B46: Transporte | C46: ='Orçamento Familiar'!C46 -> Combustível | E46: ='Orçamento Familiar'!G46 -> 400 | F46: =P46 -> 276.27 | G46: =E46-F46 -> 123.73 | I46: 226.27 | N46: 50 | P46: =SUM(I46:O46) -> 276.27
C47: ='Orçamento Familiar'!C47 -> Manutenção | E47: ='Orçamento Familiar'!G47 -> 500 | F47: =P47 -> 430.9 | G47: =E47-F47 -> 69.1 | N47: 430.9 | P47: =SUM(I47:O47) -> 430.9 | Q47: 430,90 =3/6
C48: ='Orçamento Familiar'!C48 -> Multas | E48: ='Orçamento Familiar'!G48 -> 0 | F48: =P48 -> 0 | G48: =E48-F48 -> 0 | P48: =SUM(I48:O48) -> 0
C49: ='Orçamento Familiar'!C49 -> Seguro | E49: ='Orçamento Familiar'!G49 -> 0 | F49: =P49 -> 0 | G49: =E49-F49 -> 0 | P49: =SUM(I49:O49) -> 0
C50: ='Orçamento Familiar'!C50 -> Lavagem | E50: ='Orçamento Familiar'!G50 -> 0 | F50: =P50 -> 0 | G50: =E50-F50 -> 0 | P50: =SUM(I50:O50) -> 0
C51: ='Orçamento Familiar'!C51 -> Estacionamento | E51: ='Orçamento Familiar'!G51 -> 0 | F51: =P51 -> 0 | G51: =E51-F51 -> 0 | P51: =SUM(I51:O51) -> 0
C52: ='Orçamento Familiar'!C52 -> Taxi / Uber | E52: ='Orçamento Familiar'!G52 -> 0 | F52: =P52 -> 0 | G52: =E52-F52 -> 0 | P52: =SUM(I52:O52) -> 0
C53: ='Orçamento Familiar'!C53 -> 0 | E53: ='Orçamento Familiar'!G53 -> 0 | F53: =P53 -> 0 | G53: =E53-F53 -> 0 | P53: =SUM(I53:O53) -> 0
C54: ='Orçamento Familiar'!C54 -> 0 | E54: ='Orçamento Familiar'!G54 -> 0 | F54: =P54 -> 0 | G54: =E54-F54 -> 0 | P54: =SUM(I54:O54) -> 0
B55: Saúde | C55: ='Orçamento Familiar'!C55 -> Medicamentos | E55: ='Orçamento Familiar'!G55 -> 80 | F55: =P55 -> 20 | G55: =E55-F55 -> 60 | I55: 20 | P55: =SUM(I55:O55) -> 20
C56: ='Orçamento Familiar'!C56 -> Médicos / Exames | E56: ='Orçamento Familiar'!G56 -> 0 | F56: =P56 -> 0 | G56: =E56-F56 -> 0 | P56: =SUM(I56:O56) -> 0
C57: ='Orçamento Familiar'!C57 -> Dentista | E57: ='Orçamento Familiar'!G57 -> 0 | F57: =P57 -> 0 | G57: =E57-F57 -> 0 | P57: =SUM(I57:O57) -> 0
C58: ='Orçamento Familiar'!C58 -> 0 | E58: ='Orçamento Familiar'!G58 -> 0 | F58: =P58 -> 0 | G58: =E58-F58 -> 0 | P58: =SUM(I58:O58) -> 0
C59: ='Orçamento Familiar'!C59 -> 0 | E59: ='Orçamento Familiar'!G59 -> 0 | F59: =P59 -> 0 | G59: =E59-F59 -> 0 | P59: =SUM(I59:O59) -> 0
B60: Impostos | C60: ='Orçamento Familiar'!C60 -> IPVA | E60: ='Orçamento Familiar'!G60 -> 0 | F60: =P60 -> 0 | G60: =E60-F60 -> 0 | P60: =SUM(I60:O60) -> 0
C61: ='Orçamento Familiar'!C61 -> Licenciamento | E61: ='Orçamento Familiar'!G61 -> 0 | F61: =P61 -> 0 | G61: =E61-F61 -> 0 | P61: =SUM(I61:O61) -> 0
C62: ='Orçamento Familiar'!C62 -> Imposto de Renda | E62: ='Orçamento Familiar'!G62 -> 0 | F62: =P62 -> 0 | G62: =E62-F62 -> 0 | P62: =SUM(I62:O62) -> 0
C63: ='Orçamento Familiar'!C63 -> INSS | E63: ='Orçamento Familiar'!G63 -> 0 | F63: =P63 -> 0 | G63: =E63-F63 -> 0 | P63: =SUM(I63:O63) -> 0
C64: ='Orçamento Familiar'!C64 -> 0 | E64: ='Orçamento Familiar'!G64 -> 0 | F64: =P64 -> 0 | G64: =E64-F64 -> 0 | P64: =SUM(I64:O64) -> 0
C65: ='Orçamento Familiar'!C65 -> 0 | E65: ='Orçamento Familiar'!G65 -> 0 | F65: =P65 -> 0 | G65: =E65-F65 -> 0 | P65: =SUM(I65:O65) -> 0
B66: Educação | C66: ='Orçamento Familiar'!C66 -> Especialização | E66: ='Orçamento Familiar'!G66 -> 0 | F66: =P66 -> 0 | G66: =E66-F66 -> 0 | P66: =SUM(I66:O66) -> 0
C67: ='Orçamento Familiar'!C67 -> Cursos | E67: ='Orçamento Familiar'!G67 -> 150 | F67: =P67 -> 146.83 | G67: =E67-F67 -> 3.17 | N67: 146.83 | P67: =SUM(I67:O67) -> 146.83 | Q67: Faculdade Con 1/6=146,83
C68: ='Orçamento Familiar'!C68 -> Mentoria Financeira | E68: ='Orçamento Familiar'!G68 -> 225 | F68: =P68 -> 225 | G68: =E68-F68 -> 0 | J68: 225 | P68: =SUM(I68:O68) -> 225
C69: ='Orçamento Familiar'!C69 -> 0 | E69: ='Orçamento Familiar'!G69 -> 0 | F69: =P69 -> 0 | G69: =E69-F69 -> 0 | P69: =SUM(I69:O69) -> 0
C70: ='Orçamento Familiar'!C70 -> 0 | E70: ='Orçamento Familiar'!G70 -> 0 | F70: =P70 -> 0 | G70: =E70-F70 -> 0 | P70: =SUM(I70:O70) -> 0
B71: Filhos | C71: ='Orçamento Familiar'!C71 -> Piano Laura | E71: ='Orçamento Familiar'!G71 -> 0 | F71: =P71 -> 0 | G71: =E71-F71 -> 0 | P71: =SUM(I71:O71) -> 0
C72: ='Orçamento Familiar'!C72 -> Material Escolar | E72: ='Orçamento Familiar'!G72 -> 0 | F72: =P72 -> 0 | G72: =E72-F72 -> 0 | P72: =SUM(I72:O72) -> 0
C73: ='Orçamento Familiar'!C73 -> Mesadas | E73: ='Orçamento Familiar'!G73 -> 330 | F73: =P73 -> 318.61 | G73: =E73-F73 -> 11.39 | I73: 120 | J73: 137.79 | N73: =60.82 -> 60.82 | P73: =SUM(I73:O73) -> 318.61 | Q73: 137,79=habilit Laura / 120,00 - clube Laura / 60,82 Levi 07/11
C74: ='Orçamento Familiar'!C74 -> Violão | E74: ='Orçamento Familiar'!G74 -> 0 | F74: =P74 -> 0 | G74: =E74-F74 -> 0 | P74: =SUM(I74:O74) -> 0
C75: ='Orçamento Familiar'!C75 -> Médicos / Exames | E75: ='Orçamento Familiar'!G75 -> 0 | F75: =P75 -> 0 | G75: =E75-F75 -> 0 | P75: =SUM(I75:O75) -> 0
C76: ='Orçamento Familiar'!C76 -> Cursos | E76: ='Orçamento Familiar'!G76 -> 0 | F76: =P76 -> 0 | G76: =E76-F76 -> 0 | P76: =SUM(I76:O76) -> 0
C77: ='Orçamento Familiar'!C77 -> Retiro Carnaval 2026/2027 | E77: ='Orçamento Familiar'!G77 -> 0 | F77: =P77 -> 0 | G77: =E77-F77 -> 0 | P77: =SUM(I77:O77) -> 0
C78: ='Orçamento Familiar'!C78 -> Acampadentro | E78: ='Orçamento Familiar'!G78 -> 0 | F78: =P78 -> 0 | G78: =E78-F78 -> 0 | P78: =SUM(I78:O78) -> 0
C79: ='Orçamento Familiar'!C79 -> 0 | E79: ='Orçamento Familiar'!G79 -> 0 | F79: =P79 -> 0 | G79: =E79-F79 -> 0 | P79: =SUM(I79:O79) -> 0
B80: Pet | C80: ='Orçamento Familiar'!C80 -> Ração | E80: ='Orçamento Familiar'!G80 -> 50 | F80: =P80 -> 47 | G80: =E80-F80 -> 3 | I80: 22 | J80: 25 | P80: =SUM(I80:O80) -> 47
C81: ='Orçamento Familiar'!C81 -> Vacinas | E81: ='Orçamento Familiar'!G81 -> 0 | F81: =P81 -> 0 | G81: =E81-F81 -> 0 | P81: =SUM(I81:O81) -> 0
C82: ='Orçamento Familiar'!C82 -> Veterinário | E82: ='Orçamento Familiar'!G82 -> 0 | F82: =P82 -> 0 | G82: =E82-F82 -> 0 | P82: =SUM(I82:O82) -> 0
C83: ='Orçamento Familiar'!C83 -> 0 | E83: ='Orçamento Familiar'!G83 -> 0 | F83: =P83 -> 0 | G83: =E83-F83 -> 0 | P83: =SUM(I83:O83) -> 0
C84: ='Orçamento Familiar'!C84 -> 0 | E84: ='Orçamento Familiar'!G84 -> 0 | F84: =P84 -> 0 | G84: =E84-F84 -> 0 | P84: =SUM(I84:O84) -> 0
B85: Total Despesas Essenciais | E85: =SUM(E31:E84) -> 5069.7 | F85: =SUM(F31:F84) -> 4059.88 | G85: =SUM(G31:G84) -> 1009.82 | I85: =SUM(I31:I84) -> 705.37 | J85: =SUM(J31:J84) -> 1261.29 | K85: =SUM(K31:K84) -> 450.3 | L85: =SUM(L31:L84) -> 0 | M85: =SUM(M31:M84) -> 0 | N85: =SUM(N31:N84) -> 1642.92 | O85: =SUM(O31:O84) -> 0 | P85: =SUM(P31:P84) -> 4059.88
B86: % sobre Receita | C86: ='Orçamento Familiar'!C166 -> 0 | E86: =E85/E16 -> 0.67139452 | F86: =F85/F16 -> 0.67172071 | I86: =I85/I16 -> 0.11670582 | J86: =J85/J16 -> #DIV/0! | K86: =K85/K16 -> #DIV/0! | L86: =L85/L16 -> #DIV/0! | M86: =M85/M16 -> #DIV/0! | N86: =N85/N16 -> #DIV/0! | O86: =O85/O16 -> #DIV/0! | P86: =P85/P16 -> 0.67172071
A87: Profissional e Trabalho | B87: Ministério | C87: ='Orçamento Familiar'!C87 -> Materiais (livros) | E87: ='Orçamento Familiar'!G87 -> 125 | F87: =P87 -> 0 | G87: =E87-F87 -> 125 | P87: =SUM(I87:O87) -> 0
C88: ='Orçamento Familiar'!C88 -> 0 | E88: ='Orçamento Familiar'!G88 -> 0 | F88: =P88 -> 0 | G88: =E88-F88 -> 0 | P88: =SUM(I88:O88) -> 0
C89: ='Orçamento Familiar'!C89 -> 0 | E89: ='Orçamento Familiar'!G89 -> 0 | F89: =P89 -> 0 | G89: =E89-F89 -> 0 | P89: =SUM(I89:O89) -> 0
C90: ='Orçamento Familiar'!C90 -> 0 | E90: ='Orçamento Familiar'!G90 -> 0 | F90: =P90 -> 124.27 | G90: =E90-F90 -> -124.27 | J90: 124.27 | P90: =SUM(I90:O90) -> 124.27 | Q90: livros
C91: ='Orçamento Familiar'!C91 -> 0 | E91: ='Orçamento Familiar'!G91 -> 0 | F91: =P91 -> 0 | G91: =E91-F91 -> 0 | P91: =SUM(I91:O91) -> 0
C92: ='Orçamento Familiar'!C92 -> 0 | E92: ='Orçamento Familiar'!G92 -> 0 | F92: =P92 -> 0 | G92: =E92-F92 -> 0 | P92: =SUM(I92:O92) -> 0
B93: Autônomo | C93: ='Orçamento Familiar'!C93 -> Ferramentas de trabalho | E93: ='Orçamento Familiar'!G93 -> 200 | F93: =P93 -> 51.4 | G93: =E93-F93 -> 148.6 | N93: 51.4 | P93: =SUM(I93:O93) -> 51.4 | Q93: 51,40=11/12
C94: ='Orçamento Familiar'!C94 -> Colaboradores | E94: ='Orçamento Familiar'!G94 -> 50 | F94: =P94 -> 50 | G94: =E94-F94 -> 0 | I94: 50 | P94: =SUM(I94:O94) -> 50
C95: ='Orçamento Familiar'!C95 -> 0 | E95: ='Orçamento Familiar'!G95 -> 0 | F95: =P95 -> 0 | G95: =E95-F95 -> 0 | P95: =SUM(I95:O95) -> 0
C96: ='Orçamento Familiar'!C96 -> 0 | E96: ='Orçamento Familiar'!G96 -> 0 | F96: =P96 -> 0 | G96: =E96-F96 -> 0 | P96: =SUM(I96:O96) -> 0
C97: ='Orçamento Familiar'!C97 -> 0 | E97: ='Orçamento Familiar'!G97 -> 0 | F97: =P97 -> 0 | G97: =E97-F97 -> 0 | P97: =SUM(I97:O97) -> 0
C98: ='Orçamento Familiar'!C98 -> 0 | E98: ='Orçamento Familiar'!G98 -> 0 | F98: =P98 -> 0 | G98: =E98-F98 -> 0 | P98: =SUM(I98:O98) -> 0
B99: Total Profissional e Trabalho | E99: =SUM(E87:E98) -> 375 | F99: =SUM(F87:F98) -> 225.67 | G99: =SUM(G87:G98) -> 149.33 | I99: =SUM(I87:I98) -> 50 | J99: =SUM(J87:J98) -> 124.27 | K99: =SUM(K87:K98) -> 0 | L99: =SUM(L87:L98) -> 0 | M99: =SUM(M87:M98) -> 0 | N99: =SUM(N87:N98) -> 51.4 | O99: =SUM(O87:O98) -> 0 | P99: =SUM(P87:P98) -> 225.67
B100: % sobre Receita | E100: =E99/E16 -> 0.049662296 | F100: =F99/F16 -> 0.037337856 | I100: =I99/I16 -> 0.0082726671 | J100: =J99/J16 -> #DIV/0! | K100: =K99/K16 -> #DIV/0! | L100: =L99/L16 -> #DIV/0! | M100: =M99/M16 -> #DIV/0! | N100: =N99/N16 -> #DIV/0! | O100: =O99/O16 -> #DIV/0! | P100: =P99/P16 -> 0.037337856
A101: Contribuição | B101: Ofertas | C101: ='Orçamento Familiar'!C101 -> Dízimo | E101: ='Orçamento Familiar'!G101 -> 850 | F101: =P101 -> 850 | G101: =E101-F101 -> 0 | I101: 850 | P101: =SUM(I101:O101) -> 850
C102: ='Orçamento Familiar'!C102 -> Sacrificial | E102: ='Orçamento Familiar'!G102 -> 0 | F102: =P102 -> 0 | G102: =E102-F102 -> 0 | P102: =SUM(I102:O102) -> 0
C103: ='Orçamento Familiar'!C103 -> Doações | E103: ='Orçamento Familiar'!G103 -> 0 | F103: =P103 -> 0 | G103: =E103-F103 -> 0 | P103: =SUM(I103:O103) -> 0
C104: ='Orçamento Familiar'!C104 -> 0 | E104: ='Orçamento Familiar'!G104 -> 0 | F104: =P104 -> 0 | G104: =E104-F104 -> 0 | P104: =SUM(I104:O104) -> 0
B105: Total Contribuição | E105: =SUM(E101:E104) -> 850 | F105: =SUM(F101:F104) -> 850 | G105: =SUM(G101:G104) -> 0 | I105: =SUM(I101:I104) -> 850 | J105: =SUM(J101:J104) -> 0 | K105: =SUM(K101:K104) -> 0 | L105: =SUM(L101:L104) -> 0 | M105: =SUM(M101:M104) -> 0 | N105: =SUM(N101:N104) -> 0 | O105: =SUM(O101:O104) -> 0 | P105: =SUM(P101:P104) -> 850
...

Sheet Abr
A2: Fluxo de Caixa Familiar
A5: Categoria | C5: Descrição | D5: Percentual | E5: =I5 -> Abril | I5: Abril
E6: Orçado | F6: Realizado | G6: Variação | I6: Semana 1 | J6: Semana 2 | K6: Semana 3 | L6: Semana 4 | M6: Semana 5 | N6: =Jan!N6 -> Cartão Nubank | O6: =Jan!O6 -> Cartão C & A | P6: Total
A7: Receitas | C7: ='Orçamento Familiar'!C7 -> Prebenda | E7: ='Orçamento Familiar'!H7 -> 7216 | F7: =P7 -> 0 | G7: =F7-E7 -> -7216 | P7: =SUM(I7:O7) -> 0
C8: ='Orçamento Familiar'!C8 -> Inglês | E8: ='Orçamento Familiar'!H8 -> 335 | F8: =P8 -> 0 | G8: =F8-E8 -> -335 | P8: =SUM(I8:O8) -> 0
C9: ='Orçamento Familiar'!C9 -> 13º Salário | E9: ='Orçamento Familiar'!H9 -> 0 | F9: =P9 -> 0 | G9: =F9-E9 -> 0 | P9: =SUM(I9:O9) -> 0
C10: ='Orçamento Familiar'!C10 -> Renda Extra | E10: ='Orçamento Familiar'!H10 -> 0 | F10: =P10 -> 0 | G10: =F10-E10 -> 0 | P10: =SUM(I10:O10) -> 0
C11: ='Orçamento Familiar'!C11 -> 0 | E11: ='Orçamento Familiar'!H11 -> 0 | F11: =P11 -> 0 | G11: =F11-E11 -> 0 | P11: =SUM(I11:O11) -> 0
C12: ='Orçamento Familiar'!C12 -> 0 | E12: ='Orçamento Familiar'!H12 -> 0 | F12: =P12 -> 0 | G12: =F12-E12 -> 0 | P12: =SUM(I12:O12) -> 0
C13: ='Orçamento Familiar'!C13 -> 0 | E13: ='Orçamento Familiar'!H13 -> 0 | F13: =P13 -> 0 | G13: =F13-E13 -> 0 | P13: =SUM(I13:O13) -> 0
C14: ='Orçamento Familiar'!C14 -> 0 | E14: ='Orçamento Familiar'!H14 -> 0 | F14: =P14 -> 0 | G14: =F14-E14 -> 0 | P14: =SUM(I14:O14) -> 0
C15: ='Orçamento Familiar'!C15 -> 0 | E15: ='Orçamento Familiar'!H15 -> 0 | F15: =P15 -> 0 | G15: =F15-E15 -> 0 | P15: =SUM(I15:O15) -> 0
C16: Total | E16: =SUM(E7:E15) -> 7551 | F16: =SUM(F7:F15) -> 0 | G16: =SUM(G7:G15) -> -7551 | I16: =SUM(I7:I15) -> 0 | J16: =SUM(J7:J15) -> 0 | K16: =SUM(K7:K15) -> 0 | L16: =SUM(L7:L15) -> 0 | M16: =SUM(M7:M15) -> 0 | N16: =SUM(N7:N15) -> 0 | O16: =SUM(O7:O15) -> 0 | P16: =SUM(P7:P15) -> 0
A18: Investimentos Insira aqui o montante mensal que você destinará aos seus investimentos | C18: Descrição | D18: Percentual | E18: Orçado | F18: Realizado | G18: Variação | I18: =I6 -> Semana 1 | J18: =J6 -> Semana 2 | K18: =K6 -> Semana 3 | L18: =L6 -> Semana 4 | M18: =M6 -> Semana 5 | P18: =P6 -> Total
C19: ='Orçamento Familiar'!C19 -> Reserva de Emergência (CP) R$ 9.151 | E19: ='Orçamento Familiar'!H19 -> 0 | F19: =P19 -> 0 | G19: =F19-E19 -> 0 | P19: =SUM(I19:O19) -> 0
C20: ='Orçamento Familiar'!C20 -> Projeto 1 | E20: ='Orçamento Familiar'!H20 -> 0 | F20: =P20 -> 0 | G20: =F20-E20 -> 0 | P20: =SUM(I20:O20) -> 0
C21: ='Orçamento Familiar'!C21 -> Projeto 2 | E21: ='Orçamento Familiar'!H21 -> 0 | F21: =P21 -> 0 | G21: =F21-E21 -> 0 | P21: =SUM(I21:O21) -> 0
C22: ='Orçamento Familiar'!C22 -> Projeto 3 | E22: ='Orçamento Familiar'!H22 -> 0 | F22: =P22 -> 0 | G22: =F22-E22 -> 0 | P22: =SUM(I22:O22) -> 0
C23: ='Orçamento Familiar'!C23 -> Projeto 4 | E23: ='Orçamento Familiar'!H23 -> 0 | F23: =P23 -> 0 | G23: =F23-E23 -> 0 | P23: =SUM(I23:O23) -> 0
C24: ='Orçamento Familiar'!C24 -> Projeto 5 | E24: ='Orçamento Familiar'!H24 -> 0 | F24: =P24 -> 0 | G24: =F24-E24 -> 0 | P24: =SUM(I24:O24) -> 0
C25: ='Orçamento Familiar'!C25 -> Projeto 6 | E25: ='Orçamento Familiar'!H25 -> 0 | F25: =P25 -> 0 | G25: =F25-E25 -> 0 | P25: =SUM(I25:O25) -> 0
C26: ='Orçamento Familiar'!C26 -> Independência Financeira | E26: ='Orçamento Familiar'!H26 -> 0 | F26: =P26 -> 0 | G26: =F26-E26 -> 0 | P26: =SUM(I26:O26) -> 0
C27: Total Investimentos | D27: =SUM(D19:D26) -> 0 | E27: =SUM(E19:E26) -> 0 | F27: =SUM(F19:F26) -> 0 | G27: =SUM(G19:G26) -> 0 | I27: =SUM(I19:I26) -> 0 | J27: =SUM(J19:J26) -> 0 | K27: =SUM(K19:K26) -> 0 | L27: =SUM(L19:L26) -> 0 | M27: =SUM(M19:M26) -> 0 | N27: =SUM(N19:N26) -> 0 | O27: =SUM(O19:O26) -> 0 | P27: =SUM(P19:P26) -> 0
C28: % sobre Receita | E28: =E27/E16 -> 0 | F28: =F27/F16 -> #DIV/0! | I28: =I27/I16 -> #DIV/0! | J28: =J27/J16 -> #DIV/0! | K28: =K27/K16 -> #DIV/0! | L28: =L27/L16 -> #DIV/0! | M28: =M27/M16 -> #DIV/0! | N28: =N27/N16 -> #DIV/0! | O28: =O27/O16 -> #DIV/0! | P28: =P27/P16 -> #DIV/0!
A30: Categoria | C30: Descrição | D30: Percentual | E30: Orçado | F30: Realizado | G30: Variação | I30: =I18 -> Semana 1 | J30: =J18 -> Semana 2 | K30: =K18 -> Semana 3 | L30: =L18 -> Semana 4 | M30: =M18 -> Semana 5 | N30: =N6 -> Cartão Nubank | O30: =O6 -> Cartão C & A | P30: =P18 -> Total
A31: Despesas Essenciais | B31: Moradia | C31: ='Orçamento Familiar'!C31 -> Aluguel | E31: ='Orçamento Familiar'!H31 -> 0 | F31: =P31 -> 0 | G31: =E31-F31 -> 0 | P31: =SUM(I31:O31) -> 0
C32: ='Orçamento Familiar'!C32 -> Energia Elétrica | E32: ='Orçamento Familiar'!H32 -> 0 | F32: =P32 -> 0 | G32: =E32-F32 -> 0 | P32: =SUM(I32:O32) -> 0
C33: ='Orçamento Familiar'!C33 -> Água e Esgoto | E33: ='Orçamento Familiar'!H33 -> 0 | F33: =P33 -> 0 | G33: =E33-F33 -> 0 | P33: =SUM(I33:O33) -> 0
C34: ='Orçamento Familiar'!C34 -> Gás | E34: ='Orçamento Familiar'!H34 -> 0 | F34: =P34 -> 0 | G34: =E34-F34 -> 0 | P34: =SUM(I34:O34) -> 0
C35: ='Orçamento Familiar'!C35 -> Internet e Celular | E35: ='Orçamento Familiar'!H35 -> 184.7 | F35: =P35 -> 0 | G35: =E35-F35 -> 184.7 | P35: =SUM(I35:O35) -> 0
C36: ='Orçamento Familiar'!C36 -> Manutenção | E36: ='Orçamento Familiar'!H36 -> 50 | F36: =P36 -> 0 | G36: =E36-F36 -> 50 | P36: =SUM(I36:O36) -> 0
C37: ='Orçamento Familiar'!C37 -> 0 | E37: ='Orçamento Familiar'!H37 -> 0 | F37: =P37 -> 0 | G37: =E37-F37 -> 0 | P37: =SUM(I37:O37) -> 0
C38: ='Orçamento Familiar'!C38 -> 0 | E38: ='Orçamento Familiar'!H38 -> 0 | F38: =P38 -> 0 | G38: =E38-F38 -> 0 | P38: =SUM(I38:O38) -> 0
C39: ='Orçamento Familiar'!C39 -> 0 | E39: ='Orçamento Familiar'!H39 -> 0 | F39: =P39 -> 0 | G39: =E39-F39 -> 0 | P39: =SUM(I39:O39) -> 0
B40: Alimentação | C40: ='Orçamento Familiar'!C40 -> Supermercado | E40: ='Orçamento Familiar'!H40 -> 3100 | F40: =P40 -> 366.88 | G40: =E40-F40 -> 2733.12 | N40: 366.88 | P40: =SUM(I40:O40) -> 366.88
C41: ='Orçamento Familiar'!C41 -> 0 | E41: ='Orçamento Familiar'!H41 -> 0 | F41: =P41 -> 0 | G41: =E41-F41 -> 0 | P41: =SUM(I41:O41) -> 0
C42: ='Orçamento Familiar'!C42 -> 0 | E42: ='Orçamento Familiar'!H42 -> 0 | F42: =P42 -> 0 | G42: =E42-F42 -> 0 | P42: =SUM(I42:O42) -> 0
C43: ='Orçamento Familiar'!C43 -> 0 | E43: ='Orçamento Familiar'!H43 -> 0 | F43: =P43 -> 0 | G43: =E43-F43 -> 0 | P43: =SUM(I43:O43) -> 0
C44: ='Orçamento Familiar'!C44 -> 0 | E44: ='Orçamento Familiar'!H44 -> 0 | F44: =P44 -> 0 | G44: =E44-F44 -> 0 | P44: =SUM(I44:O44) -> 0
C45: ='Orçamento Familiar'!C45 -> 0 | E45: ='Orçamento Familiar'!H45 -> 0 | F45: =P45 -> 0 | G45: =E45-F45 -> 0 | P45: =SUM(I45:O45) -> 0
B46: Transporte | C46: ='Orçamento Familiar'!C46 -> Combustível | E46: ='Orçamento Familiar'!H46 -> 400 | F46: =P46 -> 0 | G46: =E46-F46 -> 400 | P46: =SUM(I46:O46) -> 0
C47: ='Orçamento Familiar'!C47 -> Manutenção | E47: ='Orçamento Familiar'!H47 -> 555 | F47: =P47 -> 554.16 | G47: =E47-F47 -> 0.84 | N47: 554.16 | P47: =SUM(I47:O47) -> 554.16 | Q47: 430,82 =4/6 123,34 (1/3)radiador
C48: ='Orçamento Familiar'!C48 -> Multas | E48: ='Orçamento Familiar'!H48 -> 0 | F48: =P48 -> 0 | G48: =E48-F48 -> 0 | P48: =SUM(I48:O48) -> 0
C49: ='Orçamento Familiar'!C49 -> Seguro | E49: ='Orçamento Familiar'!H49 -> 0 | F49: =P49 -> 0 | G49: =E49-F49 -> 0 | P49: =SUM(I49:O49) -> 0
C50: ='Orçamento Familiar'!C50 -> Lavagem | E50: ='Orçamento Familiar'!H50 -> 0 | F50: =P50 -> 0 | G50: =E50-F50 -> 0 | P50: =SUM(I50:O50) -> 0
C51: ='Orçamento Familiar'!C51 -> Estacionamento | E51: ='Orçamento Familiar'!H51 -> 0 | F51: =P51 -> 0 | G51: =E51-F51 -> 0 | P51: =SUM(I51:O51) -> 0
C52: ='Orçamento Familiar'!C52 -> Taxi / Uber | E52: ='Orçamento Familiar'!H52 -> 0 | F52: =P52 -> 0 | G52: =E52-F52 -> 0 | P52: =SUM(I52:O52) -> 0
C53: ='Orçamento Familiar'!C53 -> 0 | E53: ='Orçamento Familiar'!H53 -> 0 | F53: =P53 -> 0 | G53: =E53-F53 -> 0 | P53: =SUM(I53:O53) -> 0
C54: ='Orçamento Familiar'!C54 -> 0 | E54: ='Orçamento Familiar'!H54 -> 0 | F54: =P54 -> 0 | G54: =E54-F54 -> 0 | P54: =SUM(I54:O54) -> 0
B55: Saúde | C55: ='Orçamento Familiar'!C55 -> Medicamentos | E55: ='Orçamento Familiar'!H55 -> 80 | F55: =P55 -> 0 | G55: =E55-F55 -> 80 | P55: =SUM(I55:O55) -> 0
C56: ='Orçamento Familiar'!C56 -> Médicos / Exames | E56: ='Orçamento Familiar'!H56 -> 0 | F56: =P56 -> 0 | G56: =E56-F56 -> 0 | P56: =SUM(I56:O56) -> 0
C57: ='Orçamento Familiar'!C57 -> Dentista | E57: ='Orçamento Familiar'!H57 -> 0 | F57: =P57 -> 0 | G57: =E57-F57 -> 0 | P57: =SUM(I57:O57) -> 0
C58: ='Orçamento Familiar'!C58 -> 0 | E58: ='Orçamento Familiar'!H58 -> 0 | F58: =P58 -> 0 | G58: =E58-F58 -> 0 | P58: =SUM(I58:O58) -> 0
C59: ='Orçamento Familiar'!C59 -> 0 | E59: ='Orçamento Familiar'!H59 -> 0 | F59: =P59 -> 0 | G59: =E59-F59 -> 0 | P59: =SUM(I59:O59) -> 0
B60: Impostos | C60: ='Orçamento Familiar'!C60 -> IPVA | E60: ='Orçamento Familiar'!H60 -> 0 | F60: =P60 -> 0 | G60: =E60-F60 -> 0 | P60: =SUM(I60:O60) -> 0
C61: ='Orçamento Familiar'!C61 -> Licenciamento | E61: ='Orçamento Familiar'!H61 -> 0 | F61: =P61 -> 0 | G61: =E61-F61 -> 0 | P61: =SUM(I61:O61) -> 0
C62: ='Orçamento Familiar'!C62 -> Imposto de Renda | E62: ='Orçamento Familiar'!H62 -> 0 | F62: =P62 -> 0 | G62: =E62-F62 -> 0 | P62: =SUM(I62:O62) -> 0
C63: ='Orçamento Familiar'!C63 -> INSS | E63: ='Orçamento Familiar'!H63 -> 0 | F63: =P63 -> 0 | G63: =E63-F63 -> 0 | P63: =SUM(I63:O63) -> 0
C64: ='Orçamento Familiar'!C64 -> 0 | E64: ='Orçamento Familiar'!H64 -> 0 | F64: =P64 -> 0 | G64: =E64-F64 -> 0 | P64: =SUM(I64:O64) -> 0
C65: ='Orçamento Familiar'!C65 -> 0 | E65: ='Orçamento Familiar'!H65 -> 0 | F65: =P65 -> 0 | G65: =E65-F65 -> 0 | P65: =SUM(I65:O65) -> 0
B66: Educação | C66: ='Orçamento Familiar'!C66 -> Especialização | E66: ='Orçamento Familiar'!H66 -> 0 | F66: =P66 -> 0 | G66: =E66-F66 -> 0 | P66: =SUM(I66:O66) -> 0
C67: ='Orçamento Familiar'!C67 -> Cursos | E67: ='Orçamento Familiar'!H67 -> 150 | F67: =P67 -> 146.82 | G67: =E67-F67 -> 3.18 | N67: 146.82 | P67: =SUM(I67:O67) -> 146.82 | Q67: Faculdade Con 2/6=146,83
C68: ='Orçamento Familiar'!C68 -> Mentoria Financeira | E68: ='Orçamento Familiar'!H68 -> 225 | F68: =P68 -> 0 | G68: =E68-F68 -> 225 | P68: =SUM(I68:O68) -> 0
C69: ='Orçamento Familiar'!C69 -> 0 | E69: ='Orçamento Familiar'!H69 -> 0 | F69: =P69 -> 0 | G69: =E69-F69 -> 0 | P69: =SUM(I69:O69) -> 0
C70: ='Orçamento Familiar'!C70 -> 0 | E70: ='Orçamento Familiar'!H70 -> 0 | F70: =P70 -> 0 | G70: =E70-F70 -> 0 | P70: =SUM(I70:O70) -> 0
B71: Filhos | C71: ='Orçamento Familiar'!C71 -> Piano Laura | E71: ='Orçamento Familiar'!H71 -> 0 | F71: =P71 -> 0 | G71: =E71-F71 -> 0 | P71: =SUM(I71:O71) -> 0
C72: ='Orçamento Familiar'!C72 -> Material Escolar | E72: ='Orçamento Familiar'!H72 -> 0 | F72: =P72 -> 0 | G72: =E72-F72 -> 0 | P72: =SUM(I72:O72) -> 0
C73: ='Orçamento Familiar'!C73 -> Mesadas | E73: ='Orçamento Familiar'!H73 -> 190 | F73: =P73 -> 60.81 | G73: =E73-F73 -> 129.19 | N73: 60.81 | P73: =SUM(I73:O73) -> 60.81 | Q73: Levi 08/11
C74: ='Orçamento Familiar'!C74 -> Violão | E74: ='Orçamento Familiar'!H74 -> 0 | F74: =P74 -> 0 | G74: =E74-F74 -> 0 | P74: =SUM(I74:O74) -> 0
C75: ='Orçamento Familiar'!C75 -> Médicos / Exames | E75: ='Orçamento Familiar'!H75 -> 0 | F75: =P75 -> 0 | G75: =E75-F75 -> 0 | P75: =SUM(I75:O75) -> 0
C76: ='Orçamento Familiar'!C76 -> Cursos | E76: ='Orçamento Familiar'!H76 -> 0 | F76: =P76 -> 0 | G76: =E76-F76 -> 0 | P76: =SUM(I76:O76) -> 0
C77: ='Orçamento Familiar'!C77 -> Retiro Carnaval 2026/2027 | E77: ='Orçamento Familiar'!H77 -> 240 | F77: =P77 -> 0 | G77: =E77-F77 -> 240 | P77: =SUM(I77:O77) -> 0
C78: ='Orçamento Familiar'!C78 -> Acampadentro | E78: ='Orçamento Familiar'!H78 -> 0 | F78: =P78 -> 0 | G78: =E78-F78 -> 0 | P78: =SUM(I78:O78) -> 0
C79: ='Orçamento Familiar'!C79 -> 0 | E79: ='Orçamento Familiar'!H79 -> 0 | F79: =P79 -> 0 | G79: =E79-F79 -> 0 | P79: =SUM(I79:O79) -> 0
B80: Pet | C80: ='Orçamento Familiar'!C80 -> Ração | E80: ='Orçamento Familiar'!H80 -> 50 | F80: =P80 -> 0 | G80: =E80-F80 -> 50 | P80: =SUM(I80:O80) -> 0
C81: ='Orçamento Familiar'!C81 -> Vacinas | E81: ='Orçamento Familiar'!H81 -> 0 | F81: =P81 -> 0 | G81: =E81-F81 -> 0 | P81: =SUM(I81:O81) -> 0
C82: ='Orçamento Familiar'!C82 -> Veterinário | E82: ='Orçamento Familiar'!H82 -> 0 | F82: =P82 -> 0 | G82: =E82-F82 -> 0 | P82: =SUM(I82:O82) -> 0
C83: ='Orçamento Familiar'!C83 -> 0 | E83: ='Orçamento Familiar'!H83 -> 0 | F83: =P83 -> 0 | G83: =E83-F83 -> 0 | P83: =SUM(I83:O83) -> 0
C84: ='Orçamento Familiar'!C84 -> 0 | E84: ='Orçamento Familiar'!H84 -> 0 | F84: =P84 -> 0 | G84: =E84-F84 -> 0 | P84: =SUM(I84:O84) -> 0
B85: Total Despesas Essenciais | E85: =SUM(E31:E84) -> 5224.7 | F85: =SUM(F31:F84) -> 1128.67 | G85: =SUM(G31:G84) -> 4096.03 | I85: =SUM(I31:I84) -> 0 | J85: =SUM(J31:J84) -> 0 | K85: =SUM(K31:K84) -> 0 | L85: =SUM(L31:L84) -> 0 | M85: =SUM(M31:M84) -> 0 | N85: =SUM(N31:N84) -> 1128.67 | O85: =SUM(O31:O84) -> 0 | P85: =SUM(P31:P84) -> 1128.67
B86: % sobre Receita | C86: ='Orçamento Familiar'!C166 -> 0 | E86: =E85/E16 -> 0.6919216 | F86: =F85/F16 -> #DIV/0! | I86: =I85/I16 -> #DIV/0! | J86: =J85/J16 -> #DIV/0! | K86: =K85/K16 -> #DIV/0! | L86: =L85/L16 -> #DIV/0! | M86: =M85/M16 -> #DIV/0! | N86: =N85/N16 -> #DIV/0! | O86: =O85/O16 -> #DIV/0! | P86: =P85/P16 -> #DIV/0!
A87: Profissional e Trabalho | B87: Ministério | C87: ='Orçamento Familiar'!C87 -> Materiais (livros) | E87: ='Orçamento Familiar'!H87 -> 30 | F87: =P87 -> 0 | G87: =E87-F87 -> 30 | P87: =SUM(I87:O87) -> 0
C88: ='Orçamento Familiar'!C88 -> 0 | E88: ='Orçamento Familiar'!H88 -> 0 | F88: =P88 -> 0 | G88: =E88-F88 -> 0 | P88: =SUM(I88:O88) -> 0
C89: ='Orçamento Familiar'!C89 -> 0 | E89: ='Orçamento Familiar'!H89 -> 0 | F89: =P89 -> 0 | G89: =E89-F89 -> 0 | P89: =SUM(I89:O89) -> 0
C90: ='Orçamento Familiar'!C90 -> 0 | E90: ='Orçamento Familiar'!H90 -> 0 | F90: =P90 -> 0 | G90: =E90-F90 -> 0 | P90: =SUM(I90:O90) -> 0
C91: ='Orçamento Familiar'!C91 -> 0 | E91: ='Orçamento Familiar'!H91 -> 0 | F91: =P91 -> 0 | G91: =E91-F91 -> 0 | P91: =SUM(I91:O91) -> 0
C92: ='Orçamento Familiar'!C92 -> 0 | E92: ='Orçamento Familiar'!H92 -> 0 | F92: =P92 -> 0 | G92: =E92-F92 -> 0 | P92: =SUM(I92:O92) -> 0
B93: Autônomo | C93: ='Orçamento Familiar'!C93 -> Ferramentas de trabalho | E93: ='Orçamento Familiar'!H93 -> 200 | F93: =P93 -> 161.39 | G93: =E93-F93 -> 38.61 | N93: 161.39 | P93: =SUM(I93:O93) -> 161.39 | Q93: 51,40=12/12
C94: ='Orçamento Familiar'!C94 -> Colaboradores | E94: ='Orçamento Familiar'!H94 -> 0 | F94: =P94 -> 0 | G94: =E94-F94 -> 0 | P94: =SUM(I94:O94) -> 0
C95: ='Orçamento Familiar'!C95 -> 0 | E95: ='Orçamento Familiar'!H95 -> 0 | F95: =P95 -> 0 | G95: =E95-F95 -> 0 | P95: =SUM(I95:O95) -> 0
C96: ='Orçamento Familiar'!C96 -> 0 | E96: ='Orçamento Familiar'!H96 -> 0 | F96: =P96 -> 0 | G96: =E96-F96 -> 0 | P96: =SUM(I96:O96) -> 0
C97: ='Orçamento Familiar'!C97 -> 0 | E97: ='Orçamento Familiar'!H97 -> 0 | F97: =P97 -> 0 | G97: =E97-F97 -> 0 | P97: =SUM(I97:O97) -> 0
C98: ='Orçamento Familiar'!C98 -> 0 | E98: ='Orçamento Familiar'!H98 -> 0 | F98: =P98 -> 0 | G98: =E98-F98 -> 0 | P98: =SUM(I98:O98) -> 0
B99: Total Profissional e Trabalho | E99: =SUM(E87:E98) -> 230 | F99: =SUM(F87:F98) -> 161.39 | G99: =SUM(G87:G98) -> 68.61 | I99: =SUM(I87:I98) -> 0 | J99: =SUM(J87:J98) -> 0 | K99: =SUM(K87:K98) -> 0 | L99: =SUM(L87:L98) -> 0 | M99: =SUM(M87:M98) -> 0 | N99: =SUM(N87:N98) -> 161.39 | O99: =SUM(O87:O98) -> 0 | P99: =SUM(P87:P98) -> 161.39
B100: % sobre Receita | E100: =E99/E16 -> 0.030459542 | F100: =F99/F16 -> #DIV/0! | I100: =I99/I16 -> #DIV/0! | J100: =J99/J16 -> #DIV/0! | K100: =K99/K16 -> #DIV/0! | L100: =L99/L16 -> #DIV/0! | M100: =M99/M16 -> #DIV/0! | N100: =N99/N16 -> #DIV/0! | O100: =O99/O16 -> #DIV/0! | P100: =P99/P16 -> #DIV/0!
A101: Contribuição | B101: Ofertas | C101: ='Orçamento Familiar'!C101 -> Dízimo | E101: ='Orçamento Familiar'!H101 -> 850 | F101: =P101 -> 0 | G101: =E101-F101 -> 850 | P101: =SUM(I101:O101) -> 0
C102: ='Orçamento Familiar'!C102 -> Sacrificial | E102: ='Orçamento Familiar'!H102 -> 0 | F102: =P102 -> 0 | G102: =E102-F102 -> 0 | P102: =SUM(I102:O102) -> 0
C103: ='Orçamento Familiar'!C103 -> Doações | E103: ='Orçamento Familiar'!H103 -> 0 | F103: =P103 -> 0 | G103: =E103-F103 -> 0 | P103: =SUM(I103:O103) -> 0
C104: ='Orçamento Familiar'!C104 -> 0 | E104: ='Orçamento Familiar'!H104 -> 0 | F104: =P104 -> 0 | G104: =E104-F104 -> 0 | P104: =SUM(I104:O104) -> 0
B105: Total Contribuição | E105: =SUM(E101:E104) -> 850 | F105: =SUM(F101:F104) -> 0 | G105: =SUM(G101:G104) -> 850 | I105: =SUM(I101:I104) -> 0 | J105: =SUM(J101:J104) -> 0 | K105: =SUM(K101:K104) -> 0 | L105: =SUM(L101:L104) -> 0 | M105: =SUM(M101:M104) -> 0 | N105: =SUM(N101:N104) -> 0 | O105: =SUM(O101:O104) -> 0 | P105: =SUM(P101:P104) -> 0
...

Sheet Mai
A2: Fluxo de Caixa Familiar
A5: Categoria | C5: Descrição | D5: Percentual | E5: =I5 -> Maio | I5: Maio
E6: Orçado | F6: Realizado | G6: Variação | I6: Semana 1 | J6: Semana 2 | K6: Semana 3 | L6: Semana 4 | M6: Semana 5 | N6: =Jan!N6 -> Cartão Nubank | O6: =Jan!O6 -> Cartão C & A | P6: Total
A7: Receitas | C7: ='Orçamento Familiar'!C7 -> Prebenda | E7: ='Orçamento Familiar'!I7 -> 7216 | F7: =P7 -> 0 | G7: =F7-E7 -> -7216 | P7: =SUM(I7:O7) -> 0
C8: ='Orçamento Familiar'!C8 -> Inglês | E8: ='Orçamento Familiar'!I8 -> 335 | F8: =P8 -> 0 | G8: =F8-E8 -> -335 | P8: =SUM(I8:O8) -> 0
C9: ='Orçamento Familiar'!C9 -> 13º Salário | E9: ='Orçamento Familiar'!I9 -> 0 | F9: =P9 -> 0 | G9: =F9-E9 -> 0 | P9: =SUM(I9:O9) -> 0
C10: ='Orçamento Familiar'!C10 -> Renda Extra | E10: ='Orçamento Familiar'!I10 -> 0 | F10: =P10 -> 0 | G10: =F10-E10 -> 0 | P10: =SUM(I10:O10) -> 0
C11: ='Orçamento Familiar'!C11 -> 0 | E11: ='Orçamento Familiar'!I11 -> 0 | F11: =P11 -> 0 | G11: =F11-E11 -> 0 | P11: =SUM(I11:O11) -> 0
C12: ='Orçamento Familiar'!C12 -> 0 | E12: ='Orçamento Familiar'!I12 -> 0 | F12: =P12 -> 0 | G12: =F12-E12 -> 0 | P12: =SUM(I12:O12) -> 0
C13: ='Orçamento Familiar'!C13 -> 0 | E13: ='Orçamento Familiar'!I13 -> 0 | F13: =P13 -> 0 | G13: =F13-E13 -> 0 | P13: =SUM(I13:O13) -> 0
C14: ='Orçamento Familiar'!C14 -> 0 | E14: ='Orçamento Familiar'!I14 -> 0 | F14: =P14 -> 0 | G14: =F14-E14 -> 0 | P14: =SUM(I14:O14) -> 0
C15: ='Orçamento Familiar'!C15 -> 0 | E15: ='Orçamento Familiar'!I15 -> 0 | F15: =P15 -> 0 | G15: =F15-E15 -> 0 | P15: =SUM(I15:O15) -> 0
C16: Total | E16: =SUM(E7:E15) -> 7551 | F16: =SUM(F7:F15) -> 0 | G16: =SUM(G7:G15) -> -7551 | I16: =SUM(I7:I15) -> 0 | J16: =SUM(J7:J15) -> 0 | K16: =SUM(K7:K15) -> 0 | L16: =SUM(L7:L15) -> 0 | M16: =SUM(M7:M15) -> 0 | N16: =SUM(N7:N15) -> 0 | O16: =SUM(O7:O15) -> 0 | P16: =SUM(P7:P15) -> 0
A18: Investimentos Insira aqui o montante mensal que você destinará aos seus investimentos | C18: Descrição | D18: Percentual | E18: Orçado | F18: Realizado | G18: Variação | I18: =I6 -> Semana 1 | J18: =J6 -> Semana 2 | K18: =K6 -> Semana 3 | L18: =L6 -> Semana 4 | M18: =M6 -> Semana 5 | P18: =P6 -> Total
C19: ='Orçamento Familiar'!C19 -> Reserva de Emergência (CP) R$ 9.151 | E19: ='Orçamento Familiar'!I19 -> 0 | F19: =P19 -> 0 | G19: =F19-E19 -> 0 | P19: =SUM(I19:O19) -> 0
C20: ='Orçamento Familiar'!C20 -> Projeto 1 | E20: ='Orçamento Familiar'!I20 -> 0 | F20: =P20 -> 0 | G20: =F20-E20 -> 0 | P20: =SUM(I20:O20) -> 0
C21: ='Orçamento Familiar'!C21 -> Projeto 2 | E21: ='Orçamento Familiar'!I21 -> 0 | F21: =P21 -> 0 | G21: =F21-E21 -> 0 | P21: =SUM(I21:O21) -> 0
C22: ='Orçamento Familiar'!C22 -> Projeto 3 | E22: ='Orçamento Familiar'!I22 -> 0 | F22: =P22 -> 0 | G22: =F22-E22 -> 0 | P22: =SUM(I22:O22) -> 0
C23: ='Orçamento Familiar'!C23 -> Projeto 4 | E23: ='Orçamento Familiar'!I23 -> 0 | F23: =P23 -> 0 | G23: =F23-E23 -> 0 | P23: =SUM(I23:O23) -> 0
C24: ='Orçamento Familiar'!C24 -> Projeto 5 | E24: ='Orçamento Familiar'!I24 -> 0 | F24: =P24 -> 0 | G24: =F24-E24 -> 0 | P24: =SUM(I24:O24) -> 0
C25: ='Orçamento Familiar'!C25 -> Projeto 6 | E25: ='Orçamento Familiar'!I25 -> 0 | F25: =P25 -> 0 | G25: =F25-E25 -> 0 | P25: =SUM(I25:O25) -> 0
C26: ='Orçamento Familiar'!C26 -> Independência Financeira | E26: ='Orçamento Familiar'!I26 -> 0 | F26: =P26 -> 0 | G26: =F26-E26 -> 0 | P26: =SUM(I26:O26) -> 0
C27: Total Investimentos | D27: =SUM(D19:D26) -> 0 | E27: =SUM(E19:E26) -> 0 | F27: =SUM(F19:F26) -> 0 | G27: =SUM(G19:G26) -> 0 | I27: =SUM(I19:I26) -> 0 | J27: =SUM(J19:J26) -> 0 | K27: =SUM(K19:K26) -> 0 | L27: =SUM(L19:L26) -> 0 | M27: =SUM(M19:M26) -> 0 | N27: =SUM(N19:N26) -> 0 | O27: =SUM(O19:O26) -> 0 | P27: =SUM(P19:P26) -> 0
C28: % sobre Receita | E28: =E27/E16 -> 0 | F28: =F27/F16 -> #DIV/0! | I28: =I27/I16 -> #DIV/0! | J28: =J27/J16 -> #DIV/0! | K28: =K27/K16 -> #DIV/0! | L28: =L27/L16 -> #DIV/0! | M28: =M27/M16 -> #DIV/0! | N28: =N27/N16 -> #DIV/0! | O28: =O27/O16 -> #DIV/0! | P28: =P27/P16 -> #DIV/0!
A30: Categoria | C30: Descrição | D30: Percentual | E30: Orçado | F30: Realizado | G30: Variação | I30: =I18 -> Semana 1 | J30: =J18 -> Semana 2 | K30: =K18 -> Semana 3 | L30: =L18 -> Semana 4 | M30: =M18 -> Semana 5 | N30: =N6 -> Cartão Nubank | O30: =O6 -> Cartão C & A | P30: =P18 -> Total
A31: Despesas Essenciais | B31: Moradia | C31: ='Orçamento Familiar'!C31 -> Aluguel | E31: ='Orçamento Familiar'!I31 -> 0 | F31: =P31 -> 0 | G31: =E31-F31 -> 0 | P31: =SUM(I31:O31) -> 0
C32: ='Orçamento Familiar'!C32 -> Energia Elétrica | E32: ='Orçamento Familiar'!I32 -> 0 | F32: =P32 -> 0 | G32: =E32-F32 -> 0 | P32: =SUM(I32:O32) -> 0
C33: ='Orçamento Familiar'!C33 -> Água e Esgoto | E33: ='Orçamento Familiar'!I33 -> 0 | F33: =P33 -> 0 | G33: =E33-F33 -> 0 | P33: =SUM(I33:O33) -> 0
C34: ='Orçamento Familiar'!C34 -> Gás | E34: ='Orçamento Familiar'!I34 -> 0 | F34: =P34 -> 0 | G34: =E34-F34 -> 0 | P34: =SUM(I34:O34) -> 0
C35: ='Orçamento Familiar'!C35 -> Internet e Celular | E35: ='Orçamento Familiar'!I35 -> 184.7 | F35: =P35 -> 0 | G35: =E35-F35 -> 184.7 | P35: =SUM(I35:O35) -> 0
C36: ='Orçamento Familiar'!C36 -> Manutenção | E36: ='Orçamento Familiar'!I36 -> 50 | F36: =P36 -> 0 | G36: =E36-F36 -> 50 | P36: =SUM(I36:O36) -> 0
C37: ='Orçamento Familiar'!C37 -> 0 | E37: ='Orçamento Familiar'!I37 -> 0 | F37: =P37 -> 0 | G37: =E37-F37 -> 0 | P37: =SUM(I37:O37) -> 0
C38: ='Orçamento Familiar'!C38 -> 0 | E38: ='Orçamento Familiar'!I38 -> 0 | F38: =P38 -> 0 | G38: =E38-F38 -> 0 | P38: =SUM(I38:O38) -> 0
C39: ='Orçamento Familiar'!C39 -> 0 | E39: ='Orçamento Familiar'!I39 -> 0 | F39: =P39 -> 0 | G39: =E39-F39 -> 0 | P39: =SUM(I39:O39) -> 0
B40: Alimentação | C40: ='Orçamento Familiar'!C40 -> Supermercado | E40: ='Orçamento Familiar'!I40 -> 3100 | F40: =P40 -> 0 | G40: =E40-F40 -> 3100 | P40: =SUM(I40:O40) -> 0
C41: ='Orçamento Familiar'!C41 -> 0 | E41: ='Orçamento Familiar'!I41 -> 0 | F41: =P41 -> 0 | G41: =E41-F41 -> 0 | P41: =SUM(I41:O41) -> 0
C42: ='Orçamento Familiar'!C42 -> 0 | E42: ='Orçamento Familiar'!I42 -> 0 | F42: =P42 -> 0 | G42: =E42-F42 -> 0 | P42: =SUM(I42:O42) -> 0
C43: ='Orçamento Familiar'!C43 -> 0 | E43: ='Orçamento Familiar'!I43 -> 0 | F43: =P43 -> 0 | G43: =E43-F43 -> 0 | P43: =SUM(I43:O43) -> 0
C44: ='Orçamento Familiar'!C44 -> 0 | E44: ='Orçamento Familiar'!I44 -> 0 | F44: =P44 -> 0 | G44: =E44-F44 -> 0 | P44: =SUM(I44:O44) -> 0
C45: ='Orçamento Familiar'!C45 -> 0 | E45: ='Orçamento Familiar'!I45 -> 0 | F45: =P45 -> 0 | G45: =E45-F45 -> 0 | P45: =SUM(I45:O45) -> 0
B46: Transporte | C46: ='Orçamento Familiar'!C46 -> Combustível | E46: ='Orçamento Familiar'!I46 -> 400 | F46: =P46 -> 0 | G46: =E46-F46 -> 400 | P46: =SUM(I46:O46) -> 0
C47: ='Orçamento Familiar'!C47 -> Manutenção | E47: ='Orçamento Familiar'!I47 -> 555 | F47: =P47 -> 430.9 | G47: =E47-F47 -> 124.1 | N47: 430.9 | P47: =SUM(I47:O47) -> 430.9 | Q47: 430,90 =5/6
C48: ='Orçamento Familiar'!C48 -> Multas | E48: ='Orçamento Familiar'!I48 -> 0 | F48: =P48 -> 0 | G48: =E48-F48 -> 0 | P48: =SUM(I48:O48) -> 0
C49: ='Orçamento Familiar'!C49 -> Seguro | E49: ='Orçamento Familiar'!I49 -> 0 | F49: =P49 -> 0 | G49: =E49-F49 -> 0 | P49: =SUM(I49:O49) -> 0
C50: ='Orçamento Familiar'!C50 -> Lavagem | E50: ='Orçamento Familiar'!I50 -> 0 | F50: =P50 -> 0 | G50: =E50-F50 -> 0 | P50: =SUM(I50:O50) -> 0
C51: ='Orçamento Familiar'!C51 -> Estacionamento | E51: ='Orçamento Familiar'!I51 -> 0 | F51: =P51 -> 0 | G51: =E51-F51 -> 0 | P51: =SUM(I51:O51) -> 0
C52: ='Orçamento Familiar'!C52 -> Taxi / Uber | E52: ='Orçamento Familiar'!I52 -> 0 | F52: =P52 -> 0 | G52: =E52-F52 -> 0 | P52: =SUM(I52:O52) -> 0
C53: ='Orçamento Familiar'!C53 -> 0 | E53: ='Orçamento Familiar'!I53 -> 0 | F53: =P53 -> 0 | G53: =E53-F53 -> 0 | P53: =SUM(I53:O53) -> 0
C54: ='Orçamento Familiar'!C54 -> 0 | E54: ='Orçamento Familiar'!I54 -> 0 | F54: =P54 -> 0 | G54: =E54-F54 -> 0 | P54: =SUM(I54:O54) -> 0
B55: Saúde | C55: ='Orçamento Familiar'!C55 -> Medicamentos | E55: ='Orçamento Familiar'!I55 -> 80 | F55: =P55 -> 0 | G55: =E55-F55 -> 80 | P55: =SUM(I55:O55) -> 0
C56: ='Orçamento Familiar'!C56 -> Médicos / Exames | E56: ='Orçamento Familiar'!I56 -> 0 | F56: =P56 -> 0 | G56: =E56-F56 -> 0 | P56: =SUM(I56:O56) -> 0
C57: ='Orçamento Familiar'!C57 -> Dentista | E57: ='Orçamento Familiar'!I57 -> 0 | F57: =P57 -> 0 | G57: =E57-F57 -> 0 | P57: =SUM(I57:O57) -> 0
C58: ='Orçamento Familiar'!C58 -> 0 | E58: ='Orçamento Familiar'!I58 -> 0 | F58: =P58 -> 0 | G58: =E58-F58 -> 0 | P58: =SUM(I58:O58) -> 0
C59: ='Orçamento Familiar'!C59 -> 0 | E59: ='Orçamento Familiar'!I59 -> 0 | F59: =P59 -> 0 | G59: =E59-F59 -> 0 | P59: =SUM(I59:O59) -> 0
B60: Impostos | C60: ='Orçamento Familiar'!C60 -> IPVA | E60: ='Orçamento Familiar'!I60 -> 0 | F60: =P60 -> 0 | G60: =E60-F60 -> 0 | P60: =SUM(I60:O60) -> 0
C61: ='Orçamento Familiar'!C61 -> Licenciamento | E61: ='Orçamento Familiar'!I61 -> 0 | F61: =P61 -> 0 | G61: =E61-F61 -> 0 | P61: =SUM(I61:O61) -> 0
C62: ='Orçamento Familiar'!C62 -> Imposto de Renda | E62: ='Orçamento Familiar'!I62 -> 0 | F62: =P62 -> 0 | G62: =E62-F62 -> 0 | P62: =SUM(I62:O62) -> 0
C63: ='Orçamento Familiar'!C63 -> INSS | E63: ='Orçamento Familiar'!I63 -> 0 | F63: =P63 -> 0 | G63: =E63-F63 -> 0 | P63: =SUM(I63:O63) -> 0
C64: ='Orçamento Familiar'!C64 -> 0 | E64: ='Orçamento Familiar'!I64 -> 0 | F64: =P64 -> 0 | G64: =E64-F64 -> 0 | P64: =SUM(I64:O64) -> 0
C65: ='Orçamento Familiar'!C65 -> 0 | E65: ='Orçamento Familiar'!I65 -> 0 | F65: =P65 -> 0 | G65: =E65-F65 -> 0 | P65: =SUM(I65:O65) -> 0
B66: Educação | C66: ='Orçamento Familiar'!C66 -> Especialização | E66: ='Orçamento Familiar'!I66 -> 0 | F66: =P66 -> 0 | G66: =E66-F66 -> 0 | P66: =SUM(I66:O66) -> 0
C67: ='Orçamento Familiar'!C67 -> Cursos | E67: ='Orçamento Familiar'!I67 -> 150 | F67: =P67 -> 146.83 | G67: =E67-F67 -> 3.17 | N67: 146.83 | P67: =SUM(I67:O67) -> 146.83 | Q67: Faculdade Con 3/6=146,83
C68: ='Orçamento Familiar'!C68 -> Mentoria Financeira | E68: ='Orçamento Familiar'!I68 -> 225 | F68: =P68 -> 0 | G68: =E68-F68 -> 225 | P68: =SUM(I68:O68) -> 0
C69: ='Orçamento Familiar'!C69 -> 0 | E69: ='Orçamento Familiar'!I69 -> 0 | F69: =P69 -> 0 | G69: =E69-F69 -> 0 | P69: =SUM(I69:O69) -> 0
C70: ='Orçamento Familiar'!C70 -> 0 | E70: ='Orçamento Familiar'!I70 -> 0 | F70: =P70 -> 0 | G70: =E70-F70 -> 0 | P70: =SUM(I70:O70) -> 0
B71: Filhos | C71: ='Orçamento Familiar'!C71 -> Piano Laura | E71: ='Orçamento Familiar'!I71 -> 0 | F71: =P71 -> 0 | G71: =E71-F71 -> 0 | P71: =SUM(I71:O71) -> 0
C72: ='Orçamento Familiar'!C72 -> Material Escolar | E72: ='Orçamento Familiar'!I72 -> 0 | F72: =P72 -> 0 | G72: =E72-F72 -> 0 | P72: =SUM(I72:O72) -> 0
C73: ='Orçamento Familiar'!C73 -> Mesadas | E73: ='Orçamento Familiar'!I73 -> 190 | F73: =P73 -> 60.82 | G73: =E73-F73 -> 129.18 | N73: 60.82 | P73: =SUM(I73:O73) -> 60.82 | Q73: 60,82=9/11
C74: ='Orçamento Familiar'!C74 -> Violão | E74: ='Orçamento Familiar'!I74 -> 0 | F74: =P74 -> 0 | G74: =E74-F74 -> 0 | P74: =SUM(I74:O74) -> 0
C75: ='Orçamento Familiar'!C75 -> Médicos / Exames | E75: ='Orçamento Familiar'!I75 -> 0 | F75: =P75 -> 0 | G75: =E75-F75 -> 0 | P75: =SUM(I75:O75) -> 0
C76: ='Orçamento Familiar'!C76 -> Cursos | E76: ='Orçamento Familiar'!I76 -> 0 | F76: =P76 -> 0 | G76: =E76-F76 -> 0 | P76: =SUM(I76:O76) -> 0
C77: ='Orçamento Familiar'!C77 -> Retiro Carnaval 2026/2027 | E77: ='Orçamento Familiar'!I77 -> 240 | F77: =P77 -> 0 | G77: =E77-F77 -> 240 | P77: =SUM(I77:O77) -> 0
C78: ='Orçamento Familiar'!C78 -> Acampadentro | E78: ='Orçamento Familiar'!I78 -> 0 | F78: =P78 -> 0 | G78: =E78-F78 -> 0 | P78: =SUM(I78:O78) -> 0
C79: ='Orçamento Familiar'!C79 -> 0 | E79: ='Orçamento Familiar'!I79 -> 0 | F79: =P79 -> 0 | G79: =E79-F79 -> 0 | P79: =SUM(I79:O79) -> 0
B80: Pet | C80: ='Orçamento Familiar'!C80 -> Ração | E80: ='Orçamento Familiar'!I80 -> 50 | F80: =P80 -> 0 | G80: =E80-F80 -> 50 | P80: =SUM(I80:O80) -> 0
C81: ='Orçamento Familiar'!C81 -> Vacinas | E81: ='Orçamento Familiar'!I81 -> 0 | F81: =P81 -> 0 | G81: =E81-F81 -> 0 | P81: =SUM(I81:O81) -> 0
C82: ='Orçamento Familiar'!C82 -> Veterinário | E82: ='Orçamento Familiar'!I82 -> 0 | F82: =P82 -> 0 | G82: =E82-F82 -> 0 | P82: =SUM(I82:O82) -> 0
C83: ='Orçamento Familiar'!C83 -> 0 | E83: ='Orçamento Familiar'!I83 -> 0 | F83: =P83 -> 0 | G83: =E83-F83 -> 0 | P83: =SUM(I83:O83) -> 0
C84: ='Orçamento Familiar'!C84 -> 0 | E84: ='Orçamento Familiar'!I84 -> 0 | F84: =P84 -> 0 | G84: =E84-F84 -> 0 | P84: =SUM(I84:O84) -> 0
B85: Total Despesas Essenciais | E85: =SUM(E31:E84) -> 5224.7 | F85: =SUM(F31:F84) -> 638.55 | G85: =SUM(G31:G84) -> 4586.15 | I85: =SUM(I31:I84) -> 0 | J85: =SUM(J31:J84) -> 0 | K85: =SUM(K31:K84) -> 0 | L85: =SUM(L31:L84) -> 0 | M85: =SUM(M31:M84) -> 0 | N85: =SUM(N31:N84) -> 638.55 | O85: =SUM(O31:O84) -> 0 | P85: =SUM(P31:P84) -> 638.55
B86: % sobre Receita | C86: ='Orçamento Familiar'!C166 -> 0 | E86: =E85/E16 -> 0.6919216 | F86: =F85/F16 -> #DIV/0! | I86: =I85/I16 -> #DIV/0! | J86: =J85/J16 -> #DIV/0! | K86: =K85/K16 -> #DIV/0! | L86: =L85/L16 -> #DIV/0! | M86: =M85/M16 -> #DIV/0! | N86: =N85/N16 -> #DIV/0! | O86: =O85/O16 -> #DIV/0! | P86: =P85/P16 -> #DIV/0!
A87: Profissional e Trabalho | B87: Ministério | C87: ='Orçamento Familiar'!C87 -> Materiais (livros) | E87: ='Orçamento Familiar'!I87 -> 30 | F87: =P87 -> 0 | G87: =E87-F87 -> 30 | P87: =SUM(I87:O87) -> 0
C88: ='Orçamento Familiar'!C88 -> 0 | E88: ='Orçamento Familiar'!I88 -> 0 | F88: =P88 -> 0 | G88: =E88-F88 -> 0 | P88: =SUM(I88:O88) -> 0
C89: ='Orçamento Familiar'!C89 -> 0 | E89: ='Orçamento Familiar'!I89 -> 0 | F89: =P89 -> 0 | G89: =E89-F89 -> 0 | P89: =SUM(I89:O89) -> 0
C90: ='Orçamento Familiar'!C90 -> 0 | E90: ='Orçamento Familiar'!I90 -> 0 | F90: =P90 -> 0 | G90: =E90-F90 -> 0 | P90: =SUM(I90:O90) -> 0
C91: ='Orçamento Familiar'!C91 -> 0 | E91: ='Orçamento Familiar'!I91 -> 0 | F91: =P91 -> 0 | G91: =E91-F91 -> 0 | P91: =SUM(I91:O91) -> 0
C92: ='Orçamento Familiar'!C92 -> 0 | E92: ='Orçamento Familiar'!I92 -> 0 | F92: =P92 -> 0 | G92: =E92-F92 -> 0 | P92: =SUM(I92:O92) -> 0
B93: Autônomo | C93: ='Orçamento Familiar'!C93 -> Ferramentas de trabalho | E93: ='Orçamento Familiar'!I93 -> 150 | F93: =P93 -> 0 | G93: =E93-F93 -> 150 | P93: =SUM(I93:O93) -> 0
C94: ='Orçamento Familiar'!C94 -> Colaboradores | E94: ='Orçamento Familiar'!I94 -> 0 | F94: =P94 -> 0 | G94: =E94-F94 -> 0 | P94: =SUM(I94:O94) -> 0
C95: ='Orçamento Familiar'!C95 -> 0 | E95: ='Orçamento Familiar'!I95 -> 0 | F95: =P95 -> 0 | G95: =E95-F95 -> 0 | P95: =SUM(I95:O95) -> 0
C96: ='Orçamento Familiar'!C96 -> 0 | E96: ='Orçamento Familiar'!I96 -> 0 | F96: =P96 -> 0 | G96: =E96-F96 -> 0 | P96: =SUM(I96:O96) -> 0
C97: ='Orçamento Familiar'!C97 -> 0 | E97: ='Orçamento Familiar'!I97 -> 0 | F97: =P97 -> 0 | G97: =E97-F97 -> 0 | P97: =SUM(I97:O97) -> 0
C98: ='Orçamento Familiar'!C98 -> 0 | E98: ='Orçamento Familiar'!I98 -> 0 | F98: =P98 -> 0 | G98: =E98-F98 -> 0 | P98: =SUM(I98:O98) -> 0
B99: Total Profissional e Trabalho | E99: =SUM(E87:E98) -> 180 | F99: =SUM(F87:F98) -> 0 | G99: =SUM(G87:G98) -> 180 | I99: =SUM(I87:I98) -> 0 | J99: =SUM(J87:J98) -> 0 | K99: =SUM(K87:K98) -> 0 | L99: =SUM(L87:L98) -> 0 | M99: =SUM(M87:M98) -> 0 | N99: =SUM(N87:N98) -> 0 | O99: =SUM(O87:O98) -> 0 | P99: =SUM(P87:P98) -> 0
B100: % sobre Receita | E100: =E99/E16 -> 0.023837902 | F100: =F99/F16 -> #DIV/0! | I100: =I99/I16 -> #DIV/0! | J100: =J99/J16 -> #DIV/0! | K100: =K99/K16 -> #DIV/0! | L100: =L99/L16 -> #DIV/0! | M100: =M99/M16 -> #DIV/0! | N100: =N99/N16 -> #DIV/0! | O100: =O99/O16 -> #DIV/0! | P100: =P99/P16 -> #DIV/0!
A101: Contribuição | B101: Ofertas | C101: ='Orçamento Familiar'!C101 -> Dízimo | E101: ='Orçamento Familiar'!I101 -> 850 | F101: =P101 -> 0 | G101: =E101-F101 -> 850 | P101: =SUM(I101:O101) -> 0
C102: ='Orçamento Familiar'!C102 -> Sacrificial | E102: ='Orçamento Familiar'!I102 -> 0 | F102: =P102 -> 0 | G102: =E102-F102 -> 0 | P102: =SUM(I102:O102) -> 0
C103: ='Orçamento Familiar'!C103 -> Doações | E103: ='Orçamento Familiar'!I103 -> 0 | F103: =P103 -> 0 | G103: =E103-F103 -> 0 | P103: =SUM(I103:O103) -> 0
C104: ='Orçamento Familiar'!C104 -> 0 | E104: ='Orçamento Familiar'!I104 -> 0 | F104: =P104 -> 0 | G104: =E104-F104 -> 0 | P104: =SUM(I104:O104) -> 0
B105: Total Contribuição | E105: =SUM(E101:E104) -> 850 | F105: =SUM(F101:F104) -> 0 | G105: =SUM(G101:G104) -> 850 | I105: =SUM(I101:I104) -> 0 | J105: =SUM(J101:J104) -> 0 | K105: =SUM(K101:K104) -> 0 | L105: =SUM(L101:L104) -> 0 | M105: =SUM(M101:M104) -> 0 | N105: =SUM(N101:N104) -> 0 | O105: =SUM(O101:O104) -> 0 | P105: =SUM(P101:P104) -> 0
...

Sheet Jun
A2: Fluxo de Caixa Familiar
A5: Categoria | C5: Descrição | D5: Percentual | E5: =I5 -> Junho | I5: Junho
E6: Orçado | F6: Realizado | G6: Variação | I6: Semana 1 | J6: Semana 2 | K6: Semana 3 | L6: Semana 4 | M6: Semana 5 | N6: =Jan!N6 -> Cartão Nubank | O6: =Jan!O6 -> Cartão C & A | P6: Total
A7: Receitas | C7: ='Orçamento Familiar'!C7 -> Prebenda | E7: ='Orçamento Familiar'!J7 -> 7216 | F7: =P7 -> 0 | G7: =F7-E7 -> -7216 | P7: =SUM(I7:O7) -> 0
C8: ='Orçamento Familiar'!C8 -> Inglês | E8: ='Orçamento Familiar'!J8 -> 335 | F8: =P8 -> 0 | G8: =F8-E8 -> -335 | P8: =SUM(I8:O8) -> 0
C9: ='Orçamento Familiar'!C9 -> 13º Salário | E9: ='Orçamento Familiar'!J9 -> 0 | F9: =P9 -> 0 | G9: =F9-E9 -> 0 | P9: =SUM(I9:O9) -> 0
C10: ='Orçamento Familiar'!C10 -> Renda Extra | E10: ='Orçamento Familiar'!J10 -> 0 | F10: =P10 -> 0 | G10: =F10-E10 -> 0 | P10: =SUM(I10:O10) -> 0
C11: ='Orçamento Familiar'!C11 -> 0 | E11: ='Orçamento Familiar'!J11 -> 0 | F11: =P11 -> 0 | G11: =F11-E11 -> 0 | P11: =SUM(I11:O11) -> 0
C12: ='Orçamento Familiar'!C12 -> 0 | E12: ='Orçamento Familiar'!J12 -> 0 | F12: =P12 -> 0 | G12: =F12-E12 -> 0 | P12: =SUM(I12:O12) -> 0
C13: ='Orçamento Familiar'!C13 -> 0 | E13: ='Orçamento Familiar'!J13 -> 0 | F13: =P13 -> 0 | G13: =F13-E13 -> 0 | P13: =SUM(I13:O13) -> 0
C14: ='Orçamento Familiar'!C14 -> 0 | E14: ='Orçamento Familiar'!J14 -> 0 | F14: =P14 -> 0 | G14: =F14-E14 -> 0 | P14: =SUM(I14:O14) -> 0
C15: ='Orçamento Familiar'!C15 -> 0 | E15: ='Orçamento Familiar'!J15 -> 0 | F15: =P15 -> 0 | G15: =F15-E15 -> 0 | P15: =SUM(I15:O15) -> 0
C16: Total | E16: =SUM(E7:E15) -> 7551 | F16: =SUM(F7:F15) -> 0 | G16: =SUM(G7:G15) -> -7551 | I16: =SUM(I7:I15) -> 0 | J16: =SUM(J7:J15) -> 0 | K16: =SUM(K7:K15) -> 0 | L16: =SUM(L7:L15) -> 0 | M16: =SUM(M7:M15) -> 0 | N16: =SUM(N7:N15) -> 0 | O16: =SUM(O7:O15) -> 0 | P16: =SUM(P7:P15) -> 0
A18: Investimentos Insira aqui o montante mensal que você destinará aos seus investimentos | C18: Descrição | D18: Percentual | E18: Orçado | F18: Realizado | G18: Variação | I18: =I6 -> Semana 1 | J18: =J6 -> Semana 2 | K18: =K6 -> Semana 3 | L18: =L6 -> Semana 4 | M18: =M6 -> Semana 5 | P18: =P6 -> Total
C19: ='Orçamento Familiar'!C19 -> Reserva de Emergência (CP) R$ 9.151 | E19: ='Orçamento Familiar'!J19 -> 0 | F19: =P19 -> 0 | G19: =F19-E19 -> 0 | P19: =SUM(I19:O19) -> 0
C20: ='Orçamento Familiar'!C20 -> Projeto 1 | E20: ='Orçamento Familiar'!J20 -> 0 | F20: =P20 -> 0 | G20: =F20-E20 -> 0 | P20: =SUM(I20:O20) -> 0
C21: ='Orçamento Familiar'!C21 -> Projeto 2 | E21: ='Orçamento Familiar'!J21 -> 0 | F21: =P21 -> 0 | G21: =F21-E21 -> 0 | P21: =SUM(I21:O21) -> 0
C22: ='Orçamento Familiar'!C22 -> Projeto 3 | E22: ='Orçamento Familiar'!J22 -> 0 | F22: =P22 -> 0 | G22: =F22-E22 -> 0 | P22: =SUM(I22:O22) -> 0
C23: ='Orçamento Familiar'!C23 -> Projeto 4 | E23: ='Orçamento Familiar'!J23 -> 0 | F23: =P23 -> 0 | G23: =F23-E23 -> 0 | P23: =SUM(I23:O23) -> 0
C24: ='Orçamento Familiar'!C24 -> Projeto 5 | E24: ='Orçamento Familiar'!J24 -> 0 | F24: =P24 -> 0 | G24: =F24-E24 -> 0 | P24: =SUM(I24:O24) -> 0
C25: ='Orçamento Familiar'!C25 -> Projeto 6 | E25: ='Orçamento Familiar'!J25 -> 0 | F25: =P25 -> 0 | G25: =F25-E25 -> 0 | P25: =SUM(I25:O25) -> 0
C26: ='Orçamento Familiar'!C26 -> Independência Financeira | E26: ='Orçamento Familiar'!J26 -> 0 | F26: =P26 -> 0 | G26: =F26-E26 -> 0 | P26: =SUM(I26:O26) -> 0
C27: Total Investimentos | D27: =SUM(D19:D26) -> 0 | E27: =SUM(E19:E26) -> 0 | F27: =SUM(F19:F26) -> 0 | G27: =SUM(G19:G26) -> 0 | I27: =SUM(I19:I26) -> 0 | J27: =SUM(J19:J26) -> 0 | K27: =SUM(K19:K26) -> 0 | L27: =SUM(L19:L26) -> 0 | M27: =SUM(M19:M26) -> 0 | N27: =SUM(N19:N26) -> 0 | O27: =SUM(O19:O26) -> 0 | P27: =SUM(P19:P26) -> 0
C28: % sobre Receita | E28: =E27/E16 -> 0 | F28: =F27/F16 -> #DIV/0! | I28: =I27/I16 -> #DIV/0! | J28: =J27/J16 -> #DIV/0! | K28: =K27/K16 -> #DIV/0! | L28: =L27/L16 -> #DIV/0! | M28: =M27/M16 -> #DIV/0! | N28: =N27/N16 -> #DIV/0! | O28: =O27/O16 -> #DIV/0! | P28: =P27/P16 -> #DIV/0!
A30: Categoria | C30: Descrição | D30: Percentual | E30: Orçado | F30: Realizado | G30: Variação | I30: =I18 -> Semana 1 | J30: =J18 -> Semana 2 | K30: =K18 -> Semana 3 | L30: =L18 -> Semana 4 | M30: =M18 -> Semana 5 | N30: =N6 -> Cartão Nubank | O30: =O6 -> Cartão C & A | P30: =P18 -> Total
A31: Despesas Essenciais | B31: Moradia | C31: ='Orçamento Familiar'!C31 -> Aluguel | E31: ='Orçamento Familiar'!J31 -> 0 | F31: =P31 -> 0 | G31: =E31-F31 -> 0 | P31: =SUM(I31:O31) -> 0
C32: ='Orçamento Familiar'!C32 -> Energia Elétrica | E32: ='Orçamento Familiar'!J32 -> 0 | F32: =P32 -> 0 | G32: =E32-F32 -> 0 | P32: =SUM(I32:O32) -> 0
C33: ='Orçamento Familiar'!C33 -> Água e Esgoto | E33: ='Orçamento Familiar'!J33 -> 0 | F33: =P33 -> 0 | G33: =E33-F33 -> 0 | P33: =SUM(I33:O33) -> 0
C34: ='Orçamento Familiar'!C34 -> Gás | E34: ='Orçamento Familiar'!J34 -> 0 | F34: =P34 -> 0 | G34: =E34-F34 -> 0 | P34: =SUM(I34:O34) -> 0
C35: ='Orçamento Familiar'!C35 -> Internet e Celular | E35: ='Orçamento Familiar'!J35 -> 184.7 | F35: =P35 -> 0 | G35: =E35-F35 -> 184.7 | P35: =SUM(I35:O35) -> 0
C36: ='Orçamento Familiar'!C36 -> Manutenção | E36: ='Orçamento Familiar'!J36 -> 50 | F36: =P36 -> 0 | G36: =E36-F36 -> 50 | P36: =SUM(I36:O36) -> 0
C37: ='Orçamento Familiar'!C37 -> 0 | E37: ='Orçamento Familiar'!J37 -> 0 | F37: =P37 -> 0 | G37: =E37-F37 -> 0 | P37: =SUM(I37:O37) -> 0
C38: ='Orçamento Familiar'!C38 -> 0 | E38: ='Orçamento Familiar'!J38 -> 0 | F38: =P38 -> 0 | G38: =E38-F38 -> 0 | P38: =SUM(I38:O38) -> 0
C39: ='Orçamento Familiar'!C39 -> 0 | E39: ='Orçamento Familiar'!J39 -> 0 | F39: =P39 -> 0 | G39: =E39-F39 -> 0 | P39: =SUM(I39:O39) -> 0
B40: Alimentação | C40: ='Orçamento Familiar'!C40 -> Supermercado | E40: ='Orçamento Familiar'!J40 -> 3100 | F40: =P40 -> 0 | G40: =E40-F40 -> 3100 | P40: =SUM(I40:O40) -> 0
C41: ='Orçamento Familiar'!C41 -> 0 | E41: ='Orçamento Familiar'!J41 -> 0 | F41: =P41 -> 0 | G41: =E41-F41 -> 0 | P41: =SUM(I41:O41) -> 0
C42: ='Orçamento Familiar'!C42 -> 0 | E42: ='Orçamento Familiar'!J42 -> 0 | F42: =P42 -> 0 | G42: =E42-F42 -> 0 | P42: =SUM(I42:O42) -> 0
C43: ='Orçamento Familiar'!C43 -> 0 | E43: ='Orçamento Familiar'!J43 -> 0 | F43: =P43 -> 0 | G43: =E43-F43 -> 0 | P43: =SUM(I43:O43) -> 0
C44: ='Orçamento Familiar'!C44 -> 0 | E44: ='Orçamento Familiar'!J44 -> 0 | F44: =P44 -> 0 | G44: =E44-F44 -> 0 | P44: =SUM(I44:O44) -> 0
C45: ='Orçamento Familiar'!C45 -> 0 | E45: ='Orçamento Familiar'!J45 -> 0 | F45: =P45 -> 0 | G45: =E45-F45 -> 0 | P45: =SUM(I45:O45) -> 0
B46: Transporte | C46: ='Orçamento Familiar'!C46 -> Combustível | E46: ='Orçamento Familiar'!J46 -> 400 | F46: =P46 -> 0 | G46: =E46-F46 -> 400 | P46: =SUM(I46:O46) -> 0
C47: ='Orçamento Familiar'!C47 -> Manutenção | E47: ='Orçamento Familiar'!J47 -> 555 | F47: =P47 -> 430.9 | G47: =E47-F47 -> 124.1 | N47: 430.9 | P47: =SUM(I47:O47) -> 430.9 | Q47: 430,90 =6/6
C48: ='Orçamento Familiar'!C48 -> Multas | E48: ='Orçamento Familiar'!J48 -> 0 | F48: =P48 -> 0 | G48: =E48-F48 -> 0 | P48: =SUM(I48:O48) -> 0
C49: ='Orçamento Familiar'!C49 -> Seguro | E49: ='Orçamento Familiar'!J49 -> 0 | F49: =P49 -> 0 | G49: =E49-F49 -> 0 | P49: =SUM(I49:O49) -> 0
C50: ='Orçamento Familiar'!C50 -> Lavagem | E50: ='Orçamento Familiar'!J50 -> 0 | F50: =P50 -> 0 | G50: =E50-F50 -> 0 | P50: =SUM(I50:O50) -> 0
C51: ='Orçamento Familiar'!C51 -> Estacionamento | E51: ='Orçamento Familiar'!J51 -> 0 | F51: =P51 -> 0 | G51: =E51-F51 -> 0 | P51: =SUM(I51:O51) -> 0
C52: ='Orçamento Familiar'!C52 -> Taxi / Uber | E52: ='Orçamento Familiar'!J52 -> 0 | F52: =P52 -> 0 | G52: =E52-F52 -> 0 | P52: =SUM(I52:O52) -> 0
C53: ='Orçamento Familiar'!C53 -> 0 | E53: ='Orçamento Familiar'!J53 -> 0 | F53: =P53 -> 0 | G53: =E53-F53 -> 0 | P53: =SUM(I53:O53) -> 0
C54: ='Orçamento Familiar'!C54 -> 0 | E54: ='Orçamento Familiar'!J54 -> 0 | F54: =P54 -> 0 | G54: =E54-F54 -> 0 | P54: =SUM(I54:O54) -> 0
B55: Saúde | C55: ='Orçamento Familiar'!C55 -> Medicamentos | E55: ='Orçamento Familiar'!J55 -> 80 | F55: =P55 -> 0 | G55: =E55-F55 -> 80 | P55: =SUM(I55:O55) -> 0
C56: ='Orçamento Familiar'!C56 -> Médicos / Exames | E56: ='Orçamento Familiar'!J56 -> 0 | F56: =P56 -> 0 | G56: =E56-F56 -> 0 | P56: =SUM(I56:O56) -> 0
C57: ='Orçamento Familiar'!C57 -> Dentista | E57: ='Orçamento Familiar'!J57 -> 0 | F57: =P57 -> 0 | G57: =E57-F57 -> 0 | P57: =SUM(I57:O57) -> 0
C58: ='Orçamento Familiar'!C58 -> 0 | E58: ='Orçamento Familiar'!J58 -> 0 | F58: =P58 -> 0 | G58: =E58-F58 -> 0 | P58: =SUM(I58:O58) -> 0
C59: ='Orçamento Familiar'!C59 -> 0 | E59: ='Orçamento Familiar'!J59 -> 0 | F59: =P59 -> 0 | G59: =E59-F59 -> 0 | P59: =SUM(I59:O59) -> 0
B60: Impostos | C60: ='Orçamento Familiar'!C60 -> IPVA | E60: ='Orçamento Familiar'!J60 -> 0 | F60: =P60 -> 0 | G60: =E60-F60 -> 0 | P60: =SUM(I60:O60) -> 0
C61: ='Orçamento Familiar'!C61 -> Licenciamento | E61: ='Orçamento Familiar'!J61 -> 0 | F61: =P61 -> 0 | G61: =E61-F61 -> 0 | P61: =SUM(I61:O61) -> 0
C62: ='Orçamento Familiar'!C62 -> Imposto de Renda | E62: ='Orçamento Familiar'!J62 -> 0 | F62: =P62 -> 0 | G62: =E62-F62 -> 0 | P62: =SUM(I62:O62) -> 0
C63: ='Orçamento Familiar'!C63 -> INSS | E63: ='Orçamento Familiar'!J63 -> 0 | F63: =P63 -> 0 | G63: =E63-F63 -> 0 | P63: =SUM(I63:O63) -> 0
C64: ='Orçamento Familiar'!C64 -> 0 | E64: ='Orçamento Familiar'!J64 -> 0 | F64: =P64 -> 0 | G64: =E64-F64 -> 0 | P64: =SUM(I64:O64) -> 0
C65: ='Orçamento Familiar'!C65 -> 0 | E65: ='Orçamento Familiar'!J65 -> 0 | F65: =P65 -> 0 | G65: =E65-F65 -> 0 | P65: =SUM(I65:O65) -> 0
B66: Educação | C66: ='Orçamento Familiar'!C66 -> Especialização | E66: ='Orçamento Familiar'!J66 -> 0 | F66: =P66 -> 0 | G66: =E66-F66 -> 0 | P66: =SUM(I66:O66) -> 0
C67: ='Orçamento Familiar'!C67 -> Cursos | E67: ='Orçamento Familiar'!J67 -> 150 | F67: =P67 -> 146.83 | G67: =E67-F67 -> 3.17 | N67: 146.83 | P67: =SUM(I67:O67) -> 146.83 | Q67: Faculdade Con 4/6=146,83
C68: ='Orçamento Familiar'!C68 -> Mentoria Financeira | E68: ='Orçamento Familiar'!J68 -> 225 | F68: =P68 -> 0 | G68: =E68-F68 -> 225 | P68: =SUM(I68:O68) -> 0
C69: ='Orçamento Familiar'!C69 -> 0 | E69: ='Orçamento Familiar'!J69 -> 0 | F69: =P69 -> 0 | G69: =E69-F69 -> 0 | P69: =SUM(I69:O69) -> 0
C70: ='Orçamento Familiar'!C70 -> 0 | E70: ='Orçamento Familiar'!J70 -> 0 | F70: =P70 -> 0 | G70: =E70-F70 -> 0 | P70: =SUM(I70:O70) -> 0
B71: Filhos | C71: ='Orçamento Familiar'!C71 -> Piano Laura | E71: ='Orçamento Familiar'!J71 -> 0 | F71: =P71 -> 0 | G71: =E71-F71 -> 0 | P71: =SUM(I71:O71) -> 0
C72: ='Orçamento Familiar'!C72 -> Material Escolar | E72: ='Orçamento Familiar'!J72 -> 0 | F72: =P72 -> 0 | G72: =E72-F72 -> 0 | P72: =SUM(I72:O72) -> 0
C73: ='Orçamento Familiar'!C73 -> Mesadas | E73: ='Orçamento Familiar'!J73 -> 190 | F73: =P73 -> 60.82 | G73: =E73-F73 -> 129.18 | N73: 60.82 | P73: =SUM(I73:O73) -> 60.82 | Q73: 60,82=10/11
C74: ='Orçamento Familiar'!C74 -> Violão | E74: ='Orçamento Familiar'!J74 -> 0 | F74: =P74 -> 0 | G74: =E74-F74 -> 0 | P74: =SUM(I74:O74) -> 0
C75: ='Orçamento Familiar'!C75 -> Médicos / Exames | E75: ='Orçamento Familiar'!J75 -> 0 | F75: =P75 -> 0 | G75: =E75-F75 -> 0 | P75: =SUM(I75:O75) -> 0
C76: ='Orçamento Familiar'!C76 -> Cursos | E76: ='Orçamento Familiar'!J76 -> 0 | F76: =P76 -> 0 | G76: =E76-F76 -> 0 | P76: =SUM(I76:O76) -> 0
C77: ='Orçamento Familiar'!C77 -> Retiro Carnaval 2026/2027 | E77: ='Orçamento Familiar'!J77 -> 240 | F77: =P77 -> 0 | G77: =E77-F77 -> 240 | P77: =SUM(I77:O77) -> 0
C78: ='Orçamento Familiar'!C78 -> Acampadentro | E78: ='Orçamento Familiar'!J78 -> 0 | F78: =P78 -> 0 | G78: =E78-F78 -> 0 | P78: =SUM(I78:O78) -> 0
C79: ='Orçamento Familiar'!C79 -> 0 | E79: ='Orçamento Familiar'!J79 -> 0 | F79: =P79 -> 0 | G79: =E79-F79 -> 0 | P79: =SUM(I79:O79) -> 0
B80: Pet | C80: ='Orçamento Familiar'!C80 -> Ração | E80: ='Orçamento Familiar'!J80 -> 50 | F80: =P80 -> 0 | G80: =E80-F80 -> 50 | P80: =SUM(I80:O80) -> 0
C81: ='Orçamento Familiar'!C81 -> Vacinas | E81: ='Orçamento Familiar'!J81 -> 0 | F81: =P81 -> 0 | G81: =E81-F81 -> 0 | P81: =SUM(I81:O81) -> 0
C82: ='Orçamento Familiar'!C82 -> Veterinário | E82: ='Orçamento Familiar'!J82 -> 0 | F82: =P82 -> 0 | G82: =E82-F82 -> 0 | P82: =SUM(I82:O82) -> 0
C83: ='Orçamento Familiar'!C83 -> 0 | E83: ='Orçamento Familiar'!J83 -> 0 | F83: =P83 -> 0 | G83: =E83-F83 -> 0 | P83: =SUM(I83:O83) -> 0
C84: ='Orçamento Familiar'!C84 -> 0 | E84: ='Orçamento Familiar'!J84 -> 0 | F84: =P84 -> 0 | G84: =E84-F84 -> 0 | P84: =SUM(I84:O84) -> 0
B85: Total Despesas Essenciais | E85: =SUM(E31:E84) -> 5224.7 | F85: =SUM(F31:F84) -> 638.55 | G85: =SUM(G31:G84) -> 4586.15 | I85: =SUM(I31:I84) -> 0 | J85: =SUM(J31:J84) -> 0 | K85: =SUM(K31:K84) -> 0 | L85: =SUM(L31:L84) -> 0 | M85: =SUM(M31:M84) -> 0 | N85: =SUM(N31:N84) -> 638.55 | O85: =SUM(O31:O84) -> 0 | P85: =SUM(P31:P84) -> 638.55
B86: % sobre Receita | C86: ='Orçamento Familiar'!C166 -> 0 | E86: =E85/E16 -> 0.6919216 | F86: =F85/F16 -> #DIV/0! | I86: =I85/I16 -> #DIV/0! | J86: =J85/J16 -> #DIV/0! | K86: =K85/K16 -> #DIV/0! | L86: =L85/L16 -> #DIV/0! | M86: =M85/M16 -> #DIV/0! | N86: =N85/N16 -> #DIV/0! | O86: =O85/O16 -> #DIV/0! | P86: =P85/P16 -> #DIV/0!
A87: Profissional e Trabalho | B87: Ministério | C87: ='Orçamento Familiar'!C87 -> Materiais (livros) | E87: ='Orçamento Familiar'!J87 -> 30 | F87: =P87 -> 0 | G87: =E87-F87 -> 30 | P87: =SUM(I87:O87) -> 0
C88: ='Orçamento Familiar'!C88 -> 0 | E88: ='Orçamento Familiar'!J88 -> 0 | F88: =P88 -> 0 | G88: =E88-F88 -> 0 | P88: =SUM(I88:O88) -> 0
C89: ='Orçamento Familiar'!C89 -> 0 | E89: ='Orçamento Familiar'!J89 -> 0 | F89: =P89 -> 0 | G89: =E89-F89 -> 0 | P89: =SUM(I89:O89) -> 0
C90: ='Orçamento Familiar'!C90 -> 0 | E90: ='Orçamento Familiar'!J90 -> 0 | F90: =P90 -> 0 | G90: =E90-F90 -> 0 | P90: =SUM(I90:O90) -> 0
C91: ='Orçamento Familiar'!C91 -> 0 | E91: ='Orçamento Familiar'!J91 -> 0 | F91: =P91 -> 0 | G91: =E91-F91 -> 0 | P91: =SUM(I91:O91) -> 0
C92: ='Orçamento Familiar'!C92 -> 0 | E92: ='Orçamento Familiar'!J92 -> 0 | F92: =P92 -> 0 | G92: =E92-F92 -> 0 | P92: =SUM(I92:O92) -> 0
B93: Autônomo | C93: ='Orçamento Familiar'!C93 -> Ferramentas de trabalho | E93: ='Orçamento Familiar'!J93 -> 150 | F93: =P93 -> 0 | G93: =E93-F93 -> 150 | P93: =SUM(I93:O93) -> 0
C94: ='Orçamento Familiar'!C94 -> Colaboradores | E94: ='Orçamento Familiar'!J94 -> 0 | F94: =P94 -> 0 | G94: =E94-F94 -> 0 | P94: =SUM(I94:O94) -> 0
C95: ='Orçamento Familiar'!C95 -> 0 | E95: ='Orçamento Familiar'!J95 -> 0 | F95: =P95 -> 0 | G95: =E95-F95 -> 0 | P95: =SUM(I95:O95) -> 0
C96: ='Orçamento Familiar'!C96 -> 0 | E96: ='Orçamento Familiar'!J96 -> 0 | F96: =P96 -> 0 | G96: =E96-F96 -> 0 | P96: =SUM(I96:O96) -> 0
C97: ='Orçamento Familiar'!C97 -> 0 | E97: ='Orçamento Familiar'!J97 -> 0 | F97: =P97 -> 0 | G97: =E97-F97 -> 0 | P97: =SUM(I97:O97) -> 0
C98: ='Orçamento Familiar'!C98 -> 0 | E98: ='Orçamento Familiar'!J98 -> 0 | F98: =P98 -> 0 | G98: =E98-F98 -> 0 | P98: =SUM(I98:O98) -> 0
B99: Total Profissional e Trabalho | E99: =SUM(E87:E98) -> 180 | F99: =SUM(F87:F98) -> 0 | G99: =SUM(G87:G98) -> 180 | I99: =SUM(I87:I98) -> 0 | J99: =SUM(J87:J98) -> 0 | K99: =SUM(K87:K98) -> 0 | L99: =SUM(L87:L98) -> 0 | M99: =SUM(M87:M98) -> 0 | N99: =SUM(N87:N98) -> 0 | O99: =SUM(O87:O98) -> 0 | P99: =SUM(P87:P98) -> 0
B100: % sobre Receita | E100: =E99/E16 -> 0.023837902 | F100: =F99/F16 -> #DIV/0! | I100: =I99/I16 -> #DIV/0! | J100: =J99/J16 -> #DIV/0! | K100: =K99/K16 -> #DIV/0! | L100: =L99/L16 -> #DIV/0! | M100: =M99/M16 -> #DIV/0! | N100: =N99/N16 -> #DIV/0! | O100: =O99/O16 -> #DIV/0! | P100: =P99/P16 -> #DIV/0!
A101: Contribuição | B101: Ofertas | C101: ='Orçamento Familiar'!C101 -> Dízimo | E101: ='Orçamento Familiar'!J101 -> 850 | F101: =P101 -> 0 | G101: =E101-F101 -> 850 | P101: =SUM(I101:O101) -> 0
C102: ='Orçamento Familiar'!C102 -> Sacrificial | E102: ='Orçamento Familiar'!J102 -> 0 | F102: =P102 -> 0 | G102: =E102-F102 -> 0 | P102: =SUM(I102:O102) -> 0
C103: ='Orçamento Familiar'!C103 -> Doações | E103: ='Orçamento Familiar'!J103 -> 0 | F103: =P103 -> 0 | G103: =E103-F103 -> 0 | P103: =SUM(I103:O103) -> 0
C104: ='Orçamento Familiar'!C104 -> 0 | E104: ='Orçamento Familiar'!J104 -> 0 | F104: =P104 -> 0 | G104: =E104-F104 -> 0 | P104: =SUM(I104:O104) -> 0
B105: Total Contribuição | E105: =SUM(E101:E104) -> 850 | F105: =SUM(F101:F104) -> 0 | G105: =SUM(G101:G104) -> 850 | I105: =SUM(I101:I104) -> 0 | J105: =SUM(J101:J104) -> 0 | K105: =SUM(K101:K104) -> 0 | L105: =SUM(L101:L104) -> 0 | M105: =SUM(M101:M104) -> 0 | N105: =SUM(N101:N104) -> 0 | O105: =SUM(O101:O104) -> 0 | P105: =SUM(P101:P104) -> 0
...

Sheet Jul
A2: Fluxo de Caixa Familiar
A5: Categoria | C5: Descrição | D5: Percentual | E5: =I5 -> Julho | I5: Julho
E6: Orçado | F6: Realizado | G6: Variação | I6: Semana 1 | J6: Semana 2 | K6: Semana 3 | L6: Semana 4 | M6: Semana 5 | N6: =Jan!N6 -> Cartão Nubank | O6: =Jan!O6 -> Cartão C & A | P6: Total
A7: Receitas | C7: ='Orçamento Familiar'!C7 -> Prebenda | E7: ='Orçamento Familiar'!K7 -> 7216 | F7: =P7 -> 0 | G7: =F7-E7 -> -7216 | P7: =SUM(I7:O7) -> 0
C8: ='Orçamento Familiar'!C8 -> Inglês | E8: ='Orçamento Familiar'!K8 -> 335 | F8: =P8 -> 0 | G8: =F8-E8 -> -335 | P8: =SUM(I8:O8) -> 0
C9: ='Orçamento Familiar'!C9 -> 13º Salário | E9: ='Orçamento Familiar'!K9 -> 0 | F9: =P9 -> 0 | G9: =F9-E9 -> 0 | P9: =SUM(I9:O9) -> 0
C10: ='Orçamento Familiar'!C10 -> Renda Extra | E10: ='Orçamento Familiar'!K10 -> 0 | F10: =P10 -> 0 | G10: =F10-E10 -> 0 | P10: =SUM(I10:O10) -> 0
C11: ='Orçamento Familiar'!C11 -> 0 | E11: ='Orçamento Familiar'!K11 -> 0 | F11: =P11 -> 0 | G11: =F11-E11 -> 0 | P11: =SUM(I11:O11) -> 0
C12: ='Orçamento Familiar'!C12 -> 0 | E12: ='Orçamento Familiar'!K12 -> 0 | F12: =P12 -> 0 | G12: =F12-E12 -> 0 | P12: =SUM(I12:O12) -> 0
C13: ='Orçamento Familiar'!C13 -> 0 | E13: ='Orçamento Familiar'!K13 -> 0 | F13: =P13 -> 0 | G13: =F13-E13 -> 0 | P13: =SUM(I13:O13) -> 0
C14: ='Orçamento Familiar'!C14 -> 0 | E14: ='Orçamento Familiar'!K14 -> 0 | F14: =P14 -> 0 | G14: =F14-E14 -> 0 | P14: =SUM(I14:O14) -> 0
C15: ='Orçamento Familiar'!C15 -> 0 | E15: ='Orçamento Familiar'!K15 -> 0 | F15: =P15 -> 0 | G15: =F15-E15 -> 0 | P15: =SUM(I15:O15) -> 0
C16: Total | E16: =SUM(E7:E15) -> 7551 | F16: =SUM(F7:F15) -> 0 | G16: =SUM(G7:G15) -> -7551 | I16: =SUM(I7:I15) -> 0 | J16: =SUM(J7:J15) -> 0 | K16: =SUM(K7:K15) -> 0 | L16: =SUM(L7:L15) -> 0 | M16: =SUM(M7:M15) -> 0 | N16: =SUM(N7:N15) -> 0 | O16: =SUM(O7:O15) -> 0 | P16: =SUM(P7:P15) -> 0
A18: Investimentos Insira aqui o montante mensal que você destinará aos seus investimentos | C18: Descrição | D18: Percentual | E18: Orçado | F18: Realizado | G18: Variação | I18: =I6 -> Semana 1 | J18: =J6 -> Semana 2 | K18: =K6 -> Semana 3 | L18: =L6 -> Semana 4 | M18: =M6 -> Semana 5 | P18: =P6 -> Total
C19: ='Orçamento Familiar'!C19 -> Reserva de Emergência (CP) R$ 9.151 | E19: ='Orçamento Familiar'!K19 -> 0 | F19: =P19 -> 0 | G19: =F19-E19 -> 0 | P19: =SUM(I19:O19) -> 0
C20: ='Orçamento Familiar'!C20 -> Projeto 1 | E20: ='Orçamento Familiar'!K20 -> 0 | F20: =P20 -> 0 | G20: =F20-E20 -> 0 | P20: =SUM(I20:O20) -> 0
C21: ='Orçamento Familiar'!C21 -> Projeto 2 | E21: ='Orçamento Familiar'!K21 -> 0 | F21: =P21 -> 0 | G21: =F21-E21 -> 0 | P21: =SUM(I21:O21) -> 0
C22: ='Orçamento Familiar'!C22 -> Projeto 3 | E22: ='Orçamento Familiar'!K22 -> 0 | F22: =P22 -> 0 | G22: =F22-E22 -> 0 | P22: =SUM(I22:O22) -> 0
C23: ='Orçamento Familiar'!C23 -> Projeto 4 | E23: ='Orçamento Familiar'!K23 -> 0 | F23: =P23 -> 0 | G23: =F23-E23 -> 0 | P23: =SUM(I23:O23) -> 0
C24: ='Orçamento Familiar'!C24 -> Projeto 5 | E24: ='Orçamento Familiar'!K24 -> 0 | F24: =P24 -> 0 | G24: =F24-E24 -> 0 | P24: =SUM(I24:O24) -> 0
C25: ='Orçamento Familiar'!C25 -> Projeto 6 | E25: ='Orçamento Familiar'!K25 -> 0 | F25: =P25 -> 0 | G25: =F25-E25 -> 0 | P25: =SUM(I25:O25) -> 0
C26: ='Orçamento Familiar'!C26 -> Independência Financeira | E26: ='Orçamento Familiar'!K26 -> 0 | F26: =P26 -> 0 | G26: =F26-E26 -> 0 | P26: =SUM(I26:O26) -> 0
C27: Total Investimentos | D27: =SUM(D19:D26) -> 0 | E27: =SUM(E19:E26) -> 0 | F27: =SUM(F19:F26) -> 0 | G27: =SUM(G19:G26) -> 0 | I27: =SUM(I19:I26) -> 0 | J27: =SUM(J19:J26) -> 0 | K27: =SUM(K19:K26) -> 0 | L27: =SUM(L19:L26) -> 0 | M27: =SUM(M19:M26) -> 0 | N27: =SUM(N19:N26) -> 0 | O27: =SUM(O19:O26) -> 0 | P27: =SUM(P19:P26) -> 0
C28: % sobre Receita | E28: =E27/E16 -> 0 | F28: =F27/F16 -> #DIV/0! | I28: =I27/I16 -> #DIV/0! | J28: =J27/J16 -> #DIV/0! | K28: =K27/K16 -> #DIV/0! | L28: =L27/L16 -> #DIV/0! | M28: =M27/M16 -> #DIV/0! | N28: =N27/N16 -> #DIV/0! | O28: =O27/O16 -> #DIV/0! | P28: =P27/P16 -> #DIV/0!
A30: Categoria | C30: Descrição | D30: Percentual | E30: Orçado | F30: Realizado | G30: Variação | I30: =I18 -> Semana 1 | J30: =J18 -> Semana 2 | K30: =K18 -> Semana 3 | L30: =L18 -> Semana 4 | M30: =M18 -> Semana 5 | N30: =N6 -> Cartão Nubank | O30: =O6 -> Cartão C & A | P30: =P18 -> Total
A31: Despesas Essenciais | B31: Moradia | C31: ='Orçamento Familiar'!C31 -> Aluguel | E31: ='Orçamento Familiar'!K31 -> 0 | F31: =P31 -> 0 | G31: =E31-F31 -> 0 | P31: =SUM(I31:O31) -> 0
C32: ='Orçamento Familiar'!C32 -> Energia Elétrica | E32: ='Orçamento Familiar'!K32 -> 0 | F32: =P32 -> 0 | G32: =E32-F32 -> 0 | P32: =SUM(I32:O32) -> 0
C33: ='Orçamento Familiar'!C33 -> Água e Esgoto | E33: ='Orçamento Familiar'!K33 -> 0 | F33: =P33 -> 0 | G33: =E33-F33 -> 0 | P33: =SUM(I33:O33) -> 0
C34: ='Orçamento Familiar'!C34 -> Gás | E34: ='Orçamento Familiar'!K34 -> 0 | F34: =P34 -> 0 | G34: =E34-F34 -> 0 | P34: =SUM(I34:O34) -> 0
C35: ='Orçamento Familiar'!C35 -> Internet e Celular | E35: ='Orçamento Familiar'!K35 -> 184.7 | F35: =P35 -> 0 | G35: =E35-F35 -> 184.7 | P35: =SUM(I35:O35) -> 0
C36: ='Orçamento Familiar'!C36 -> Manutenção | E36: ='Orçamento Familiar'!K36 -> 50 | F36: =P36 -> 0 | G36: =E36-F36 -> 50 | P36: =SUM(I36:O36) -> 0
C37: ='Orçamento Familiar'!C37 -> 0 | E37: ='Orçamento Familiar'!K37 -> 0 | F37: =P37 -> 0 | G37: =E37-F37 -> 0 | P37: =SUM(I37:O37) -> 0
C38: ='Orçamento Familiar'!C38 -> 0 | E38: ='Orçamento Familiar'!K38 -> 0 | F38: =P38 -> 0 | G38: =E38-F38 -> 0 | P38: =SUM(I38:O38) -> 0
C39: ='Orçamento Familiar'!C39 -> 0 | E39: ='Orçamento Familiar'!K39 -> 0 | F39: =P39 -> 0 | G39: =E39-F39 -> 0 | P39: =SUM(I39:O39) -> 0
B40: Alimentação | C40: ='Orçamento Familiar'!C40 -> Supermercado | E40: ='Orçamento Familiar'!K40 -> 3100 | F40: =P40 -> 0 | G40: =E40-F40 -> 3100 | P40: =SUM(I40:O40) -> 0
C41: ='Orçamento Familiar'!C41 -> 0 | E41: ='Orçamento Familiar'!K41 -> 0 | F41: =P41 -> 0 | G41: =E41-F41 -> 0 | P41: =SUM(I41:O41) -> 0
C42: ='Orçamento Familiar'!C42 -> 0 | E42: ='Orçamento Familiar'!K42 -> 0 | F42: =P42 -> 0 | G42: =E42-F42 -> 0 | P42: =SUM(I42:O42) -> 0
C43: ='Orçamento Familiar'!C43 -> 0 | E43: ='Orçamento Familiar'!K43 -> 0 | F43: =P43 -> 0 | G43: =E43-F43 -> 0 | P43: =SUM(I43:O43) -> 0
C44: ='Orçamento Familiar'!C44 -> 0 | E44: ='Orçamento Familiar'!K44 -> 0 | F44: =P44 -> 0 | G44: =E44-F44 -> 0 | P44: =SUM(I44:O44) -> 0
C45: ='Orçamento Familiar'!C45 -> 0 | E45: ='Orçamento Familiar'!K45 -> 0 | F45: =P45 -> 0 | G45: =E45-F45 -> 0 | P45: =SUM(I45:O45) -> 0
B46: Transporte | C46: ='Orçamento Familiar'!C46 -> Combustível | E46: ='Orçamento Familiar'!K46 -> 400 | F46: =P46 -> 0 | G46: =E46-F46 -> 400 | P46: =SUM(I46:O46) -> 0
C47: ='Orçamento Familiar'!C47 -> Manutenção | E47: ='Orçamento Familiar'!K47 -> 0 | F47: =P47 -> 0 | G47: =E47-F47 -> 0 | P47: =SUM(I47:O47) -> 0
C48: ='Orçamento Familiar'!C48 -> Multas | E48: ='Orçamento Familiar'!K48 -> 0 | F48: =P48 -> 0 | G48: =E48-F48 -> 0 | P48: =SUM(I48:O48) -> 0
C49: ='Orçamento Familiar'!C49 -> Seguro | E49: ='Orçamento Familiar'!K49 -> 0 | F49: =P49 -> 0 | G49: =E49-F49 -> 0 | P49: =SUM(I49:O49) -> 0
C50: ='Orçamento Familiar'!C50 -> Lavagem | E50: ='Orçamento Familiar'!K50 -> 0 | F50: =P50 -> 0 | G50: =E50-F50 -> 0 | P50: =SUM(I50:O50) -> 0
C51: ='Orçamento Familiar'!C51 -> Estacionamento | E51: ='Orçamento Familiar'!K51 -> 0 | F51: =P51 -> 0 | G51: =E51-F51 -> 0 | P51: =SUM(I51:O51) -> 0
C52: ='Orçamento Familiar'!C52 -> Taxi / Uber | E52: ='Orçamento Familiar'!K52 -> 0 | F52: =P52 -> 0 | G52: =E52-F52 -> 0 | P52: =SUM(I52:O52) -> 0
C53: ='Orçamento Familiar'!C53 -> 0 | E53: ='Orçamento Familiar'!K53 -> 0 | F53: =P53 -> 0 | G53: =E53-F53 -> 0 | P53: =SUM(I53:O53) -> 0
C54: ='Orçamento Familiar'!C54 -> 0 | E54: ='Orçamento Familiar'!K54 -> 0 | F54: =P54 -> 0 | G54: =E54-F54 -> 0 | P54: =SUM(I54:O54) -> 0
B55: Saúde | C55: ='Orçamento Familiar'!C55 -> Medicamentos | E55: ='Orçamento Familiar'!K55 -> 80 | F55: =P55 -> 0 | G55: =E55-F55 -> 80 | P55: =SUM(I55:O55) -> 0
C56: ='Orçamento Familiar'!C56 -> Médicos / Exames | E56: ='Orçamento Familiar'!K56 -> 0 | F56: =P56 -> 0 | G56: =E56-F56 -> 0 | P56: =SUM(I56:O56) -> 0
C57: ='Orçamento Familiar'!C57 -> Dentista | E57: ='Orçamento Familiar'!K57 -> 0 | F57: =P57 -> 0 | G57: =E57-F57 -> 0 | P57: =SUM(I57:O57) -> 0
C58: ='Orçamento Familiar'!C58 -> 0 | E58: ='Orçamento Familiar'!K58 -> 0 | F58: =P58 -> 0 | G58: =E58-F58 -> 0 | P58: =SUM(I58:O58) -> 0
C59: ='Orçamento Familiar'!C59 -> 0 | E59: ='Orçamento Familiar'!K59 -> 0 | F59: =P59 -> 0 | G59: =E59-F59 -> 0 | P59: =SUM(I59:O59) -> 0
B60: Impostos | C60: ='Orçamento Familiar'!C60 -> IPVA | E60: ='Orçamento Familiar'!K60 -> 0 | F60: =P60 -> 0 | G60: =E60-F60 -> 0 | P60: =SUM(I60:O60) -> 0
C61: ='Orçamento Familiar'!C61 -> Licenciamento | E61: ='Orçamento Familiar'!K61 -> 0 | F61: =P61 -> 0 | G61: =E61-F61 -> 0 | P61: =SUM(I61:O61) -> 0
C62: ='Orçamento Familiar'!C62 -> Imposto de Renda | E62: ='Orçamento Familiar'!K62 -> 0 | F62: =P62 -> 0 | G62: =E62-F62 -> 0 | P62: =SUM(I62:O62) -> 0
C63: ='Orçamento Familiar'!C63 -> INSS | E63: ='Orçamento Familiar'!K63 -> 0 | F63: =P63 -> 0 | G63: =E63-F63 -> 0 | P63: =SUM(I63:O63) -> 0
C64: ='Orçamento Familiar'!C64 -> 0 | E64: ='Orçamento Familiar'!K64 -> 0 | F64: =P64 -> 0 | G64: =E64-F64 -> 0 | P64: =SUM(I64:O64) -> 0
C65: ='Orçamento Familiar'!C65 -> 0 | E65: ='Orçamento Familiar'!K65 -> 0 | F65: =P65 -> 0 | G65: =E65-F65 -> 0 | P65: =SUM(I65:O65) -> 0
B66: Educação | C66: ='Orçamento Familiar'!C66 -> Especialização | E66: ='Orçamento Familiar'!K66 -> 0 | F66: =P66 -> 0 | G66: =E66-F66 -> 0 | P66: =SUM(I66:O66) -> 0
C67: ='Orçamento Familiar'!C67 -> Cursos | E67: ='Orçamento Familiar'!K67 -> 150 | F67: =P67 -> 146.83 | G67: =E67-F67 -> 3.17 | N67: 146.83 | P67: =SUM(I67:O67) -> 146.83 | Q67: Faculdade Con 5/6=146,83
C68: ='Orçamento Familiar'!C68 -> Mentoria Financeira | E68: ='Orçamento Familiar'!K68 -> 225 | F68: =P68 -> 0 | G68: =E68-F68 -> 225 | P68: =SUM(I68:O68) -> 0
C69: ='Orçamento Familiar'!C69 -> 0 | E69: ='Orçamento Familiar'!K69 -> 0 | F69: =P69 -> 0 | G69: =E69-F69 -> 0 | P69: =SUM(I69:O69) -> 0
C70: ='Orçamento Familiar'!C70 -> 0 | E70: ='Orçamento Familiar'!K70 -> 0 | F70: =P70 -> 0 | G70: =E70-F70 -> 0 | P70: =SUM(I70:O70) -> 0
B71: Filhos | C71: ='Orçamento Familiar'!C71 -> Piano Laura | E71: ='Orçamento Familiar'!K71 -> 0 | F71: =P71 -> 0 | G71: =E71-F71 -> 0 | P71: =SUM(I71:O71) -> 0
C72: ='Orçamento Familiar'!C72 -> Material Escolar | E72: ='Orçamento Familiar'!K72 -> 0 | F72: =P72 -> 0 | G72: =E72-F72 -> 0 | P72: =SUM(I72:O72) -> 0
C73: ='Orçamento Familiar'!C73 -> Mesadas | E73: ='Orçamento Familiar'!K73 -> 190 | F73: =P73 -> 60.82 | G73: =E73-F73 -> 129.18 | N73: 60.82 | P73: =SUM(I73:O73) -> 60.82 | Q73: 60,82=11/11
C74: ='Orçamento Familiar'!C74 -> Violão | E74: ='Orçamento Familiar'!K74 -> 0 | F74: =P74 -> 0 | G74: =E74-F74 -> 0 | P74: =SUM(I74:O74) -> 0
C75: ='Orçamento Familiar'!C75 -> Médicos / Exames | E75: ='Orçamento Familiar'!K75 -> 0 | F75: =P75 -> 0 | G75: =E75-F75 -> 0 | P75: =SUM(I75:O75) -> 0
C76: ='Orçamento Familiar'!C76 -> Cursos | E76: ='Orçamento Familiar'!K76 -> 0 | F76: =P76 -> 0 | G76: =E76-F76 -> 0 | P76: =SUM(I76:O76) -> 0
C77: ='Orçamento Familiar'!C77 -> Retiro Carnaval 2026/2027 | E77: ='Orçamento Familiar'!K77 -> 240 | F77: =P77 -> 0 | G77: =E77-F77 -> 240 | P77: =SUM(I77:O77) -> 0
C78: ='Orçamento Familiar'!C78 -> Acampadentro | E78: ='Orçamento Familiar'!K78 -> 0 | F78: =P78 -> 0 | G78: =E78-F78 -> 0 | P78: =SUM(I78:O78) -> 0
C79: ='Orçamento Familiar'!C79 -> 0 | E79: ='Orçamento Familiar'!K79 -> 0 | F79: =P79 -> 0 | G79: =E79-F79 -> 0 | P79: =SUM(I79:O79) -> 0
B80: Pet | C80: ='Orçamento Familiar'!C80 -> Ração | E80: ='Orçamento Familiar'!K80 -> 50 | F80: =P80 -> 0 | G80: =E80-F80 -> 50 | P80: =SUM(I80:O80) -> 0
C81: ='Orçamento Familiar'!C81 -> Vacinas | E81: ='Orçamento Familiar'!K81 -> 0 | F81: =P81 -> 0 | G81: =E81-F81 -> 0 | P81: =SUM(I81:O81) -> 0
C82: ='Orçamento Familiar'!C82 -> Veterinário | E82: ='Orçamento Familiar'!K82 -> 0 | F82: =P82 -> 0 | G82: =E82-F82 -> 0 | P82: =SUM(I82:O82) -> 0
C83: ='Orçamento Familiar'!C83 -> 0 | E83: ='Orçamento Familiar'!K83 -> 0 | F83: =P83 -> 0 | G83: =E83-F83 -> 0 | P83: =SUM(I83:O83) -> 0
C84: ='Orçamento Familiar'!C84 -> 0 | E84: ='Orçamento Familiar'!K84 -> 0 | F84: =P84 -> 0 | G84: =E84-F84 -> 0 | P84: =SUM(I84:O84) -> 0
B85: Total Despesas Essenciais | E85: =SUM(E31:E84) -> 4669.7 | F85: =SUM(F31:F84) -> 207.65 | G85: =SUM(G31:G84) -> 4462.05 | I85: =SUM(I31:I84) -> 0 | J85: =SUM(J31:J84) -> 0 | K85: =SUM(K31:K84) -> 0 | L85: =SUM(L31:L84) -> 0 | M85: =SUM(M31:M84) -> 0 | N85: =SUM(N31:N84) -> 207.65 | O85: =SUM(O31:O84) -> 0 | P85: =SUM(P31:P84) -> 207.65
B86: % sobre Receita | C86: ='Orçamento Familiar'!C166 -> 0 | E86: =E85/E16 -> 0.6184214 | F86: =F85/F16 -> #DIV/0! | I86: =I85/I16 -> #DIV/0! | J86: =J85/J16 -> #DIV/0! | K86: =K85/K16 -> #DIV/0! | L86: =L85/L16 -> #DIV/0! | M86: =M85/M16 -> #DIV/0! | N86: =N85/N16 -> #DIV/0! | O86: =O85/O16 -> #DIV/0! | P86: =P85/P16 -> #DIV/0!
A87: Profissional e Trabalho | B87: Ministério | C87: ='Orçamento Familiar'!C87 -> Materiais (livros) | E87: ='Orçamento Familiar'!K87 -> 30 | F87: =P87 -> 0 | G87: =E87-F87 -> 30 | P87: =SUM(I87:O87) -> 0
C88: ='Orçamento Familiar'!C88 -> 0 | E88: ='Orçamento Familiar'!K88 -> 0 | F88: =P88 -> 0 | G88: =E88-F88 -> 0 | P88: =SUM(I88:O88) -> 0
C89: ='Orçamento Familiar'!C89 -> 0 | E89: ='Orçamento Familiar'!K89 -> 0 | F89: =P89 -> 0 | G89: =E89-F89 -> 0 | P89: =SUM(I89:O89) -> 0
C90: ='Orçamento Familiar'!C90 -> 0 | E90: ='Orçamento Familiar'!K90 -> 0 | F90: =P90 -> 0 | G90: =E90-F90 -> 0 | P90: =SUM(I90:O90) -> 0
C91: ='Orçamento Familiar'!C91 -> 0 | E91: ='Orçamento Familiar'!K91 -> 0 | F91: =P91 -> 0 | G91: =E91-F91 -> 0 | P91: =SUM(I91:O91) -> 0
C92: ='Orçamento Familiar'!C92 -> 0 | E92: ='Orçamento Familiar'!K92 -> 0 | F92: =P92 -> 0 | G92: =E92-F92 -> 0 | P92: =SUM(I92:O92) -> 0
B93: Autônomo | C93: ='Orçamento Familiar'!C93 -> Ferramentas de trabalho | E93: ='Orçamento Familiar'!K93 -> 150 | F93: =P93 -> 0 | G93: =E93-F93 -> 150 | P93: =SUM(I93:O93) -> 0
C94: ='Orçamento Familiar'!C94 -> Colaboradores | E94: ='Orçamento Familiar'!K94 -> 0 | F94: =P94 -> 0 | G94: =E94-F94 -> 0 | P94: =SUM(I94:O94) -> 0
C95: ='Orçamento Familiar'!C95 -> 0 | E95: ='Orçamento Familiar'!K95 -> 0 | F95: =P95 -> 0 | G95: =E95-F95 -> 0 | P95: =SUM(I95:O95) -> 0
C96: ='Orçamento Familiar'!C96 -> 0 | E96: ='Orçamento Familiar'!K96 -> 0 | F96: =P96 -> 0 | G96: =E96-F96 -> 0 | P96: =SUM(I96:O96) -> 0
C97: ='Orçamento Familiar'!C97 -> 0 | E97: ='Orçamento Familiar'!K97 -> 0 | F97: =P97 -> 0 | G97: =E97-F97 -> 0 | P97: =SUM(I97:O97) -> 0
C98: ='Orçamento Familiar'!C98 -> 0 | E98: ='Orçamento Familiar'!K98 -> 0 | F98: =P98 -> 0 | G98: =E98-F98 -> 0 | P98: =SUM(I98:O98) -> 0
B99: Total Profissional e Trabalho | E99: =SUM(E87:E98) -> 180 | F99: =SUM(F87:F98) -> 0 | G99: =SUM(G87:G98) -> 180 | I99: =SUM(I87:I98) -> 0 | J99: =SUM(J87:J98) -> 0 | K99: =SUM(K87:K98) -> 0 | L99: =SUM(L87:L98) -> 0 | M99: =SUM(M87:M98) -> 0 | N99: =SUM(N87:N98) -> 0 | O99: =SUM(O87:O98) -> 0 | P99: =SUM(P87:P98) -> 0
B100: % sobre Receita | E100: =E99/E16 -> 0.023837902 | F100: =F99/F16 -> #DIV/0! | I100: =I99/I16 -> #DIV/0! | J100: =J99/J16 -> #DIV/0! | K100: =K99/K16 -> #DIV/0! | L100: =L99/L16 -> #DIV/0! | M100: =M99/M16 -> #DIV/0! | N100: =N99/N16 -> #DIV/0! | O100: =O99/O16 -> #DIV/0! | P100: =P99/P16 -> #DIV/0!
A101: Contribuição | B101: Ofertas | C101: ='Orçamento Familiar'!C101 -> Dízimo | E101: ='Orçamento Familiar'!K101 -> 850 | F101: =P101 -> 0 | G101: =E101-F101 -> 850 | P101: =SUM(I101:O101) -> 0
C102: ='Orçamento Familiar'!C102 -> Sacrificial | E102: ='Orçamento Familiar'!K102 -> 0 | F102: =P102 -> 0 | G102: =E102-F102 -> 0 | P102: =SUM(I102:O102) -> 0
C103: ='Orçamento Familiar'!C103 -> Doações | E103: ='Orçamento Familiar'!K103 -> 0 | F103: =P103 -> 0 | G103: =E103-F103 -> 0 | P103: =SUM(I103:O103) -> 0
C104: ='Orçamento Familiar'!C104 -> 0 | E104: ='Orçamento Familiar'!K104 -> 0 | F104: =P104 -> 0 | G104: =E104-F104 -> 0 | P104: =SUM(I104:O104) -> 0
B105: Total Contribuição | E105: =SUM(E101:E104) -> 850 | F105: =SUM(F101:F104) -> 0 | G105: =SUM(G101:G104) -> 850 | I105: =SUM(I101:I104) -> 0 | J105: =SUM(J101:J104) -> 0 | K105: =SUM(K101:K104) -> 0 | L105: =SUM(L101:L104) -> 0 | M105: =SUM(M101:M104) -> 0 | N105: =SUM(N101:N104) -> 0 | O105: =SUM(O101:O104) -> 0 | P105: =SUM(P101:P104) -> 0
...

Sheet Ago
A2: Fluxo de Caixa Familiar
A5: Categoria | C5: Descrição | D5: Percentual | E5: =I5 -> Agosto | I5: Agosto
E6: Orçado | F6: Realizado | G6: Variação | I6: Semana 1 | J6: Semana 2 | K6: Semana 3 | L6: Semana 4 | M6: Semana 5 | N6: =Jan!N6 -> Cartão Nubank | O6: =Jan!O6 -> Cartão C & A | P6: Total
A7: Receitas | C7: ='Orçamento Familiar'!C7 -> Prebenda | E7: ='Orçamento Familiar'!L7 -> 7216 | F7: =P7 -> 0 | G7: =F7-E7 -> -7216 | P7: =SUM(I7:O7) -> 0
C8: ='Orçamento Familiar'!C8 -> Inglês | E8: ='Orçamento Familiar'!L8 -> 335 | F8: =P8 -> 0 | G8: =F8-E8 -> -335 | P8: =SUM(I8:O8) -> 0
C9: ='Orçamento Familiar'!C9 -> 13º Salário | E9: ='Orçamento Familiar'!L9 -> 0 | F9: =P9 -> 0 | G9: =F9-E9 -> 0 | P9: =SUM(I9:O9) -> 0
C10: ='Orçamento Familiar'!C10 -> Renda Extra | E10: ='Orçamento Familiar'!L10 -> 0 | F10: =P10 -> 0 | G10: =F10-E10 -> 0 | P10: =SUM(I10:O10) -> 0
C11: ='Orçamento Familiar'!C11 -> 0 | E11: ='Orçamento Familiar'!L11 -> 0 | F11: =P11 -> 0 | G11: =F11-E11 -> 0 | P11: =SUM(I11:O11) -> 0
C12: ='Orçamento Familiar'!C12 -> 0 | E12: ='Orçamento Familiar'!L12 -> 0 | F12: =P12 -> 0 | G12: =F12-E12 -> 0 | P12: =SUM(I12:O12) -> 0
C13: ='Orçamento Familiar'!C13 -> 0 | E13: ='Orçamento Familiar'!L13 -> 0 | F13: =P13 -> 0 | G13: =F13-E13 -> 0 | P13: =SUM(I13:O13) -> 0
C14: ='Orçamento Familiar'!C14 -> 0 | E14: ='Orçamento Familiar'!L14 -> 0 | F14: =P14 -> 0 | G14: =F14-E14 -> 0 | P14: =SUM(I14:O14) -> 0
C15: ='Orçamento Familiar'!C15 -> 0 | E15: ='Orçamento Familiar'!L15 -> 0 | F15: =P15 -> 0 | G15: =F15-E15 -> 0 | P15: =SUM(I15:O15) -> 0
C16: Total | E16: =SUM(E7:E15) -> 7551 | F16: =SUM(F7:F15) -> 0 | G16: =SUM(G7:G15) -> -7551 | I16: =SUM(I7:I15) -> 0 | J16: =SUM(J7:J15) -> 0 | K16: =SUM(K7:K15) -> 0 | L16: =SUM(L7:L15) -> 0 | M16: =SUM(M7:M15) -> 0 | N16: =SUM(N7:N15) -> 0 | O16: =SUM(O7:O15) -> 0 | P16: =SUM(P7:P15) -> 0
A18: Investimentos Insira aqui o montante mensal que você destinará aos seus investimentos | C18: Descrição | D18: Percentual | E18: Orçado | F18: Realizado | G18: Variação | I18: =I6 -> Semana 1 | J18: =J6 -> Semana 2 | K18: =K6 -> Semana 3 | L18: =L6 -> Semana 4 | M18: =M6 -> Semana 5 | P18: =P6 -> Total
C19: ='Orçamento Familiar'!C19 -> Reserva de Emergência (CP) R$ 9.151 | E19: ='Orçamento Familiar'!L19 -> 0 | F19: =P19 -> 0 | G19: =F19-E19 -> 0 | P19: =SUM(I19:O19) -> 0
C20: ='Orçamento Familiar'!C20 -> Projeto 1 | E20: ='Orçamento Familiar'!L20 -> 0 | F20: =P20 -> 0 | G20: =F20-E20 -> 0 | P20: =SUM(I20:O20) -> 0
C21: ='Orçamento Familiar'!C21 -> Projeto 2 | E21: ='Orçamento Familiar'!L21 -> 0 | F21: =P21 -> 0 | G21: =F21-E21 -> 0 | P21: =SUM(I21:O21) -> 0
C22: ='Orçamento Familiar'!C22 -> Projeto 3 | E22: ='Orçamento Familiar'!L22 -> 0 | F22: =P22 -> 0 | G22: =F22-E22 -> 0 | P22: =SUM(I22:O22) -> 0
C23: ='Orçamento Familiar'!C23 -> Projeto 4 | E23: ='Orçamento Familiar'!L23 -> 0 | F23: =P23 -> 0 | G23: =F23-E23 -> 0 | P23: =SUM(I23:O23) -> 0
C24: ='Orçamento Familiar'!C24 -> Projeto 5 | E24: ='Orçamento Familiar'!L24 -> 0 | F24: =P24 -> 0 | G24: =F24-E24 -> 0 | P24: =SUM(I24:O24) -> 0
C25: ='Orçamento Familiar'!C25 -> Projeto 6 | E25: ='Orçamento Familiar'!L25 -> 0 | F25: =P25 -> 0 | G25: =F25-E25 -> 0 | P25: =SUM(I25:O25) -> 0
C26: ='Orçamento Familiar'!C26 -> Independência Financeira | E26: ='Orçamento Familiar'!L26 -> 0 | F26: =P26 -> 0 | G26: =F26-E26 -> 0 | P26: =SUM(I26:O26) -> 0
C27: Total Investimentos | D27: =SUM(D19:D26) -> 0 | E27: =SUM(E19:E26) -> 0 | F27: =SUM(F19:F26) -> 0 | G27: =SUM(G19:G26) -> 0 | I27: =SUM(I19:I26) -> 0 | J27: =SUM(J19:J26) -> 0 | K27: =SUM(K19:K26) -> 0 | L27: =SUM(L19:L26) -> 0 | M27: =SUM(M19:M26) -> 0 | N27: =SUM(N19:N26) -> 0 | O27: =SUM(O19:O26) -> 0 | P27: =SUM(P19:P26) -> 0
C28: % sobre Receita | E28: =E27/E16 -> 0 | F28: =F27/F16 -> #DIV/0! | I28: =I27/I16 -> #DIV/0! | J28: =J27/J16 -> #DIV/0! | K28: =K27/K16 -> #DIV/0! | L28: =L27/L16 -> #DIV/0! | M28: =M27/M16 -> #DIV/0! | N28: =N27/N16 -> #DIV/0! | O28: =O27/O16 -> #DIV/0! | P28: =P27/P16 -> #DIV/0!
A30: Categoria | C30: Descrição | D30: Percentual | E30: Orçado | F30: Realizado | G30: Variação | I30: =I18 -> Semana 1 | J30: =J18 -> Semana 2 | K30: =K18 -> Semana 3 | L30: =L18 -> Semana 4 | M30: =M18 -> Semana 5 | N30: =N6 -> Cartão Nubank | O30: =O6 -> Cartão C & A | P30: =P18 -> Total
A31: Despesas Essenciais | B31: Moradia | C31: ='Orçamento Familiar'!C31 -> Aluguel | E31: ='Orçamento Familiar'!L31 -> 0 | F31: =P31 -> 0 | G31: =E31-F31 -> 0 | P31: =SUM(I31:O31) -> 0
C32: ='Orçamento Familiar'!C32 -> Energia Elétrica | E32: ='Orçamento Familiar'!L32 -> 0 | F32: =P32 -> 0 | G32: =E32-F32 -> 0 | P32: =SUM(I32:O32) -> 0
C33: ='Orçamento Familiar'!C33 -> Água e Esgoto | E33: ='Orçamento Familiar'!L33 -> 0 | F33: =P33 -> 0 | G33: =E33-F33 -> 0 | P33: =SUM(I33:O33) -> 0
C34: ='Orçamento Familiar'!C34 -> Gás | E34: ='Orçamento Familiar'!L34 -> 0 | F34: =P34 -> 0 | G34: =E34-F34 -> 0 | P34: =SUM(I34:O34) -> 0
C35: ='Orçamento Familiar'!C35 -> Internet e Celular | E35: ='Orçamento Familiar'!L35 -> 184.7 | F35: =P35 -> 0 | G35: =E35-F35 -> 184.7 | P35: =SUM(I35:O35) -> 0
C36: ='Orçamento Familiar'!C36 -> Manutenção | E36: ='Orçamento Familiar'!L36 -> 50 | F36: =P36 -> 0 | G36: =E36-F36 -> 50 | P36: =SUM(I36:O36) -> 0
C37: ='Orçamento Familiar'!C37 -> 0 | E37: ='Orçamento Familiar'!L37 -> 0 | F37: =P37 -> 0 | G37: =E37-F37 -> 0 | P37: =SUM(I37:O37) -> 0
C38: ='Orçamento Familiar'!C38 -> 0 | E38: ='Orçamento Familiar'!L38 -> 0 | F38: =P38 -> 0 | G38: =E38-F38 -> 0 | P38: =SUM(I38:O38) -> 0
C39: ='Orçamento Familiar'!C39 -> 0 | E39: ='Orçamento Familiar'!L39 -> 0 | F39: =P39 -> 0 | G39: =E39-F39 -> 0 | P39: =SUM(I39:O39) -> 0
B40: Alimentação | C40: ='Orçamento Familiar'!C40 -> Supermercado | E40: ='Orçamento Familiar'!L40 -> 3100 | F40: =P40 -> 0 | G40: =E40-F40 -> 3100 | P40: =SUM(I40:O40) -> 0
C41: ='Orçamento Familiar'!C41 -> 0 | E41: ='Orçamento Familiar'!L41 -> 0 | F41: =P41 -> 0 | G41: =E41-F41 -> 0 | P41: =SUM(I41:O41) -> 0
C42: ='Orçamento Familiar'!C42 -> 0 | E42: ='Orçamento Familiar'!L42 -> 0 | F42: =P42 -> 0 | G42: =E42-F42 -> 0 | P42: =SUM(I42:O42) -> 0
C43: ='Orçamento Familiar'!C43 -> 0 | E43: ='Orçamento Familiar'!L43 -> 0 | F43: =P43 -> 0 | G43: =E43-F43 -> 0 | P43: =SUM(I43:O43) -> 0
C44: ='Orçamento Familiar'!C44 -> 0 | E44: ='Orçamento Familiar'!L44 -> 0 | F44: =P44 -> 0 | G44: =E44-F44 -> 0 | P44: =SUM(I44:O44) -> 0
C45: ='Orçamento Familiar'!C45 -> 0 | E45: ='Orçamento Familiar'!L45 -> 0 | F45: =P45 -> 0 | G45: =E45-F45 -> 0 | P45: =SUM(I45:O45) -> 0
B46: Transporte | C46: ='Orçamento Familiar'!C46 -> Combustível | E46: ='Orçamento Familiar'!L46 -> 400 | F46: =P46 -> 0 | G46: =E46-F46 -> 400 | P46: =SUM(I46:O46) -> 0
C47: ='Orçamento Familiar'!C47 -> Manutenção | E47: ='Orçamento Familiar'!L47 -> 0 | F47: =P47 -> 0 | G47: =E47-F47 -> 0 | P47: =SUM(I47:O47) -> 0
C48: ='Orçamento Familiar'!C48 -> Multas | E48: ='Orçamento Familiar'!L48 -> 0 | F48: =P48 -> 0 | G48: =E48-F48 -> 0 | P48: =SUM(I48:O48) -> 0
C49: ='Orçamento Familiar'!C49 -> Seguro | E49: ='Orçamento Familiar'!L49 -> 0 | F49: =P49 -> 0 | G49: =E49-F49 -> 0 | P49: =SUM(I49:O49) -> 0
C50: ='Orçamento Familiar'!C50 -> Lavagem | E50: ='Orçamento Familiar'!L50 -> 0 | F50: =P50 -> 0 | G50: =E50-F50 -> 0 | P50: =SUM(I50:O50) -> 0
C51: ='Orçamento Familiar'!C51 -> Estacionamento | E51: ='Orçamento Familiar'!L51 -> 0 | F51: =P51 -> 0 | G51: =E51-F51 -> 0 | P51: =SUM(I51:O51) -> 0
C52: ='Orçamento Familiar'!C52 -> Taxi / Uber | E52: ='Orçamento Familiar'!L52 -> 0 | F52: =P52 -> 0 | G52: =E52-F52 -> 0 | P52: =SUM(I52:O52) -> 0
C53: ='Orçamento Familiar'!C53 -> 0 | E53: ='Orçamento Familiar'!L53 -> 0 | F53: =P53 -> 0 | G53: =E53-F53 -> 0 | P53: =SUM(I53:O53) -> 0
C54: ='Orçamento Familiar'!C54 -> 0 | E54: ='Orçamento Familiar'!L54 -> 0 | F54: =P54 -> 0 | G54: =E54-F54 -> 0 | P54: =SUM(I54:O54) -> 0
B55: Saúde | C55: ='Orçamento Familiar'!C55 -> Medicamentos | E55: ='Orçamento Familiar'!L55 -> 80 | F55: =P55 -> 0 | G55: =E55-F55 -> 80 | P55: =SUM(I55:O55) -> 0
C56: ='Orçamento Familiar'!C56 -> Médicos / Exames | E56: ='Orçamento Familiar'!L56 -> 0 | F56: =P56 -> 0 | G56: =E56-F56 -> 0 | P56: =SUM(I56:O56) -> 0
C57: ='Orçamento Familiar'!C57 -> Dentista | E57: ='Orçamento Familiar'!L57 -> 0 | F57: =P57 -> 0 | G57: =E57-F57 -> 0 | P57: =SUM(I57:O57) -> 0
C58: ='Orçamento Familiar'!C58 -> 0 | E58: ='Orçamento Familiar'!L58 -> 0 | F58: =P58 -> 0 | G58: =E58-F58 -> 0 | P58: =SUM(I58:O58) -> 0
C59: ='Orçamento Familiar'!C59 -> 0 | E59: ='Orçamento Familiar'!L59 -> 0 | F59: =P59 -> 0 | G59: =E59-F59 -> 0 | P59: =SUM(I59:O59) -> 0
B60: Impostos | C60: ='Orçamento Familiar'!C60 -> IPVA | E60: ='Orçamento Familiar'!L60 -> 0 | F60: =P60 -> 0 | G60: =E60-F60 -> 0 | P60: =SUM(I60:O60) -> 0
C61: ='Orçamento Familiar'!C61 -> Licenciamento | E61: ='Orçamento Familiar'!L61 -> 0 | F61: =P61 -> 0 | G61: =E61-F61 -> 0 | P61: =SUM(I61:O61) -> 0
C62: ='Orçamento Familiar'!C62 -> Imposto de Renda | E62: ='Orçamento Familiar'!L62 -> 0 | F62: =P62 -> 0 | G62: =E62-F62 -> 0 | P62: =SUM(I62:O62) -> 0
C63: ='Orçamento Familiar'!C63 -> INSS | E63: ='Orçamento Familiar'!L63 -> 0 | F63: =P63 -> 0 | G63: =E63-F63 -> 0 | P63: =SUM(I63:O63) -> 0
C64: ='Orçamento Familiar'!C64 -> 0 | E64: ='Orçamento Familiar'!L64 -> 0 | F64: =P64 -> 0 | G64: =E64-F64 -> 0 | P64: =SUM(I64:O64) -> 0
C65: ='Orçamento Familiar'!C65 -> 0 | E65: ='Orçamento Familiar'!L65 -> 0 | F65: =P65 -> 0 | G65: =E65-F65 -> 0 | P65: =SUM(I65:O65) -> 0
B66: Educação | C66: ='Orçamento Familiar'!C66 -> Especialização | E66: ='Orçamento Familiar'!L66 -> 0 | F66: =P66 -> 0 | G66: =E66-F66 -> 0 | P66: =SUM(I66:O66) -> 0
C67: ='Orçamento Familiar'!C67 -> Cursos | E67: ='Orçamento Familiar'!L67 -> 150 | F67: =P67 -> 146.83 | G67: =E67-F67 -> 3.17 | N67: 146.83 | P67: =SUM(I67:O67) -> 146.83 | Q67: Faculdade Con 6/6=146,83
C68: ='Orçamento Familiar'!C68 -> Mentoria Financeira | E68: ='Orçamento Familiar'!L68 -> 225 | F68: =P68 -> 0 | G68: =E68-F68 -> 225 | P68: =SUM(I68:O68) -> 0
C69: ='Orçamento Familiar'!C69 -> 0 | E69: ='Orçamento Familiar'!L69 -> 0 | F69: =P69 -> 0 | G69: =E69-F69 -> 0 | P69: =SUM(I69:O69) -> 0
C70: ='Orçamento Familiar'!C70 -> 0 | E70: ='Orçamento Familiar'!L70 -> 0 | F70: =P70 -> 0 | G70: =E70-F70 -> 0 | P70: =SUM(I70:O70) -> 0
B71: Filhos | C71: ='Orçamento Familiar'!C71 -> Piano Laura | E71: ='Orçamento Familiar'!L71 -> 0 | F71: =P71 -> 0 | G71: =E71-F71 -> 0 | P71: =SUM(I71:O71) -> 0
C72: ='Orçamento Familiar'!C72 -> Material Escolar | E72: ='Orçamento Familiar'!L72 -> 0 | F72: =P72 -> 0 | G72: =E72-F72 -> 0 | P72: =SUM(I72:O72) -> 0
C73: ='Orçamento Familiar'!C73 -> Mesadas | E73: ='Orçamento Familiar'!L73 -> 120 | F73: =P73 -> 0 | G73: =E73-F73 -> 120 | P73: =SUM(I73:O73) -> 0
C74: ='Orçamento Familiar'!C74 -> Violão | E74: ='Orçamento Familiar'!L74 -> 0 | F74: =P74 -> 0 | G74: =E74-F74 -> 0 | P74: =SUM(I74:O74) -> 0
C75: ='Orçamento Familiar'!C75 -> Médicos / Exames | E75: ='Orçamento Familiar'!L75 -> 0 | F75: =P75 -> 0 | G75: =E75-F75 -> 0 | P75: =SUM(I75:O75) -> 0
C76: ='Orçamento Familiar'!C76 -> Cursos | E76: ='Orçamento Familiar'!L76 -> 0 | F76: =P76 -> 0 | G76: =E76-F76 -> 0 | P76: =SUM(I76:O76) -> 0
C77: ='Orçamento Familiar'!C77 -> Retiro Carnaval 2026/2027 | E77: ='Orçamento Familiar'!L77 -> 240 | F77: =P77 -> 0 | G77: =E77-F77 -> 240 | P77: =SUM(I77:O77) -> 0
C78: ='Orçamento Familiar'!C78 -> Acampadentro | E78: ='Orçamento Familiar'!L78 -> 0 | F78: =P78 -> 0 | G78: =E78-F78 -> 0 | P78: =SUM(I78:O78) -> 0
C79: ='Orçamento Familiar'!C79 -> 0 | E79: ='Orçamento Familiar'!L79 -> 0 | F79: =P79 -> 0 | G79: =E79-F79 -> 0 | P79: =SUM(I79:O79) -> 0
B80: Pet | C80: ='Orçamento Familiar'!C80 -> Ração | E80: ='Orçamento Familiar'!L80 -> 50 | F80: =P80 -> 0 | G80: =E80-F80 -> 50 | P80: =SUM(I80:O80) -> 0
C81: ='Orçamento Familiar'!C81 -> Vacinas | E81: ='Orçamento Familiar'!L81 -> 0 | F81: =P81 -> 0 | G81: =E81-F81 -> 0 | P81: =SUM(I81:O81) -> 0
C82: ='Orçamento Familiar'!C82 -> Veterinário | E82: ='Orçamento Familiar'!L82 -> 0 | F82: =P82 -> 0 | G82: =E82-F82 -> 0 | P82: =SUM(I82:O82) -> 0
C83: ='Orçamento Familiar'!C83 -> 0 | E83: ='Orçamento Familiar'!L83 -> 0 | F83: =P83 -> 0 | G83: =E83-F83 -> 0 | P83: =SUM(I83:O83) -> 0
C84: ='Orçamento Familiar'!C84 -> 0 | E84: ='Orçamento Familiar'!L84 -> 0 | F84: =P84 -> 0 | G84: =E84-F84 -> 0 | P84: =SUM(I84:O84) -> 0
B85: Total Despesas Essenciais | E85: =SUM(E31:E84) -> 4599.7 | F85: =SUM(F31:F84) -> 146.83 | G85: =SUM(G31:G84) -> 4452.87 | I85: =SUM(I31:I84) -> 0 | J85: =SUM(J31:J84) -> 0 | K85: =SUM(K31:K84) -> 0 | L85: =SUM(L31:L84) -> 0 | M85: =SUM(M31:M84) -> 0 | N85: =SUM(N31:N84) -> 146.83 | O85: =SUM(O31:O84) -> 0 | P85: =SUM(P31:P84) -> 146.83
B86: % sobre Receita | C86: ='Orçamento Familiar'!C166 -> 0 | E86: =E85/E16 -> 0.60915111 | F86: =F85/F16 -> #DIV/0! | I86: =I85/I16 -> #DIV/0! | J86: =J85/J16 -> #DIV/0! | K86: =K85/K16 -> #DIV/0! | L86: =L85/L16 -> #DIV/0! | M86: =M85/M16 -> #DIV/0! | N86: =N85/N16 -> #DIV/0! | O86: =O85/O16 -> #DIV/0! | P86: =P85/P16 -> #DIV/0!
A87: Profissional e Trabalho | B87: Ministério | C87: ='Orçamento Familiar'!C87 -> Materiais (livros) | E87: ='Orçamento Familiar'!L87 -> 30 | F87: =P87 -> 0 | G87: =E87-F87 -> 30 | P87: =SUM(I87:O87) -> 0
C88: ='Orçamento Familiar'!C88 -> 0 | E88: ='Orçamento Familiar'!L88 -> 0 | F88: =P88 -> 0 | G88: =E88-F88 -> 0 | P88: =SUM(I88:O88) -> 0
C89: ='Orçamento Familiar'!C89 -> 0 | E89: ='Orçamento Familiar'!L89 -> 0 | F89: =P89 -> 0 | G89: =E89-F89 -> 0 | P89: =SUM(I89:O89) -> 0
C90: ='Orçamento Familiar'!C90 -> 0 | E90: ='Orçamento Familiar'!L90 -> 0 | F90: =P90 -> 0 | G90: =E90-F90 -> 0 | P90: =SUM(I90:O90) -> 0
C91: ='Orçamento Familiar'!C91 -> 0 | E91: ='Orçamento Familiar'!L91 -> 0 | F91: =P91 -> 0 | G91: =E91-F91 -> 0 | P91: =SUM(I91:O91) -> 0
C92: ='Orçamento Familiar'!C92 -> 0 | E92: ='Orçamento Familiar'!L92 -> 0 | F92: =P92 -> 0 | G92: =E92-F92 -> 0 | P92: =SUM(I92:O92) -> 0
B93: Autônomo | C93: ='Orçamento Familiar'!C93 -> Ferramentas de trabalho | E93: ='Orçamento Familiar'!L93 -> 150 | F93: =P93 -> 0 | G93: =E93-F93 -> 150 | P93: =SUM(I93:O93) -> 0
C94: ='Orçamento Familiar'!C94 -> Colaboradores | E94: ='Orçamento Familiar'!L94 -> 0 | F94: =P94 -> 0 | G94: =E94-F94 -> 0 | P94: =SUM(I94:O94) -> 0
C95: ='Orçamento Familiar'!C95 -> 0 | E95: ='Orçamento Familiar'!L95 -> 0 | F95: =P95 -> 0 | G95: =E95-F95 -> 0 | P95: =SUM(I95:O95) -> 0
C96: ='Orçamento Familiar'!C96 -> 0 | E96: ='Orçamento Familiar'!L96 -> 0 | F96: =P96 -> 0 | G96: =E96-F96 -> 0 | P96: =SUM(I96:O96) -> 0
C97: ='Orçamento Familiar'!C97 -> 0 | E97: ='Orçamento Familiar'!L97 -> 0 | F97: =P97 -> 0 | G97: =E97-F97 -> 0 | P97: =SUM(I97:O97) -> 0
C98: ='Orçamento Familiar'!C98 -> 0 | E98: ='Orçamento Familiar'!L98 -> 0 | F98: =P98 -> 0 | G98: =E98-F98 -> 0 | P98: =SUM(I98:O98) -> 0
B99: Total Profissional e Trabalho | E99: =SUM(E87:E98) -> 180 | F99: =SUM(F87:F98) -> 0 | G99: =SUM(G87:G98) -> 180 | I99: =SUM(I87:I98) -> 0 | J99: =SUM(J87:J98) -> 0 | K99: =SUM(K87:K98) -> 0 | L99: =SUM(L87:L98) -> 0 | M99: =SUM(M87:M98) -> 0 | N99: =SUM(N87:N98) -> 0 | O99: =SUM(O87:O98) -> 0 | P99: =SUM(P87:P98) -> 0
B100: % sobre Receita | E100: =E99/E16 -> 0.023837902 | F100: =F99/F16 -> #DIV/0! | I100: =I99/I16 -> #DIV/0! | J100: =J99/J16 -> #DIV/0! | K100: =K99/K16 -> #DIV/0! | L100: =L99/L16 -> #DIV/0! | M100: =M99/M16 -> #DIV/0! | N100: =N99/N16 -> #DIV/0! | O100: =O99/O16 -> #DIV/0! | P100: =P99/P16 -> #DIV/0!
A101: Contribuição | B101: Ofertas | C101: ='Orçamento Familiar'!C101 -> Dízimo | E101: ='Orçamento Familiar'!L101 -> 850 | F101: =P101 -> 0 | G101: =E101-F101 -> 850 | P101: =SUM(I101:O101) -> 0
C102: ='Orçamento Familiar'!C102 -> Sacrificial | E102: ='Orçamento Familiar'!L102 -> 0 | F102: =P102 -> 0 | G102: =E102-F102 -> 0 | P102: =SUM(I102:O102) -> 0
C103: ='Orçamento Familiar'!C103 -> Doações | E103: ='Orçamento Familiar'!L103 -> 0 | F103: =P103 -> 0 | G103: =E103-F103 -> 0 | P103: =SUM(I103:O103) -> 0
C104: ='Orçamento Familiar'!C104 -> 0 | E104: ='Orçamento Familiar'!L104 -> 0 | F104: =P104 -> 0 | G104: =E104-F104 -> 0 | P104: =SUM(I104:O104) -> 0
B105: Total Contribuição | E105: =SUM(E101:E104) -> 850 | F105: =SUM(F101:F104) -> 0 | G105: =SUM(G101:G104) -> 850 | I105: =SUM(I101:I104) -> 0 | J105: =SUM(J101:J104) -> 0 | K105: =SUM(K101:K104) -> 0 | L105: =SUM(L101:L104) -> 0 | M105: =SUM(M101:M104) -> 0 | N105: =SUM(N101:N104) -> 0 | O105: =SUM(O101:O104) -> 0 | P105: =SUM(P101:P104) -> 0
...

Sheet Set
A2: Fluxo de Caixa Familiar
A5: Categoria | C5: Descrição | D5: Percentual | E5: =I5 -> Setembro | I5: Setembro
E6: Orçado | F6: Realizado | G6: Variação | I6: Semana 1 | J6: Semana 2 | K6: Semana 3 | L6: Semana 4 | M6: Semana 5 | N6: =Jan!N6 -> Cartão Nubank | O6: =Jan!O6 -> Cartão C & A | P6: Total
A7: Receitas | C7: ='Orçamento Familiar'!C7 -> Prebenda | E7: ='Orçamento Familiar'!M7 -> 7216 | F7: =P7 -> 0 | G7: =F7-E7 -> -7216 | P7: =SUM(I7:O7) -> 0
C8: ='Orçamento Familiar'!C8 -> Inglês | E8: ='Orçamento Familiar'!M8 -> 335 | F8: =P8 -> 0 | G8: =F8-E8 -> -335 | P8: =SUM(I8:O8) -> 0
C9: ='Orçamento Familiar'!C9 -> 13º Salário | E9: ='Orçamento Familiar'!M9 -> 0 | F9: =P9 -> 0 | G9: =F9-E9 -> 0 | P9: =SUM(I9:O9) -> 0
C10: ='Orçamento Familiar'!C10 -> Renda Extra | E10: ='Orçamento Familiar'!M10 -> 0 | F10: =P10 -> 0 | G10: =F10-E10 -> 0 | P10: =SUM(I10:O10) -> 0
C11: ='Orçamento Familiar'!C11 -> 0 | E11: ='Orçamento Familiar'!M11 -> 0 | F11: =P11 -> 0 | G11: =F11-E11 -> 0 | P11: =SUM(I11:O11) -> 0
C12: ='Orçamento Familiar'!C12 -> 0 | E12: ='Orçamento Familiar'!M12 -> 0 | F12: =P12 -> 0 | G12: =F12-E12 -> 0 | P12: =SUM(I12:O12) -> 0
C13: ='Orçamento Familiar'!C13 -> 0 | E13: ='Orçamento Familiar'!M13 -> 0 | F13: =P13 -> 0 | G13: =F13-E13 -> 0 | P13: =SUM(I13:O13) -> 0
C14: ='Orçamento Familiar'!C14 -> 0 | E14: ='Orçamento Familiar'!M14 -> 0 | F14: =P14 -> 0 | G14: =F14-E14 -> 0 | P14: =SUM(I14:O14) -> 0
C15: ='Orçamento Familiar'!C15 -> 0 | E15: ='Orçamento Familiar'!M15 -> 0 | F15: =P15 -> 0 | G15: =F15-E15 -> 0 | P15: =SUM(I15:O15) -> 0
C16: Total | E16: =SUM(E7:E15) -> 7551 | F16: =SUM(F7:F15) -> 0 | G16: =SUM(G7:G15) -> -7551 | I16: =SUM(I7:I15) -> 0 | J16: =SUM(J7:J15) -> 0 | K16: =SUM(K7:K15) -> 0 | L16: =SUM(L7:L15) -> 0 | M16: =SUM(M7:M15) -> 0 | N16: =SUM(N7:N15) -> 0 | O16: =SUM(O7:O15) -> 0 | P16: =SUM(P7:P15) -> 0
A18: Investimentos Insira aqui o montante mensal que você destinará aos seus investimentos | C18: Descrição | D18: Percentual | E18: Orçado | F18: Realizado | G18: Variação | I18: =I6 -> Semana 1 | J18: =J6 -> Semana 2 | K18: =K6 -> Semana 3 | L18: =L6 -> Semana 4 | M18: =M6 -> Semana 5 | P18: =P6 -> Total
C19: ='Orçamento Familiar'!C19 -> Reserva de Emergência (CP) R$ 9.151 | E19: ='Orçamento Familiar'!M19 -> 0 | F19: =P19 -> 0 | G19: =F19-E19 -> 0 | I19: =I16*$D$19 -> 0 | J19: =J16*$D$19 -> 0 | K19: =K16*$D$19 -> 0 | L19: =L16*$D$19 -> 0 | M19: =M16*$D$19 -> 0 | N19: =N16*$D$19 -> 0 | O19: =O16*$D$19 -> 0 | P19: =SUM(I19:O19) -> 0
C20: ='Orçamento Familiar'!C20 -> Projeto 1 | E20: ='Orçamento Familiar'!M20 -> 0 | F20: =P20 -> 0 | G20: =F20-E20 -> 0 | P20: =SUM(I20:O20) -> 0
C21: ='Orçamento Familiar'!C21 -> Projeto 2 | E21: ='Orçamento Familiar'!M21 -> 0 | F21: =P21 -> 0 | G21: =F21-E21 -> 0 | P21: =SUM(I21:O21) -> 0
C22: ='Orçamento Familiar'!C22 -> Projeto 3 | E22: ='Orçamento Familiar'!M22 -> 0 | F22: =P22 -> 0 | G22: =F22-E22 -> 0 | P22: =SUM(I22:O22) -> 0
C23: ='Orçamento Familiar'!C23 -> Projeto 4 | E23: ='Orçamento Familiar'!M23 -> 0 | F23: =P23 -> 0 | G23: =F23-E23 -> 0 | P23: =SUM(I23:O23) -> 0
C24: ='Orçamento Familiar'!C24 -> Projeto 5 | E24: ='Orçamento Familiar'!M24 -> 0 | F24: =P24 -> 0 | G24: =F24-E24 -> 0 | P24: =SUM(I24:O24) -> 0
C25: ='Orçamento Familiar'!C25 -> Projeto 6 | E25: ='Orçamento Familiar'!M25 -> 0 | F25: =P25 -> 0 | G25: =F25-E25 -> 0 | P25: =SUM(I25:O25) -> 0
C26: ='Orçamento Familiar'!C26 -> Independência Financeira | E26: ='Orçamento Familiar'!M26 -> 0 | F26: =P26 -> 0 | G26: =F26-E26 -> 0 | P26: =SUM(I26:O26) -> 0
C27: Total Investimentos | D27: =SUM(D19:D26) -> 0 | E27: =SUM(E19:E26) -> 0 | F27: =SUM(F19:F26) -> 0 | G27: =SUM(G19:G26) -> 0 | I27: =SUM(I19:I26) -> 0 | J27: =SUM(J19:J26) -> 0 | K27: =SUM(K19:K26) -> 0 | L27: =SUM(L19:L26) -> 0 | M27: =SUM(M19:M26) -> 0 | N27: =SUM(N19:N26) -> 0 | O27: =SUM(O19:O26) -> 0 | P27: =SUM(P19:P26) -> 0
C28: % sobre Receita | E28: =E27/E16 -> 0 | F28: =F27/F16 -> #DIV/0! | I28: =I27/I16 -> #DIV/0! | J28: =J27/J16 -> #DIV/0! | K28: =K27/K16 -> #DIV/0! | L28: =L27/L16 -> #DIV/0! | M28: =M27/M16 -> #DIV/0! | N28: =N27/N16 -> #DIV/0! | O28: =O27/O16 -> #DIV/0! | P28: =P27/P16 -> #DIV/0!
A30: Categoria | C30: Descrição | D30: Percentual | E30: Orçado | F30: Realizado | G30: Variação | I30: =I18 -> Semana 1 | J30: =J18 -> Semana 2 | K30: =K18 -> Semana 3 | L30: =L18 -> Semana 4 | M30: =M18 -> Semana 5 | N30: =N6 -> Cartão Nubank | O30: =O6 -> Cartão C & A | P30: =P18 -> Total
A31: Despesas Essenciais | B31: Moradia | C31: ='Orçamento Familiar'!C31 -> Aluguel | E31: ='Orçamento Familiar'!M31 -> 0 | F31: =P31 -> 0 | G31: =E31-F31 -> 0 | P31: =SUM(I31:O31) -> 0
C32: ='Orçamento Familiar'!C32 -> Energia Elétrica | E32: ='Orçamento Familiar'!M32 -> 0 | F32: =P32 -> 0 | G32: =E32-F32 -> 0 | P32: =SUM(I32:O32) -> 0
C33: ='Orçamento Familiar'!C33 -> Água e Esgoto | E33: ='Orçamento Familiar'!M33 -> 0 | F33: =P33 -> 0 | G33: =E33-F33 -> 0 | P33: =SUM(I33:O33) -> 0
C34: ='Orçamento Familiar'!C34 -> Gás | E34: ='Orçamento Familiar'!M34 -> 0 | F34: =P34 -> 0 | G34: =E34-F34 -> 0 | P34: =SUM(I34:O34) -> 0
C35: ='Orçamento Familiar'!C35 -> Internet e Celular | E35: ='Orçamento Familiar'!M35 -> 184.7 | F35: =P35 -> 0 | G35: =E35-F35 -> 184.7 | P35: =SUM(I35:O35) -> 0
C36: ='Orçamento Familiar'!C36 -> Manutenção | E36: ='Orçamento Familiar'!M36 -> 50 | F36: =P36 -> 0 | G36: =E36-F36 -> 50 | P36: =SUM(I36:O36) -> 0
C37: ='Orçamento Familiar'!C37 -> 0 | E37: ='Orçamento Familiar'!M37 -> 0 | F37: =P37 -> 0 | G37: =E37-F37 -> 0 | P37: =SUM(I37:O37) -> 0
C38: ='Orçamento Familiar'!C38 -> 0 | E38: ='Orçamento Familiar'!M38 -> 0 | F38: =P38 -> 0 | G38: =E38-F38 -> 0 | P38: =SUM(I38:O38) -> 0
C39: ='Orçamento Familiar'!C39 -> 0 | E39: ='Orçamento Familiar'!M39 -> 0 | F39: =P39 -> 0 | G39: =E39-F39 -> 0 | P39: =SUM(I39:O39) -> 0
B40: Alimentação | C40: ='Orçamento Familiar'!C40 -> Supermercado | E40: ='Orçamento Familiar'!M40 -> 3100 | F40: =P40 -> 0 | G40: =E40-F40 -> 3100 | P40: =SUM(I40:O40) -> 0
C41: ='Orçamento Familiar'!C41 -> 0 | E41: ='Orçamento Familiar'!M41 -> 0 | F41: =P41 -> 0 | G41: =E41-F41 -> 0 | P41: =SUM(I41:O41) -> 0
C42: ='Orçamento Familiar'!C42 -> 0 | E42: ='Orçamento Familiar'!M42 -> 0 | F42: =P42 -> 0 | G42: =E42-F42 -> 0 | P42: =SUM(I42:O42) -> 0
C43: ='Orçamento Familiar'!C43 -> 0 | E43: ='Orçamento Familiar'!M43 -> 0 | F43: =P43 -> 0 | G43: =E43-F43 -> 0 | P43: =SUM(I43:O43) -> 0
C44: ='Orçamento Familiar'!C44 -> 0 | E44: ='Orçamento Familiar'!M44 -> 0 | F44: =P44 -> 0 | G44: =E44-F44 -> 0 | P44: =SUM(I44:O44) -> 0
C45: ='Orçamento Familiar'!C45 -> 0 | E45: ='Orçamento Familiar'!M45 -> 0 | F45: =P45 -> 0 | G45: =E45-F45 -> 0 | P45: =SUM(I45:O45) -> 0
B46: Transporte | C46: ='Orçamento Familiar'!C46 -> Combustível | E46: ='Orçamento Familiar'!M46 -> 400 | F46: =P46 -> 0 | G46: =E46-F46 -> 400 | P46: =SUM(I46:O46) -> 0
C47: ='Orçamento Familiar'!C47 -> Manutenção | E47: ='Orçamento Familiar'!M47 -> 0 | F47: =P47 -> 0 | G47: =E47-F47 -> 0 | P47: =SUM(I47:O47) -> 0
C48: ='Orçamento Familiar'!C48 -> Multas | E48: ='Orçamento Familiar'!M48 -> 0 | F48: =P48 -> 0 | G48: =E48-F48 -> 0 | P48: =SUM(I48:O48) -> 0
C49: ='Orçamento Familiar'!C49 -> Seguro | E49: ='Orçamento Familiar'!M49 -> 0 | F49: =P49 -> 0 | G49: =E49-F49 -> 0 | P49: =SUM(I49:O49) -> 0
C50: ='Orçamento Familiar'!C50 -> Lavagem | E50: ='Orçamento Familiar'!M50 -> 0 | F50: =P50 -> 0 | G50: =E50-F50 -> 0 | P50: =SUM(I50:O50) -> 0
C51: ='Orçamento Familiar'!C51 -> Estacionamento | E51: ='Orçamento Familiar'!M51 -> 0 | F51: =P51 -> 0 | G51: =E51-F51 -> 0 | P51: =SUM(I51:O51) -> 0
C52: ='Orçamento Familiar'!C52 -> Taxi / Uber | E52: ='Orçamento Familiar'!M52 -> 0 | F52: =P52 -> 0 | G52: =E52-F52 -> 0 | P52: =SUM(I52:O52) -> 0
C53: ='Orçamento Familiar'!C53 -> 0 | E53: ='Orçamento Familiar'!M53 -> 0 | F53: =P53 -> 0 | G53: =E53-F53 -> 0 | P53: =SUM(I53:O53) -> 0
C54: ='Orçamento Familiar'!C54 -> 0 | E54: ='Orçamento Familiar'!M54 -> 0 | F54: =P54 -> 0 | G54: =E54-F54 -> 0 | P54: =SUM(I54:O54) -> 0
B55: Saúde | C55: ='Orçamento Familiar'!C55 -> Medicamentos | E55: ='Orçamento Familiar'!M55 -> 80 | F55: =P55 -> 0 | G55: =E55-F55 -> 80 | P55: =SUM(I55:O55) -> 0
C56: ='Orçamento Familiar'!C56 -> Médicos / Exames | E56: ='Orçamento Familiar'!M56 -> 0 | F56: =P56 -> 0 | G56: =E56-F56 -> 0 | P56: =SUM(I56:O56) -> 0
C57: ='Orçamento Familiar'!C57 -> Dentista | E57: ='Orçamento Familiar'!M57 -> 0 | F57: =P57 -> 0 | G57: =E57-F57 -> 0 | P57: =SUM(I57:O57) -> 0
C58: ='Orçamento Familiar'!C58 -> 0 | E58: ='Orçamento Familiar'!M58 -> 0 | F58: =P58 -> 0 | G58: =E58-F58 -> 0 | P58: =SUM(I58:O58) -> 0
C59: ='Orçamento Familiar'!C59 -> 0 | E59: ='Orçamento Familiar'!M59 -> 0 | F59: =P59 -> 0 | G59: =E59-F59 -> 0 | P59: =SUM(I59:O59) -> 0
B60: Impostos | C60: ='Orçamento Familiar'!C60 -> IPVA | E60: ='Orçamento Familiar'!M60 -> 0 | F60: =P60 -> 0 | G60: =E60-F60 -> 0 | P60: =SUM(I60:O60) -> 0
C61: ='Orçamento Familiar'!C61 -> Licenciamento | E61: ='Orçamento Familiar'!M61 -> 0 | F61: =P61 -> 0 | G61: =E61-F61 -> 0 | P61: =SUM(I61:O61) -> 0
C62: ='Orçamento Familiar'!C62 -> Imposto de Renda | E62: ='Orçamento Familiar'!M62 -> 0 | F62: =P62 -> 0 | G62: =E62-F62 -> 0 | P62: =SUM(I62:O62) -> 0
C63: ='Orçamento Familiar'!C63 -> INSS | E63: ='Orçamento Familiar'!M63 -> 0 | F63: =P63 -> 0 | G63: =E63-F63 -> 0 | P63: =SUM(I63:O63) -> 0
C64: ='Orçamento Familiar'!C64 -> 0 | E64: ='Orçamento Familiar'!M64 -> 0 | F64: =P64 -> 0 | G64: =E64-F64 -> 0 | P64: =SUM(I64:O64) -> 0
C65: ='Orçamento Familiar'!C65 -> 0 | E65: ='Orçamento Familiar'!M65 -> 0 | F65: =P65 -> 0 | G65: =E65-F65 -> 0 | P65: =SUM(I65:O65) -> 0
B66: Educação | C66: ='Orçamento Familiar'!C66 -> Especialização | E66: ='Orçamento Familiar'!M66 -> 0 | F66: =P66 -> 0 | G66: =E66-F66 -> 0 | P66: =SUM(I66:O66) -> 0
C67: ='Orçamento Familiar'!C67 -> Cursos | E67: ='Orçamento Familiar'!M67 -> 0 | F67: =P67 -> 0 | G67: =E67-F67 -> 0 | P67: =SUM(I67:O67) -> 0
C68: ='Orçamento Familiar'!C68 -> Mentoria Financeira | E68: ='Orçamento Familiar'!M68 -> 225 | F68: =P68 -> 0 | G68: =E68-F68 -> 225 | P68: =SUM(I68:O68) -> 0
C69: ='Orçamento Familiar'!C69 -> 0 | E69: ='Orçamento Familiar'!M69 -> 0 | F69: =P69 -> 0 | G69: =E69-F69 -> 0 | P69: =SUM(I69:O69) -> 0
C70: ='Orçamento Familiar'!C70 -> 0 | E70: ='Orçamento Familiar'!M70 -> 0 | F70: =P70 -> 0 | G70: =E70-F70 -> 0 | P70: =SUM(I70:O70) -> 0
B71: Filhos | C71: ='Orçamento Familiar'!C71 -> Piano Laura | E71: ='Orçamento Familiar'!M71 -> 0 | F71: =P71 -> 0 | G71: =E71-F71 -> 0 | P71: =SUM(I71:O71) -> 0
C72: ='Orçamento Familiar'!C72 -> Material Escolar | E72: ='Orçamento Familiar'!M72 -> 0 | F72: =P72 -> 0 | G72: =E72-F72 -> 0 | P72: =SUM(I72:O72) -> 0
C73: ='Orçamento Familiar'!C73 -> Mesadas | E73: ='Orçamento Familiar'!M73 -> 120 | F73: =P73 -> 0 | G73: =E73-F73 -> 120 | P73: =SUM(I73:O73) -> 0
C74: ='Orçamento Familiar'!C74 -> Violão | E74: ='Orçamento Familiar'!M74 -> 0 | F74: =P74 -> 0 | G74: =E74-F74 -> 0 | P74: =SUM(I74:O74) -> 0
C75: ='Orçamento Familiar'!C75 -> Médicos / Exames | E75: ='Orçamento Familiar'!M75 -> 0 | F75: =P75 -> 0 | G75: =E75-F75 -> 0 | P75: =SUM(I75:O75) -> 0
